Workbook

Sheet Q1 2025
A1: Evenement | B1: Artikelnr | C1: Omschrijving | D1: Besteld | E1: Stuksprijs | F1: Brutobedrag | G1: Bruto - Rel.korting | H1: Relatiekorting percentage | I1: Groep | J1: Artikelprijs | K1: Vergelijk | L1: Provisie | M1: Prijstype | N1: Prijs 2 | O1: Brutobedrag 2 | P1: Bruto-Rel. korting 2
A2: 4AM Festival.xls | B2: 5021001 | C2: Stroomaansl. 3kW + WCD + Verbruik 1d | D2: 2 | E2: 154.5 | F2: 309 | G2: 278.1 | H2: 10 | I2: =_xlfn.XLOOKUP(Q1_2025[[#This Row],[Artikelnr]],Artikel_prijzen[Artnr],Artikel_prijzen[Groep],"") -> Elektra | J2: =_xlfn.XLOOKUP(Q1_2025[[#This Row],[Artikelnr]],Artikel_prijzen[Artnr],Artikel_prijzen[Prijs 2025],"") -> 106.8625 | K2: =IF(Q1_2025[[#This Row],[Artikelprijs]]<>"",IF(Q1_2025[[#This Row],[Stuksprijs]]=Q1_2025[[#This Row],[Artikelprijs]],"Prijs gelijk","Prijs wijkt af"),"") -> Prijs wijkt af | M2: Stuksprijs | N2: =IF(Q1_2025[[#This Row],[Prijstype]]="Artikelprijs",Q1_2025[[#This Row],[Artikelprijs]],Q1_2025[[#This Row],[Stuksprijs]]) -> 154.5 | O2: =IF(Q1_2025[[#This Row],[Prijstype]]="Artikelprijs",Q1_2025[[#This Row],[Artikelprijs]] * Q1_2025[[#This Row],[Besteld]],Q1_2025[[#This Row],[Brutobedrag]]) -> 309 | P2: =IF(Q1_2025[[#This Row],[Prijstype]] = "Artikelprijs",Q1_2025[[#This Row],[Brutobedrag 2]]*(100-Q1_2025[[#This Row],[Relatiekorting percentage]])/100,Q1_2025[[#This Row],[Bruto - Rel.korting]]) -> 278.1
A3: 4AM Festival.xls | B3: 5021001 | C3: Stroomaansl. 3kW + WCD + Verbruik 1d | D3: 1 | E3: 154.5 | F3: 154.5 | G3: 139.05 | H3: 10 | I3: =_xlfn.XLOOKUP(Q1_2025[[#This Row],[Artikelnr]],Artikel_prijzen[Artnr],Artikel_prijzen[Groep],"") -> Elektra | J3: =_xlfn.XLOOKUP(Q1_2025[[#This Row],[Artikelnr]],Artikel_prijzen[Artnr],Artikel_prijzen[Prijs 2025],"") -> 106.8625 | K3: =IF(Q1_2025[[#This Row],[Artikelprijs]]<>"",IF(Q1_2025[[#This Row],[Stuksprijs]]=Q1_2025[[#This Row],[Artikelprijs]],"Prijs gelijk","Prijs wijkt af"),"") -> Prijs wijkt af | M3: Stuksprijs | N3: =IF(Q1_2025[[#This Row],[Prijstype]]="Artikelprijs",Q1_2025[[#This Row],[Artikelprijs]],Q1_2025[[#This Row],[Stuksprijs]]) -> 154.5 | O3: =IF(Q1_2025[[#This Row],[Prijstype]]="Artikelprijs",Q1_2025[[#This Row],[Artikelprijs]] * Q1_2025[[#This Row],[Besteld]],Q1_2025[[#This Row],[Brutobedrag]]) -> 154.5 | P3: =IF(Q1_2025[[#This Row],[Prijstype]] = "Artikelprijs",Q1_2025[[#This Row],[Brutobedrag 2]]*(100-Q1_2025[[#This Row],[Relatiekorting percentage]])/100,Q1_2025[[#This Row],[Bruto - Rel.korting]]) -> 139.05
A4: AAO 2025.xls | B4: 5031053 | C4: Prolyte truss H30V 3 meter alu | D4: 34 | E4: 113.3 | F4: 3852.2 | G4: 2696.54 | H4: 30 | I4: =_xlfn.XLOOKUP(Q1_2025[[#This Row],[Artikelnr]],Artikel_prijzen[Artnr],Artikel_prijzen[Groep],"") | J4: =_xlfn.XLOOKUP(Q1_2025[[#This Row],[Artikelnr]],Artikel_prijzen[Artnr],Artikel_prijzen[Prijs 2025],"") | K4: =IF(Q1_2025[[#This Row],[Artikelprijs]]<>"",IF(Q1_2025[[#This Row],[Stuksprijs]]=Q1_2025[[#This Row],[Artikelprijs]],"Prijs gelijk","Prijs wijkt af"),"") | N4: =IF(Q1_2025[[#This Row],[Prijstype]]="Artikelprijs",Q1_2025[[#This Row],[Artikelprijs]],Q1_2025[[#This Row],[Stuksprijs]]) -> 113.3 | O4: =IF(Q1_2025[[#This Row],[Prijstype]]="Artikelprijs",Q1_2025[[#This Row],[Artikelprijs]] * Q1_2025[[#This Row],[Besteld]],Q1_2025[[#This Row],[Brutobedrag]]) -> 3852.2 | P4: =IF(Q1_2025[[#This Row],[Prijstype]] = "Artikelprijs",Q1_2025[[#This Row],[Brutobedrag 2]]*(100-Q1_2025[[#This Row],[Relatiekorting percentage]])/100,Q1_2025[[#This Row],[Bruto - Rel.korting]]) -> 2696.54
A5: AAO 2025.xls | B5: 5031052 | C5: Prolyte truss H30V 2 meter alu | D5: 5 | E5: 88.07 | F5: 440.35 | G5: 308.24 | H5: 30 | I5: =_xlfn.XLOOKUP(Q1_2025[[#This Row],[Artikelnr]],Artikel_prijzen[Artnr],Artikel_prijzen[Groep],"") | J5: =_xlfn.XLOOKUP(Q1_2025[[#This Row],[Artikelnr]],Artikel_prijzen[Artnr],Artikel_prijzen[Prijs 2025],"") | K5: =IF(Q1_2025[[#This Row],[Artikelprijs]]<>"",IF(Q1_2025[[#This Row],[Stuksprijs]]=Q1_2025[[#This Row],[Artikelprijs]],"Prijs gelijk","Prijs wijkt af"),"") | N5: =IF(Q1_2025[[#This Row],[Prijstype]]="Artikelprijs",Q1_2025[[#This Row],[Artikelprijs]],Q1_2025[[#This Row],[Stuksprijs]]) -> 88.07 | O5: =IF(Q1_2025[[#This Row],[Prijstype]]="Artikelprijs",Q1_2025[[#This Row],[Artikelprijs]] * Q1_2025[[#This Row],[Besteld]],Q1_2025[[#This Row],[Brutobedrag]]) -> 440.35 | P5: =IF(Q1_2025[[#This Row],[Prijstype]] = "Artikelprijs",Q1_2025[[#This Row],[Brutobedrag 2]]*(100-Q1_2025[[#This Row],[Relatiekorting percentage]])/100,Q1_2025[[#This Row],[Bruto - Rel.korting]]) -> 308.24
A6: AAO 2025.xls | B6: 5031049 | C6: Prolyte truss H30V 0,5 meter alu | D6: 1 | E6: 35.02 | F6: 35.02 | G6: 24.51 | H6: 30 | I6: =_xlfn.XLOOKUP(Q1_2025[[#This Row],[Artikelnr]],Artikel_prijzen[Artnr],Artikel_prijzen[Groep],"") | J6: =_xlfn.XLOOKUP(Q1_2025[[#This Row],[Artikelnr]],Artikel_prijzen[Artnr],Artikel_prijzen[Prijs 2025],"") | K6: =IF(Q1_2025[[#This Row],[Artikelprijs]]<>"",IF(Q1_2025[[#This Row],[Stuksprijs]]=Q1_2025[[#This Row],[Artikelprijs]],"Prijs gelijk","Prijs wijkt af"),"") | N6: =IF(Q1_2025[[#This Row],[Prijstype]]="Artikelprijs",Q1_2025[[#This Row],[Artikelprijs]],Q1_2025[[#This Row],[Stuksprijs]]) -> 35.02 | O6: =IF(Q1_2025[[#This Row],[Prijstype]]="Artikelprijs",Q1_2025[[#This Row],[Artikelprijs]] * Q1_2025[[#This Row],[Besteld]],Q1_2025[[#This Row],[Brutobedrag]]) -> 35.02 | P6: =IF(Q1_2025[[#This Row],[Prijstype]] = "Artikelprijs",Q1_2025[[#This Row],[Brutobedrag 2]]*(100-Q1_2025[[#This Row],[Relatiekorting percentage]])/100,Q1_2025[[#This Row],[Bruto - Rel.korting]]) -> 24.51
A7: AAO 2025.xls | B7: 5031056 | C7: Prolyte truss H30V Hoek V003 alu | D7: 3 | E7: 69.78 | F7: 209.34 | G7: 146.54 | H7: 30 | I7: =_xlfn.XLOOKUP(Q1_2025[[#This Row],[Artikelnr]],Artikel_prijzen[Artnr],Artikel_prijzen[Groep],"") | J7: =_xlfn.XLOOKUP(Q1_2025[[#This Row],[Artikelnr]],Artikel_prijzen[Artnr],Artikel_prijzen[Prijs 2025],"") | K7: =IF(Q1_2025[[#This Row],[Artikelprijs]]<>"",IF(Q1_2025[[#This Row],[Stuksprijs]]=Q1_2025[[#This Row],[Artikelprijs]],"Prijs gelijk","Prijs wijkt af"),"") | N7: =IF(Q1_2025[[#This Row],[Prijstype]]="Artikelprijs",Q1_2025[[#This Row],[Artikelprijs]],Q1_2025[[#This Row],[Stuksprijs]]) -> 69.78 | O7: =IF(Q1_2025[[#This Row],[Prijstype]]="Artikelprijs",Q1_2025[[#This Row],[Artikelprijs]] * Q1_2025[[#This Row],[Besteld]],Q1_2025[[#This Row],[Brutobedrag]]) -> 209.34 | P7: =IF(Q1_2025[[#This Row],[Prijstype]] = "Artikelprijs",Q1_2025[[#This Row],[Brutobedrag 2]]*(100-Q1_2025[[#This Row],[Relatiekorting percentage]])/100,Q1_2025[[#This Row],[Bruto - Rel.korting]]) -> 146.54
A8: AAO 2025.xls | B8: 5031059 | C8: Prolyte truss H30V Hoek V017 alu | D8: 1 | E8: 69.78 | F8: 69.78 | G8: 48.85 | H8: 30 | I8: =_xlfn.XLOOKUP(Q1_2025[[#This Row],[Artikelnr]],Artikel_prijzen[Artnr],Artikel_prijzen[Groep],"") | J8: =_xlfn.XLOOKUP(Q1_2025[[#This Row],[Artikelnr]],Artikel_prijzen[Artnr],Artikel_prijzen[Prijs 2025],"") | K8: =IF(Q1_2025[[#This Row],[Artikelprijs]]<>"",IF(Q1_2025[[#This Row],[Stuksprijs]]=Q1_2025[[#This Row],[Artikelprijs]],"Prijs gelijk","Prijs wijkt af"),"") | N8: =IF(Q1_2025[[#This Row],[Prijstype]]="Artikelprijs",Q1_2025[[#This Row],[Artikelprijs]],Q1_2025[[#This Row],[Stuksprijs]]) -> 69.78 | O8: =IF(Q1_2025[[#This Row],[Prijstype]]="Artikelprijs",Q1_2025[[#This Row],[Artikelprijs]] * Q1_2025[[#This Row],[Besteld]],Q1_2025[[#This Row],[Brutobedrag]]) -> 69.78 | P8: =IF(Q1_2025[[#This Row],[Prijstype]] = "Artikelprijs",Q1_2025[[#This Row],[Brutobedrag 2]]*(100-Q1_2025[[#This Row],[Relatiekorting percentage]])/100,Q1_2025[[#This Row],[Bruto - Rel.korting]]) -> 48.85
A9: AAO 2025.xls | B9: 5030229 | C9: Motortakel incl. ophangpunt + montage max 250kg | D9: 13 | E9: 303.85 | F9: 3950.05 | G9: 2765.03 | H9: 30 | I9: =_xlfn.XLOOKUP(Q1_2025[[#This Row],[Artikelnr]],Artikel_prijzen[Artnr],Artikel_prijzen[Groep],"") -> Rigging | J9: =_xlfn.XLOOKUP(Q1_2025[[#This Row],[Artikelnr]],Artikel_prijzen[Artnr],Artikel_prijzen[Prijs 2025],"") -> 295 | K9: =IF(Q1_2025[[#This Row],[Artikelprijs]]<>"",IF(Q1_2025[[#This Row],[Stuksprijs]]=Q1_2025[[#This Row],[Artikelprijs]],"Prijs gelijk","Prijs wijkt af"),"") -> Prijs wijkt af | M9: Artikelprijs | N9: =IF(Q1_2025[[#This Row],[Prijstype]]="Artikelprijs",Q1_2025[[#This Row],[Artikelprijs]],Q1_2025[[#This Row],[Stuksprijs]]) -> 295 | O9: =IF(Q1_2025[[#This Row],[Prijstype]]="Artikelprijs",Q1_2025[[#This Row],[Artikelprijs]] * Q1_2025[[#This Row],[Besteld]],Q1_2025[[#This Row],[Brutobedrag]]) -> 3835 | P9: =IF(Q1_2025[[#This Row],[Prijstype]] = "Artikelprijs",Q1_2025[[#This Row],[Brutobedrag 2]]*(100-Q1_2025[[#This Row],[Relatiekorting percentage]])/100,Q1_2025[[#This Row],[Bruto - Rel.korting]]) -> 2684.5
A10: AAO 2025.xls | B10: 3098001 | C10: Floodlight HQI - 2000W Asym. | D10: 20 | E10: 285 | F10: 5700 | G10: 4275 | H10: 25 | I10: =_xlfn.XLOOKUP(Q1_2025[[#This Row],[Artikelnr]],Artikel_prijzen[Artnr],Artikel_prijzen[Groep],"") | J10: =_xlfn.XLOOKUP(Q1_2025[[#This Row],[Artikelnr]],Artikel_prijzen[Artnr],Artikel_prijzen[Prijs 2025],"") | K10: =IF(Q1_2025[[#This Row],[Artikelprijs]]<>"",IF(Q1_2025[[#This Row],[Stuksprijs]]=Q1_2025[[#This Row],[Artikelprijs]],"Prijs gelijk","Prijs wijkt af"),"") | N10: =IF(Q1_2025[[#This Row],[Prijstype]]="Artikelprijs",Q1_2025[[#This Row],[Artikelprijs]],Q1_2025[[#This Row],[Stuksprijs]]) -> 285 | O10: =IF(Q1_2025[[#This Row],[Prijstype]]="Artikelprijs",Q1_2025[[#This Row],[Artikelprijs]] * Q1_2025[[#This Row],[Besteld]],Q1_2025[[#This Row],[Brutobedrag]]) -> 5700 | P10: =IF(Q1_2025[[#This Row],[Prijstype]] = "Artikelprijs",Q1_2025[[#This Row],[Brutobedrag 2]]*(100-Q1_2025[[#This Row],[Relatiekorting percentage]])/100,Q1_2025[[#This Row],[Bruto - Rel.korting]]) -> 4275
A11: AAO 2025.xls | B11: 5030229 | C11: Motortakel incl. ophangpunt + montage max 250kg | D11: 4 | E11: 303.85 | F11: 1215.4 | G11: 850.78 | H11: 30 | I11: =_xlfn.XLOOKUP(Q1_2025[[#This Row],[Artikelnr]],Artikel_prijzen[Artnr],Artikel_prijzen[Groep],"") -> Rigging | J11: =_xlfn.XLOOKUP(Q1_2025[[#This Row],[Artikelnr]],Artikel_prijzen[Artnr],Artikel_prijzen[Prijs 2025],"") -> 295 | K11: =IF(Q1_2025[[#This Row],[Artikelprijs]]<>"",IF(Q1_2025[[#This Row],[Stuksprijs]]=Q1_2025[[#This Row],[Artikelprijs]],"Prijs gelijk","Prijs wijkt af"),"") -> Prijs wijkt af | M11: Artikelprijs | N11: =IF(Q1_2025[[#This Row],[Prijstype]]="Artikelprijs",Q1_2025[[#This Row],[Artikelprijs]],Q1_2025[[#This Row],[Stuksprijs]]) -> 295 | O11: =IF(Q1_2025[[#This Row],[Prijstype]]="Artikelprijs",Q1_2025[[#This Row],[Artikelprijs]] * Q1_2025[[#This Row],[Besteld]],Q1_2025[[#This Row],[Brutobedrag]]) -> 1180 | P11: =IF(Q1_2025[[#This Row],[Prijstype]] = "Artikelprijs",Q1_2025[[#This Row],[Brutobedrag 2]]*(100-Q1_2025[[#This Row],[Relatiekorting percentage]])/100,Q1_2025[[#This Row],[Bruto - Rel.korting]]) -> 826
A12: AAO 2025.xls | B12: 5031053 | C12: Prolyte truss H30V 3 meter alu | D12: 20 | E12: 113.3 | F12: 2266 | G12: 1586.2 | H12: 30 | I12: =_xlfn.XLOOKUP(Q1_2025[[#This Row],[Artikelnr]],Artikel_prijzen[Artnr],Artikel_prijzen[Groep],"") | J12: =_xlfn.XLOOKUP(Q1_2025[[#This Row],[Artikelnr]],Artikel_prijzen[Artnr],Artikel_prijzen[Prijs 2025],"") | K12: =IF(Q1_2025[[#This Row],[Artikelprijs]]<>"",IF(Q1_2025[[#This Row],[Stuksprijs]]=Q1_2025[[#This Row],[Artikelprijs]],"Prijs gelijk","Prijs wijkt af"),"") | N12: =IF(Q1_2025[[#This Row],[Prijstype]]="Artikelprijs",Q1_2025[[#This Row],[Artikelprijs]],Q1_2025[[#This Row],[Stuksprijs]]) -> 113.3 | O12: =IF(Q1_2025[[#This Row],[Prijstype]]="Artikelprijs",Q1_2025[[#This Row],[Artikelprijs]] * Q1_2025[[#This Row],[Besteld]],Q1_2025[[#This Row],[Brutobedrag]]) -> 2266 | P12: =IF(Q1_2025[[#This Row],[Prijstype]] = "Artikelprijs",Q1_2025[[#This Row],[Brutobedrag 2]]*(100-Q1_2025[[#This Row],[Relatiekorting percentage]])/100,Q1_2025[[#This Row],[Bruto - Rel.korting]]) -> 1586.2
A13: AAO 2025.xls | B13: 5031052 | C13: Prolyte truss H30V 2 meter alu | D13: 2 | E13: 88.07 | F13: 176.14 | G13: 123.3 | H13: 30 | I13: =_xlfn.XLOOKUP(Q1_2025[[#This Row],[Artikelnr]],Artikel_prijzen[Artnr],Artikel_prijzen[Groep],"") | J13: =_xlfn.XLOOKUP(Q1_2025[[#This Row],[Artikelnr]],Artikel_prijzen[Artnr],Artikel_prijzen[Prijs 2025],"") | K13: =IF(Q1_2025[[#This Row],[Artikelprijs]]<>"",IF(Q1_2025[[#This Row],[Stuksprijs]]=Q1_2025[[#This Row],[Artikelprijs]],"Prijs gelijk","Prijs wijkt af"),"") | N13: =IF(Q1_2025[[#This Row],[Prijstype]]="Artikelprijs",Q1_2025[[#This Row],[Artikelprijs]],Q1_2025[[#This Row],[Stuksprijs]]) -> 88.07 | O13: =IF(Q1_2025[[#This Row],[Prijstype]]="Artikelprijs",Q1_2025[[#This Row],[Artikelprijs]] * Q1_2025[[#This Row],[Besteld]],Q1_2025[[#This Row],[Brutobedrag]]) -> 176.14 | P13: =IF(Q1_2025[[#This Row],[Prijstype]] = "Artikelprijs",Q1_2025[[#This Row],[Brutobedrag 2]]*(100-Q1_2025[[#This Row],[Relatiekorting percentage]])/100,Q1_2025[[#This Row],[Bruto - Rel.korting]]) -> 123.3
A14: AAO 2025.xls | B14: 5030229 | C14: Motortakel incl. ophangpunt + montage max 250kg | D14: 8 | E14: 303.85 | F14: 2430.8 | G14: 1701.56 | H14: 30 | I14: =_xlfn.XLOOKUP(Q1_2025[[#This Row],[Artikelnr]],Artikel_prijzen[Artnr],Artikel_prijzen[Groep],"") -> Rigging | J14: =_xlfn.XLOOKUP(Q1_2025[[#This Row],[Artikelnr]],Artikel_prijzen[Artnr],Artikel_prijzen[Prijs 2025],"") -> 295 | K14: =IF(Q1_2025[[#This Row],[Artikelprijs]]<>"",IF(Q1_2025[[#This Row],[Stuksprijs]]=Q1_2025[[#This Row],[Artikelprijs]],"Prijs gelijk","Prijs wijkt af"),"") -> Prijs wijkt af | M14: Artikelprijs | N14: =IF(Q1_2025[[#This Row],[Prijstype]]="Artikelprijs",Q1_2025[[#This Row],[Artikelprijs]],Q1_2025[[#This Row],[Stuksprijs]]) -> 295 | O14: =IF(Q1_2025[[#This Row],[Prijstype]]="Artikelprijs",Q1_2025[[#This Row],[Artikelprijs]] * Q1_2025[[#This Row],[Besteld]],Q1_2025[[#This Row],[Brutobedrag]]) -> 2360 | P14: =IF(Q1_2025[[#This Row],[Prijstype]] = "Artikelprijs",Q1_2025[[#This Row],[Brutobedrag 2]]*(100-Q1_2025[[#This Row],[Relatiekorting percentage]])/100,Q1_2025[[#This Row],[Bruto - Rel.korting]]) -> 1652
A15: AAO 2025.xls | B15: 2098001 | C15: Gordijnen 3 x 8 mtr. | D15: 25 | E15: 91 | F15: 2275 | G15: 1592.5 | H15: 30 | I15: =_xlfn.XLOOKUP(Q1_2025[[#This Row],[Artikelnr]],Artikel_prijzen[Artnr],Artikel_prijzen[Groep],"") | J15: =_xlfn.XLOOKUP(Q1_2025[[#This Row],[Artikelnr]],Artikel_prijzen[Artnr],Artikel_prijzen[Prijs 2025],"") | K15: =IF(Q1_2025[[#This Row],[Artikelprijs]]<>"",IF(Q1_2025[[#This Row],[Stuksprijs]]=Q1_2025[[#This Row],[Artikelprijs]],"Prijs gelijk","Prijs wijkt af"),"") | N15: =IF(Q1_2025[[#This Row],[Prijstype]]="Artikelprijs",Q1_2025[[#This Row],[Artikelprijs]],Q1_2025[[#This Row],[Stuksprijs]]) -> 91 | O15: =IF(Q1_2025[[#This Row],[Prijstype]]="Artikelprijs",Q1_2025[[#This Row],[Artikelprijs]] * Q1_2025[[#This Row],[Besteld]],Q1_2025[[#This Row],[Brutobedrag]]) -> 2275 | P15: =IF(Q1_2025[[#This Row],[Prijstype]] = "Artikelprijs",Q1_2025[[#This Row],[Brutobedrag 2]]*(100-Q1_2025[[#This Row],[Relatiekorting percentage]])/100,Q1_2025[[#This Row],[Bruto - Rel.korting]]) -> 1592.5
A16: AAO 2025.xls | B16: 2098001 | C16: Gordijnen 3 x 6 mtr. | D16: 4 | E16: 65 | F16: 260 | G16: 182 | H16: 30 | I16: =_xlfn.XLOOKUP(Q1_2025[[#This Row],[Artikelnr]],Artikel_prijzen[Artnr],Artikel_prijzen[Groep],"") | J16: =_xlfn.XLOOKUP(Q1_2025[[#This Row],[Artikelnr]],Artikel_prijzen[Artnr],Artikel_prijzen[Prijs 2025],"") | K16: =IF(Q1_2025[[#This Row],[Artikelprijs]]<>"",IF(Q1_2025[[#This Row],[Stuksprijs]]=Q1_2025[[#This Row],[Artikelprijs]],"Prijs gelijk","Prijs wijkt af"),"") | N16: =IF(Q1_2025[[#This Row],[Prijstype]]="Artikelprijs",Q1_2025[[#This Row],[Artikelprijs]],Q1_2025[[#This Row],[Stuksprijs]]) -> 65 | O16: =IF(Q1_2025[[#This Row],[Prijstype]]="Artikelprijs",Q1_2025[[#This Row],[Artikelprijs]] * Q1_2025[[#This Row],[Besteld]],Q1_2025[[#This Row],[Brutobedrag]]) -> 260 | P16: =IF(Q1_2025[[#This Row],[Prijstype]] = "Artikelprijs",Q1_2025[[#This Row],[Brutobedrag 2]]*(100-Q1_2025[[#This Row],[Relatiekorting percentage]])/100,Q1_2025[[#This Row],[Bruto - Rel.korting]]) -> 182
A17: AAO 2025.xls | B17: 5301001 | C17: Transport vice versa | D17: 2 | E17: 228 | F17: 456 | G17: 456 | H17: 0 | I17: =_xlfn.XLOOKUP(Q1_2025[[#This Row],[Artikelnr]],Artikel_prijzen[Artnr],Artikel_prijzen[Groep],"") | J17: =_xlfn.XLOOKUP(Q1_2025[[#This Row],[Artikelnr]],Artikel_prijzen[Artnr],Artikel_prijzen[Prijs 2025],"") | K17: =IF(Q1_2025[[#This Row],[Artikelprijs]]<>"",IF(Q1_2025[[#This Row],[Stuksprijs]]=Q1_2025[[#This Row],[Artikelprijs]],"Prijs gelijk","Prijs wijkt af"),"") | N17: =IF(Q1_2025[[#This Row],[Prijstype]]="Artikelprijs",Q1_2025[[#This Row],[Artikelprijs]],Q1_2025[[#This Row],[Stuksprijs]]) -> 228 | O17: =IF(Q1_2025[[#This Row],[Prijstype]]="Artikelprijs",Q1_2025[[#This Row],[Artikelprijs]] * Q1_2025[[#This Row],[Besteld]],Q1_2025[[#This Row],[Brutobedrag]]) -> 456 | P17: =IF(Q1_2025[[#This Row],[Prijstype]] = "Artikelprijs",Q1_2025[[#This Row],[Brutobedrag 2]]*(100-Q1_2025[[#This Row],[Relatiekorting percentage]])/100,Q1_2025[[#This Row],[Bruto - Rel.korting]]) -> 456
A18: AAO 2025.xls | B18: 5031053 | C18: Prolyte truss H30V 3 meter alu | D18: 33 | E18: 113.3 | F18: 3738.9 | G18: 2617.23 | H18: 30 | I18: =_xlfn.XLOOKUP(Q1_2025[[#This Row],[Artikelnr]],Artikel_prijzen[Artnr],Artikel_prijzen[Groep],"") | J18: =_xlfn.XLOOKUP(Q1_2025[[#This Row],[Artikelnr]],Artikel_prijzen[Artnr],Artikel_prijzen[Prijs 2025],"") | K18: =IF(Q1_2025[[#This Row],[Artikelprijs]]<>"",IF(Q1_2025[[#This Row],[Stuksprijs]]=Q1_2025[[#This Row],[Artikelprijs]],"Prijs gelijk","Prijs wijkt af"),"") | N18: =IF(Q1_2025[[#This Row],[Prijstype]]="Artikelprijs",Q1_2025[[#This Row],[Artikelprijs]],Q1_2025[[#This Row],[Stuksprijs]]) -> 113.3 | O18: =IF(Q1_2025[[#This Row],[Prijstype]]="Artikelprijs",Q1_2025[[#This Row],[Artikelprijs]] * Q1_2025[[#This Row],[Besteld]],Q1_2025[[#This Row],[Brutobedrag]]) -> 3738.9 | P18: =IF(Q1_2025[[#This Row],[Prijstype]] = "Artikelprijs",Q1_2025[[#This Row],[Brutobedrag 2]]*(100-Q1_2025[[#This Row],[Relatiekorting percentage]])/100,Q1_2025[[#This Row],[Bruto - Rel.korting]]) -> 2617.23
A19: AAO 2025.xls | B19: 5031052 | C19: Prolyte truss H30V 2 meter alu | D19: 5 | E19: 88.07 | F19: 440.35 | G19: 308.24 | H19: 30 | I19: =_xlfn.XLOOKUP(Q1_2025[[#This Row],[Artikelnr]],Artikel_prijzen[Artnr],Artikel_prijzen[Groep],"") | J19: =_xlfn.XLOOKUP(Q1_2025[[#This Row],[Artikelnr]],Artikel_prijzen[Artnr],Artikel_prijzen[Prijs 2025],"") | K19: =IF(Q1_2025[[#This Row],[Artikelprijs]]<>"",IF(Q1_2025[[#This Row],[Stuksprijs]]=Q1_2025[[#This Row],[Artikelprijs]],"Prijs gelijk","Prijs wijkt af"),"") | N19: =IF(Q1_2025[[#This Row],[Prijstype]]="Artikelprijs",Q1_2025[[#This Row],[Artikelprijs]],Q1_2025[[#This Row],[Stuksprijs]]) -> 88.07 | O19: =IF(Q1_2025[[#This Row],[Prijstype]]="Artikelprijs",Q1_2025[[#This Row],[Artikelprijs]] * Q1_2025[[#This Row],[Besteld]],Q1_2025[[#This Row],[Brutobedrag]]) -> 440.35 | P19: =IF(Q1_2025[[#This Row],[Prijstype]] = "Artikelprijs",Q1_2025[[#This Row],[Brutobedrag 2]]*(100-Q1_2025[[#This Row],[Relatiekorting percentage]])/100,Q1_2025[[#This Row],[Bruto - Rel.korting]]) -> 308.24
A20: AAO 2025.xls | B20: 5031051 | C20: Prolyte truss H30V 1 meter alu | D20: 2 | E20: 52.79 | F20: 105.58 | G20: 73.91 | H20: 30 | I20: =_xlfn.XLOOKUP(Q1_2025[[#This Row],[Artikelnr]],Artikel_prijzen[Artnr],Artikel_prijzen[Groep],"") | J20: =_xlfn.XLOOKUP(Q1_2025[[#This Row],[Artikelnr]],Artikel_prijzen[Artnr],Artikel_prijzen[Prijs 2025],"") | K20: =IF(Q1_2025[[#This Row],[Artikelprijs]]<>"",IF(Q1_2025[[#This Row],[Stuksprijs]]=Q1_2025[[#This Row],[Artikelprijs]],"Prijs gelijk","Prijs wijkt af"),"") | N20: =IF(Q1_2025[[#This Row],[Prijstype]]="Artikelprijs",Q1_2025[[#This Row],[Artikelprijs]],Q1_2025[[#This Row],[Stuksprijs]]) -> 52.79 | O20: =IF(Q1_2025[[#This Row],[Prijstype]]="Artikelprijs",Q1_2025[[#This Row],[Artikelprijs]] * Q1_2025[[#This Row],[Besteld]],Q1_2025[[#This Row],[Brutobedrag]]) -> 105.58 | P20: =IF(Q1_2025[[#This Row],[Prijstype]] = "Artikelprijs",Q1_2025[[#This Row],[Brutobedrag 2]]*(100-Q1_2025[[#This Row],[Relatiekorting percentage]])/100,Q1_2025[[#This Row],[Bruto - Rel.korting]]) -> 73.91
A21: AAO 2025.xls | B21: 5031049 | C21: Prolyte truss H30V 0,5 meter alu | D21: 1 | E21: 35.02 | F21: 35.02 | G21: 24.51 | H21: 30 | I21: =_xlfn.XLOOKUP(Q1_2025[[#This Row],[Artikelnr]],Artikel_prijzen[Artnr],Artikel_prijzen[Groep],"") | J21: =_xlfn.XLOOKUP(Q1_2025[[#This Row],[Artikelnr]],Artikel_prijzen[Artnr],Artikel_prijzen[Prijs 2025],"") | K21: =IF(Q1_2025[[#This Row],[Artikelprijs]]<>"",IF(Q1_2025[[#This Row],[Stuksprijs]]=Q1_2025[[#This Row],[Artikelprijs]],"Prijs gelijk","Prijs wijkt af"),"") | N21: =IF(Q1_2025[[#This Row],[Prijstype]]="Artikelprijs",Q1_2025[[#This Row],[Artikelprijs]],Q1_2025[[#This Row],[Stuksprijs]]) -> 35.02 | O21: =IF(Q1_2025[[#This Row],[Prijstype]]="Artikelprijs",Q1_2025[[#This Row],[Artikelprijs]] * Q1_2025[[#This Row],[Besteld]],Q1_2025[[#This Row],[Brutobedrag]]) -> 35.02 | P21: =IF(Q1_2025[[#This Row],[Prijstype]] = "Artikelprijs",Q1_2025[[#This Row],[Brutobedrag 2]]*(100-Q1_2025[[#This Row],[Relatiekorting percentage]])/100,Q1_2025[[#This Row],[Bruto - Rel.korting]]) -> 24.51
A22: AAO 2025.xls | B22: 5031047 | C22: Prolyte truss H30V 0,29 meter alu | D22: 1 | E22: 35.02 | F22: 35.02 | G22: 24.51 | H22: 30 | I22: =_xlfn.XLOOKUP(Q1_2025[[#This Row],[Artikelnr]],Artikel_prijzen[Artnr],Artikel_prijzen[Groep],"") | J22: =_xlfn.XLOOKUP(Q1_2025[[#This Row],[Artikelnr]],Artikel_prijzen[Artnr],Artikel_prijzen[Prijs 2025],"") | K22: =IF(Q1_2025[[#This Row],[Artikelprijs]]<>"",IF(Q1_2025[[#This Row],[Stuksprijs]]=Q1_2025[[#This Row],[Artikelprijs]],"Prijs gelijk","Prijs wijkt af"),"") | N22: =IF(Q1_2025[[#This Row],[Prijstype]]="Artikelprijs",Q1_2025[[#This Row],[Artikelprijs]],Q1_2025[[#This Row],[Stuksprijs]]) -> 35.02 | O22: =IF(Q1_2025[[#This Row],[Prijstype]]="Artikelprijs",Q1_2025[[#This Row],[Artikelprijs]] * Q1_2025[[#This Row],[Besteld]],Q1_2025[[#This Row],[Brutobedrag]]) -> 35.02 | P22: =IF(Q1_2025[[#This Row],[Prijstype]] = "Artikelprijs",Q1_2025[[#This Row],[Brutobedrag 2]]*(100-Q1_2025[[#This Row],[Relatiekorting percentage]])/100,Q1_2025[[#This Row],[Bruto - Rel.korting]]) -> 24.51
A23: AAO 2025.xls | B23: 5031056 | C23: Prolyte truss H30V Hoek V003 alu | D23: 4 | E23: 69.78 | F23: 279.12 | G23: 195.38 | H23: 30 | I23: =_xlfn.XLOOKUP(Q1_2025[[#This Row],[Artikelnr]],Artikel_prijzen[Artnr],Artikel_prijzen[Groep],"") | J23: =_xlfn.XLOOKUP(Q1_2025[[#This Row],[Artikelnr]],Artikel_prijzen[Artnr],Artikel_prijzen[Prijs 2025],"") | K23: =IF(Q1_2025[[#This Row],[Artikelprijs]]<>"",IF(Q1_2025[[#This Row],[Stuksprijs]]=Q1_2025[[#This Row],[Artikelprijs]],"Prijs gelijk","Prijs wijkt af"),"") | N23: =IF(Q1_2025[[#This Row],[Prijstype]]="Artikelprijs",Q1_2025[[#This Row],[Artikelprijs]],Q1_2025[[#This Row],[Stuksprijs]]) -> 69.78 | O23: =IF(Q1_2025[[#This Row],[Prijstype]]="Artikelprijs",Q1_2025[[#This Row],[Artikelprijs]] * Q1_2025[[#This Row],[Besteld]],Q1_2025[[#This Row],[Brutobedrag]]) -> 279.12 | P23: =IF(Q1_2025[[#This Row],[Prijstype]] = "Artikelprijs",Q1_2025[[#This Row],[Brutobedrag 2]]*(100-Q1_2025[[#This Row],[Relatiekorting percentage]])/100,Q1_2025[[#This Row],[Bruto - Rel.korting]]) -> 195.38
A24: AAO 2025.xls | B24: 5031059 | C24: Prolyte truss H30V Hoek V017 alu | D24: 1 | E24: 69.78 | F24: 69.78 | G24: 48.85 | H24: 30 | I24: =_xlfn.XLOOKUP(Q1_2025[[#This Row],[Artikelnr]],Artikel_prijzen[Artnr],Artikel_prijzen[Groep],"") | J24: =_xlfn.XLOOKUP(Q1_2025[[#This Row],[Artikelnr]],Artikel_prijzen[Artnr],Artikel_prijzen[Prijs 2025],"") | K24: =IF(Q1_2025[[#This Row],[Artikelprijs]]<>"",IF(Q1_2025[[#This Row],[Stuksprijs]]=Q1_2025[[#This Row],[Artikelprijs]],"Prijs gelijk","Prijs wijkt af"),"") | N24: =IF(Q1_2025[[#This Row],[Prijstype]]="Artikelprijs",Q1_2025[[#This Row],[Artikelprijs]],Q1_2025[[#This Row],[Stuksprijs]]) -> 69.78 | O24: =IF(Q1_2025[[#This Row],[Prijstype]]="Artikelprijs",Q1_2025[[#This Row],[Artikelprijs]] * Q1_2025[[#This Row],[Besteld]],Q1_2025[[#This Row],[Brutobedrag]]) -> 69.78 | P24: =IF(Q1_2025[[#This Row],[Prijstype]] = "Artikelprijs",Q1_2025[[#This Row],[Brutobedrag 2]]*(100-Q1_2025[[#This Row],[Relatiekorting percentage]])/100,Q1_2025[[#This Row],[Bruto - Rel.korting]]) -> 48.85
A25: AAO 2025.xls | B25: 5030229 | C25: Motortakel incl. ophangpunt + montage max 250kg | D25: 13 | E25: 303.85 | F25: 3950.05 | G25: 2765.03 | H25: 30 | I25: =_xlfn.XLOOKUP(Q1_2025[[#This Row],[Artikelnr]],Artikel_prijzen[Artnr],Artikel_prijzen[Groep],"") -> Rigging | J25: =_xlfn.XLOOKUP(Q1_2025[[#This Row],[Artikelnr]],Artikel_prijzen[Artnr],Artikel_prijzen[Prijs 2025],"") -> 295 | K25: =IF(Q1_2025[[#This Row],[Artikelprijs]]<>"",IF(Q1_2025[[#This Row],[Stuksprijs]]=Q1_2025[[#This Row],[Artikelprijs]],"Prijs gelijk","Prijs wijkt af"),"") -> Prijs wijkt af | M25: Artikelprijs | N25: =IF(Q1_2025[[#This Row],[Prijstype]]="Artikelprijs",Q1_2025[[#This Row],[Artikelprijs]],Q1_2025[[#This Row],[Stuksprijs]]) -> 295 | O25: =IF(Q1_2025[[#This Row],[Prijstype]]="Artikelprijs",Q1_2025[[#This Row],[Artikelprijs]] * Q1_2025[[#This Row],[Besteld]],Q1_2025[[#This Row],[Brutobedrag]]) -> 3835 | P25: =IF(Q1_2025[[#This Row],[Prijstype]] = "Artikelprijs",Q1_2025[[#This Row],[Brutobedrag 2]]*(100-Q1_2025[[#This Row],[Relatiekorting percentage]])/100,Q1_2025[[#This Row],[Bruto - Rel.korting]]) -> 2684.5
A26: AAO 2025.xls | B26: 3098001 | C26: Floodlight HQI - 2000W Asym. | D26: 20 | E26: 285 | F26: 5700 | G26: 4275 | H26: 25 | I26: =_xlfn.XLOOKUP(Q1_2025[[#This Row],[Artikelnr]],Artikel_prijzen[Artnr],Artikel_prijzen[Groep],"") | J26: =_xlfn.XLOOKUP(Q1_2025[[#This Row],[Artikelnr]],Artikel_prijzen[Artnr],Artikel_prijzen[Prijs 2025],"") | K26: =IF(Q1_2025[[#This Row],[Artikelprijs]]<>"",IF(Q1_2025[[#This Row],[Stuksprijs]]=Q1_2025[[#This Row],[Artikelprijs]],"Prijs gelijk","Prijs wijkt af"),"") | N26: =IF(Q1_2025[[#This Row],[Prijstype]]="Artikelprijs",Q1_2025[[#This Row],[Artikelprijs]],Q1_2025[[#This Row],[Stuksprijs]]) -> 285 | O26: =IF(Q1_2025[[#This Row],[Prijstype]]="Artikelprijs",Q1_2025[[#This Row],[Artikelprijs]] * Q1_2025[[#This Row],[Besteld]],Q1_2025[[#This Row],[Brutobedrag]]) -> 5700 | P26: =IF(Q1_2025[[#This Row],[Prijstype]] = "Artikelprijs",Q1_2025[[#This Row],[Brutobedrag 2]]*(100-Q1_2025[[#This Row],[Relatiekorting percentage]])/100,Q1_2025[[#This Row],[Bruto - Rel.korting]]) -> 4275
A27: AAO 2025.xls | B27: 5031053 | C27: Prolyte truss H30V 3 meter alu | D27: 49 | E27: 113.3 | F27: 5551.7 | G27: 3886.19 | H27: 30 | I27: =_xlfn.XLOOKUP(Q1_2025[[#This Row],[Artikelnr]],Artikel_prijzen[Artnr],Artikel_prijzen[Groep],"") | J27: =_xlfn.XLOOKUP(Q1_2025[[#This Row],[Artikelnr]],Artikel_prijzen[Artnr],Artikel_prijzen[Prijs 2025],"") | K27: =IF(Q1_2025[[#This Row],[Artikelprijs]]<>"",IF(Q1_2025[[#This Row],[Stuksprijs]]=Q1_2025[[#This Row],[Artikelprijs]],"Prijs gelijk","Prijs wijkt af"),"") | N27: =IF(Q1_2025[[#This Row],[Prijstype]]="Artikelprijs",Q1_2025[[#This Row],[Artikelprijs]],Q1_2025[[#This Row],[Stuksprijs]]) -> 113.3 | O27: =IF(Q1_2025[[#This Row],[Prijstype]]="Artikelprijs",Q1_2025[[#This Row],[Artikelprijs]] * Q1_2025[[#This Row],[Besteld]],Q1_2025[[#This Row],[Brutobedrag]]) -> 5551.7 | P27: =IF(Q1_2025[[#This Row],[Prijstype]] = "Artikelprijs",Q1_2025[[#This Row],[Brutobedrag 2]]*(100-Q1_2025[[#This Row],[Relatiekorting percentage]])/100,Q1_2025[[#This Row],[Bruto - Rel.korting]]) -> 3886.19
A28: AAO 2025.xls | B28: 5031052 | C28: Prolyte truss H30V 2 meter alu | D28: 2 | E28: 88.07 | F28: 176.14 | G28: 123.3 | H28: 30 | I28: =_xlfn.XLOOKUP(Q1_2025[[#This Row],[Artikelnr]],Artikel_prijzen[Artnr],Artikel_prijzen[Groep],"") | J28: =_xlfn.XLOOKUP(Q1_2025[[#This Row],[Artikelnr]],Artikel_prijzen[Artnr],Artikel_prijzen[Prijs 2025],"") | K28: =IF(Q1_2025[[#This Row],[Artikelprijs]]<>"",IF(Q1_2025[[#This Row],[Stuksprijs]]=Q1_2025[[#This Row],[Artikelprijs]],"Prijs gelijk","Prijs wijkt af"),"") | N28: =IF(Q1_2025[[#This Row],[Prijstype]]="Artikelprijs",Q1_2025[[#This Row],[Artikelprijs]],Q1_2025[[#This Row],[Stuksprijs]]) -> 88.07 | O28: =IF(Q1_2025[[#This Row],[Prijstype]]="Artikelprijs",Q1_2025[[#This Row],[Artikelprijs]] * Q1_2025[[#This Row],[Besteld]],Q1_2025[[#This Row],[Brutobedrag]]) -> 176.14 | P28: =IF(Q1_2025[[#This Row],[Prijstype]] = "Artikelprijs",Q1_2025[[#This Row],[Brutobedrag 2]]*(100-Q1_2025[[#This Row],[Relatiekorting percentage]])/100,Q1_2025[[#This Row],[Bruto - Rel.korting]]) -> 123.3
A29: AAO 2025.xls | B29: 2002096 | C29: Prolyte truss H30V 1 meter | D29: 2 | E29: 29.75 | F29: 59.5 | G29: 41.65 | H29: 30 | I29: =_xlfn.XLOOKUP(Q1_2025[[#This Row],[Artikelnr]],Artikel_prijzen[Artnr],Artikel_prijzen[Groep],"") | J29: =_xlfn.XLOOKUP(Q1_2025[[#This Row],[Artikelnr]],Artikel_prijzen[Artnr],Artikel_prijzen[Prijs 2025],"") | K29: =IF(Q1_2025[[#This Row],[Artikelprijs]]<>"",IF(Q1_2025[[#This Row],[Stuksprijs]]=Q1_2025[[#This Row],[Artikelprijs]],"Prijs gelijk","Prijs wijkt af"),"") | N29: =IF(Q1_2025[[#This Row],[Prijstype]]="Artikelprijs",Q1_2025[[#This Row],[Artikelprijs]],Q1_2025[[#This Row],[Stuksprijs]]) -> 29.75 | O29: =IF(Q1_2025[[#This Row],[Prijstype]]="Artikelprijs",Q1_2025[[#This Row],[Artikelprijs]] * Q1_2025[[#This Row],[Besteld]],Q1_2025[[#This Row],[Brutobedrag]]) -> 59.5 | P29: =IF(Q1_2025[[#This Row],[Prijstype]] = "Artikelprijs",Q1_2025[[#This Row],[Brutobedrag 2]]*(100-Q1_2025[[#This Row],[Relatiekorting percentage]])/100,Q1_2025[[#This Row],[Bruto - Rel.korting]]) -> 41.65
A30: AAO 2025.xls | B30: 5031047 | C30: Prolyte truss H30V 0,29 meter alu | D30: 3 | E30: 35.02 | F30: 105.06 | G30: 73.54 | H30: 30 | I30: =_xlfn.XLOOKUP(Q1_2025[[#This Row],[Artikelnr]],Artikel_prijzen[Artnr],Artikel_prijzen[Groep],"") | J30: =_xlfn.XLOOKUP(Q1_2025[[#This Row],[Artikelnr]],Artikel_prijzen[Artnr],Artikel_prijzen[Prijs 2025],"") | K30: =IF(Q1_2025[[#This Row],[Artikelprijs]]<>"",IF(Q1_2025[[#This Row],[Stuksprijs]]=Q1_2025[[#This Row],[Artikelprijs]],"Prijs gelijk","Prijs wijkt af"),"") | N30: =IF(Q1_2025[[#This Row],[Prijstype]]="Artikelprijs",Q1_2025[[#This Row],[Artikelprijs]],Q1_2025[[#This Row],[Stuksprijs]]) -> 35.02 | O30: =IF(Q1_2025[[#This Row],[Prijstype]]="Artikelprijs",Q1_2025[[#This Row],[Artikelprijs]] * Q1_2025[[#This Row],[Besteld]],Q1_2025[[#This Row],[Brutobedrag]]) -> 105.06 | P30: =IF(Q1_2025[[#This Row],[Prijstype]] = "Artikelprijs",Q1_2025[[#This Row],[Brutobedrag 2]]*(100-Q1_2025[[#This Row],[Relatiekorting percentage]])/100,Q1_2025[[#This Row],[Bruto - Rel.korting]]) -> 73.54
A31: AAO 2025.xls | B31: 5031056 | C31: Prolyte truss H30V Hoek V003 alu | D31: 2 | E31: 69.78 | F31: 139.56 | G31: 97.69 | H31: 30 | I31: =_xlfn.XLOOKUP(Q1_2025[[#This Row],[Artikelnr]],Artikel_prijzen[Artnr],Artikel_prijzen[Groep],"") | J31: =_xlfn.XLOOKUP(Q1_2025[[#This Row],[Artikelnr]],Artikel_prijzen[Artnr],Artikel_prijzen[Prijs 2025],"") | K31: =IF(Q1_2025[[#This Row],[Artikelprijs]]<>"",IF(Q1_2025[[#This Row],[Stuksprijs]]=Q1_2025[[#This Row],[Artikelprijs]],"Prijs gelijk","Prijs wijkt af"),"") | N31: =IF(Q1_2025[[#This Row],[Prijstype]]="Artikelprijs",Q1_2025[[#This Row],[Artikelprijs]],Q1_2025[[#This Row],[Stuksprijs]]) -> 69.78 | O31: =IF(Q1_2025[[#This Row],[Prijstype]]="Artikelprijs",Q1_2025[[#This Row],[Artikelprijs]] * Q1_2025[[#This Row],[Besteld]],Q1_2025[[#This Row],[Brutobedrag]]) -> 139.56 | P31: =IF(Q1_2025[[#This Row],[Prijstype]] = "Artikelprijs",Q1_2025[[#This Row],[Brutobedrag 2]]*(100-Q1_2025[[#This Row],[Relatiekorting percentage]])/100,Q1_2025[[#This Row],[Bruto - Rel.korting]]) -> 97.69
A32: AAO 2025.xls | B32: 5031072 | C32: Prolyte truss H30V Hoek V005 alu | D32: 4 | E32: 69.78 | F32: 279.12 | G32: 195.38 | H32: 30 | I32: =_xlfn.XLOOKUP(Q1_2025[[#This Row],[Artikelnr]],Artikel_prijzen[Artnr],Artikel_prijzen[Groep],"") | J32: =_xlfn.XLOOKUP(Q1_2025[[#This Row],[Artikelnr]],Artikel_prijzen[Artnr],Artikel_prijzen[Prijs 2025],"") | K32: =IF(Q1_2025[[#This Row],[Artikelprijs]]<>"",IF(Q1_2025[[#This Row],[Stuksprijs]]=Q1_2025[[#This Row],[Artikelprijs]],"Prijs gelijk","Prijs wijkt af"),"") | N32: =IF(Q1_2025[[#This Row],[Prijstype]]="Artikelprijs",Q1_2025[[#This Row],[Artikelprijs]],Q1_2025[[#This Row],[Stuksprijs]]) -> 69.78 | O32: =IF(Q1_2025[[#This Row],[Prijstype]]="Artikelprijs",Q1_2025[[#This Row],[Artikelprijs]] * Q1_2025[[#This Row],[Besteld]],Q1_2025[[#This Row],[Brutobedrag]]) -> 279.12 | P32: =IF(Q1_2025[[#This Row],[Prijstype]] = "Artikelprijs",Q1_2025[[#This Row],[Brutobedrag 2]]*(100-Q1_2025[[#This Row],[Relatiekorting percentage]])/100,Q1_2025[[#This Row],[Bruto - Rel.korting]]) -> 195.38
A33: AAO 2025.xls | B33: 2001027 | C33: Prolyte truss Spacer 3 cm | D33: 4 | E33: 8.65 | F33: 0 | G33: 0 | H33: 30 | I33: =_xlfn.XLOOKUP(Q1_2025[[#This Row],[Artikelnr]],Artikel_prijzen[Artnr],Artikel_prijzen[Groep],"") | J33: =_xlfn.XLOOKUP(Q1_2025[[#This Row],[Artikelnr]],Artikel_prijzen[Artnr],Artikel_prijzen[Prijs 2025],"") | K33: =IF(Q1_2025[[#This Row],[Artikelprijs]]<>"",IF(Q1_2025[[#This Row],[Stuksprijs]]=Q1_2025[[#This Row],[Artikelprijs]],"Prijs gelijk","Prijs wijkt af"),"") | N33: =IF(Q1_2025[[#This Row],[Prijstype]]="Artikelprijs",Q1_2025[[#This Row],[Artikelprijs]],Q1_2025[[#This Row],[Stuksprijs]]) -> 8.65 | O33: =IF(Q1_2025[[#This Row],[Prijstype]]="Artikelprijs",Q1_2025[[#This Row],[Artikelprijs]] * Q1_2025[[#This Row],[Besteld]],Q1_2025[[#This Row],[Brutobedrag]]) -> 0 | P33: =IF(Q1_2025[[#This Row],[Prijstype]] = "Artikelprijs",Q1_2025[[#This Row],[Brutobedrag 2]]*(100-Q1_2025[[#This Row],[Relatiekorting percentage]])/100,Q1_2025[[#This Row],[Bruto - Rel.korting]]) -> 0
A34: AAO 2025.xls | B34: 5030229 | C34: Motortakel incl. ophangpunt + montage max 250kg | D34: 18 | E34: 303.85 | F34: 5469.3 | G34: 3828.51 | H34: 30 | I34: =_xlfn.XLOOKUP(Q1_2025[[#This Row],[Artikelnr]],Artikel_prijzen[Artnr],Artikel_prijzen[Groep],"") -> Rigging | J34: =_xlfn.XLOOKUP(Q1_2025[[#This Row],[Artikelnr]],Artikel_prijzen[Artnr],Artikel_prijzen[Prijs 2025],"") -> 295 | K34: =IF(Q1_2025[[#This Row],[Artikelprijs]]<>"",IF(Q1_2025[[#This Row],[Stuksprijs]]=Q1_2025[[#This Row],[Artikelprijs]],"Prijs gelijk","Prijs wijkt af"),"") -> Prijs wijkt af | M34: Artikelprijs | N34: =IF(Q1_2025[[#This Row],[Prijstype]]="Artikelprijs",Q1_2025[[#This Row],[Artikelprijs]],Q1_2025[[#This Row],[Stuksprijs]]) -> 295 | O34: =IF(Q1_2025[[#This Row],[Prijstype]]="Artikelprijs",Q1_2025[[#This Row],[Artikelprijs]] * Q1_2025[[#This Row],[Besteld]],Q1_2025[[#This Row],[Brutobedrag]]) -> 5310 | P34: =IF(Q1_2025[[#This Row],[Prijstype]] = "Artikelprijs",Q1_2025[[#This Row],[Brutobedrag 2]]*(100-Q1_2025[[#This Row],[Relatiekorting percentage]])/100,Q1_2025[[#This Row],[Bruto - Rel.korting]]) -> 3717
A35: AAO 2025.xls | B35: 3098001 | C35: Luxibel wash BP9Z | D35: 24 | E35: 225 | F35: 5400 | G35: 4050 | H35: 25 | I35: =_xlfn.XLOOKUP(Q1_2025[[#This Row],[Artikelnr]],Artikel_prijzen[Artnr],Artikel_prijzen[Groep],"") | J35: =_xlfn.XLOOKUP(Q1_2025[[#This Row],[Artikelnr]],Artikel_prijzen[Artnr],Artikel_prijzen[Prijs 2025],"") | K35: =IF(Q1_2025[[#This Row],[Artikelprijs]]<>"",IF(Q1_2025[[#This Row],[Stuksprijs]]=Q1_2025[[#This Row],[Artikelprijs]],"Prijs gelijk","Prijs wijkt af"),"") | N35: =IF(Q1_2025[[#This Row],[Prijstype]]="Artikelprijs",Q1_2025[[#This Row],[Artikelprijs]],Q1_2025[[#This Row],[Stuksprijs]]) -> 225 | O35: =IF(Q1_2025[[#This Row],[Prijstype]]="Artikelprijs",Q1_2025[[#This Row],[Artikelprijs]] * Q1_2025[[#This Row],[Besteld]],Q1_2025[[#This Row],[Brutobedrag]]) -> 5400 | P35: =IF(Q1_2025[[#This Row],[Prijstype]] = "Artikelprijs",Q1_2025[[#This Row],[Brutobedrag 2]]*(100-Q1_2025[[#This Row],[Relatiekorting percentage]])/100,Q1_2025[[#This Row],[Bruto - Rel.korting]]) -> 4050
A36: AAO 2025.xls | B36: 3098001 | C36: LED Moving Head Clay Paky Sharpy X-Frame | D36: 12 | E36: 605 | F36: 7260 | G36: 5445 | H36: 25 | I36: =_xlfn.XLOOKUP(Q1_2025[[#This Row],[Artikelnr]],Artikel_prijzen[Artnr],Artikel_prijzen[Groep],"") | J36: =_xlfn.XLOOKUP(Q1_2025[[#This Row],[Artikelnr]],Artikel_prijzen[Artnr],Artikel_prijzen[Prijs 2025],"") | K36: =IF(Q1_2025[[#This Row],[Artikelprijs]]<>"",IF(Q1_2025[[#This Row],[Stuksprijs]]=Q1_2025[[#This Row],[Artikelprijs]],"Prijs gelijk","Prijs wijkt af"),"") | N36: =IF(Q1_2025[[#This Row],[Prijstype]]="Artikelprijs",Q1_2025[[#This Row],[Artikelprijs]],Q1_2025[[#This Row],[Stuksprijs]]) -> 605 | O36: =IF(Q1_2025[[#This Row],[Prijstype]]="Artikelprijs",Q1_2025[[#This Row],[Artikelprijs]] * Q1_2025[[#This Row],[Besteld]],Q1_2025[[#This Row],[Brutobedrag]]) -> 7260 | P36: =IF(Q1_2025[[#This Row],[Prijstype]] = "Artikelprijs",Q1_2025[[#This Row],[Brutobedrag 2]]*(100-Q1_2025[[#This Row],[Relatiekorting percentage]])/100,Q1_2025[[#This Row],[Bruto - Rel.korting]]) -> 5445
A37: AAO 2025.xls | B37: 5010001 | C37: Grand MA3 Licht regeltafel | D37: 1 | E37: 1450 | F37: 1450 | G37: 1087.5 | H37: 25 | I37: =_xlfn.XLOOKUP(Q1_2025[[#This Row],[Artikelnr]],Artikel_prijzen[Artnr],Artikel_prijzen[Groep],"") | J37: =_xlfn.XLOOKUP(Q1_2025[[#This Row],[Artikelnr]],Artikel_prijzen[Artnr],Artikel_prijzen[Prijs 2025],"") | K37: =IF(Q1_2025[[#This Row],[Artikelprijs]]<>"",IF(Q1_2025[[#This Row],[Stuksprijs]]=Q1_2025[[#This Row],[Artikelprijs]],"Prijs gelijk","Prijs wijkt af"),"") | N37: =IF(Q1_2025[[#This Row],[Prijstype]]="Artikelprijs",Q1_2025[[#This Row],[Artikelprijs]],Q1_2025[[#This Row],[Stuksprijs]]) -> 1450 | O37: =IF(Q1_2025[[#This Row],[Prijstype]]="Artikelprijs",Q1_2025[[#This Row],[Artikelprijs]] * Q1_2025[[#This Row],[Besteld]],Q1_2025[[#This Row],[Brutobedrag]]) -> 1450 | P37: =IF(Q1_2025[[#This Row],[Prijstype]] = "Artikelprijs",Q1_2025[[#This Row],[Brutobedrag 2]]*(100-Q1_2025[[#This Row],[Relatiekorting percentage]])/100,Q1_2025[[#This Row],[Bruto - Rel.korting]]) -> 1087.5
A38: AAO 2025.xls | B38: 5030229 | C38: Motortakel incl. ophangpunt + montage max 250kg | D38: 4 | E38: 303.85 | F38: 1215.4 | G38: 850.78 | H38: 30 | I38: =_xlfn.XLOOKUP(Q1_2025[[#This Row],[Artikelnr]],Artikel_prijzen[Artnr],Artikel_prijzen[Groep],"") -> Rigging | J38: =_xlfn.XLOOKUP(Q1_2025[[#This Row],[Artikelnr]],Artikel_prijzen[Artnr],Artikel_prijzen[Prijs 2025],"") -> 295 | K38: =IF(Q1_2025[[#This Row],[Artikelprijs]]<>"",IF(Q1_2025[[#This Row],[Stuksprijs]]=Q1_2025[[#This Row],[Artikelprijs]],"Prijs gelijk","Prijs wijkt af"),"") -> Prijs wijkt af | M38: Artikelprijs | N38: =IF(Q1_2025[[#This Row],[Prijstype]]="Artikelprijs",Q1_2025[[#This Row],[Artikelprijs]],Q1_2025[[#This Row],[Stuksprijs]]) -> 295 | O38: =IF(Q1_2025[[#This Row],[Prijstype]]="Artikelprijs",Q1_2025[[#This Row],[Artikelprijs]] * Q1_2025[[#This Row],[Besteld]],Q1_2025[[#This Row],[Brutobedrag]]) -> 1180 | P38: =IF(Q1_2025[[#This Row],[Prijstype]] = "Artikelprijs",Q1_2025[[#This Row],[Brutobedrag 2]]*(100-Q1_2025[[#This Row],[Relatiekorting percentage]])/100,Q1_2025[[#This Row],[Bruto - Rel.korting]]) -> 826
A39: AAO 2025.xls | B39: 5030229 | C39: Motortakel incl. ophangpunt + montage max 250kg | D39: 3 | E39: 303.85 | F39: 911.55 | G39: 638.08 | H39: 30 | I39: =_xlfn.XLOOKUP(Q1_2025[[#This Row],[Artikelnr]],Artikel_prijzen[Artnr],Artikel_prijzen[Groep],"") -> Rigging | J39: =_xlfn.XLOOKUP(Q1_2025[[#This Row],[Artikelnr]],Artikel_prijzen[Artnr],Artikel_prijzen[Prijs 2025],"") -> 295 | K39: =IF(Q1_2025[[#This Row],[Artikelprijs]]<>"",IF(Q1_2025[[#This Row],[Stuksprijs]]=Q1_2025[[#This Row],[Artikelprijs]],"Prijs gelijk","Prijs wijkt af"),"") -> Prijs wijkt af | M39: Artikelprijs | N39: =IF(Q1_2025[[#This Row],[Prijstype]]="Artikelprijs",Q1_2025[[#This Row],[Artikelprijs]],Q1_2025[[#This Row],[Stuksprijs]]) -> 295 | O39: =IF(Q1_2025[[#This Row],[Prijstype]]="Artikelprijs",Q1_2025[[#This Row],[Artikelprijs]] * Q1_2025[[#This Row],[Besteld]],Q1_2025[[#This Row],[Brutobedrag]]) -> 885 | P39: =IF(Q1_2025[[#This Row],[Prijstype]] = "Artikelprijs",Q1_2025[[#This Row],[Brutobedrag 2]]*(100-Q1_2025[[#This Row],[Relatiekorting percentage]])/100,Q1_2025[[#This Row],[Bruto - Rel.korting]]) -> 619.5
A40: AAO 2025.xls | B40: 5031051 | C40: Prolyte truss H30V 1 meter alu | D40: 1 | E40: 52.79 | F40: 52.79 | G40: 36.95 | H40: 30 | I40: =_xlfn.XLOOKUP(Q1_2025[[#This Row],[Artikelnr]],Artikel_prijzen[Artnr],Artikel_prijzen[Groep],"") | J40: =_xlfn.XLOOKUP(Q1_2025[[#This Row],[Artikelnr]],Artikel_prijzen[Artnr],Artikel_prijzen[Prijs 2025],"") | K40: =IF(Q1_2025[[#This Row],[Artikelprijs]]<>"",IF(Q1_2025[[#This Row],[Stuksprijs]]=Q1_2025[[#This Row],[Artikelprijs]],"Prijs gelijk","Prijs wijkt af"),"") | N40: =IF(Q1_2025[[#This Row],[Prijstype]]="Artikelprijs",Q1_2025[[#This Row],[Artikelprijs]],Q1_2025[[#This Row],[Stuksprijs]]) -> 52.79 | O40: =IF(Q1_2025[[#This Row],[Prijstype]]="Artikelprijs",Q1_2025[[#This Row],[Artikelprijs]] * Q1_2025[[#This Row],[Besteld]],Q1_2025[[#This Row],[Brutobedrag]]) -> 52.79 | P40: =IF(Q1_2025[[#This Row],[Prijstype]] = "Artikelprijs",Q1_2025[[#This Row],[Brutobedrag 2]]*(100-Q1_2025[[#This Row],[Relatiekorting percentage]])/100,Q1_2025[[#This Row],[Bruto - Rel.korting]]) -> 36.95
A41: AAO 2025.xls | B41: 5031053 | C41: Prolyte truss H30V 3 meter alu | D41: 5 | E41: 113.3 | F41: 566.5 | G41: 396.55 | H41: 30 | I41: =_xlfn.XLOOKUP(Q1_2025[[#This Row],[Artikelnr]],Artikel_prijzen[Artnr],Artikel_prijzen[Groep],"") | J41: =_xlfn.XLOOKUP(Q1_2025[[#This Row],[Artikelnr]],Artikel_prijzen[Artnr],Artikel_prijzen[Prijs 2025],"") | K41: =IF(Q1_2025[[#This Row],[Artikelprijs]]<>"",IF(Q1_2025[[#This Row],[Stuksprijs]]=Q1_2025[[#This Row],[Artikelprijs]],"Prijs gelijk","Prijs wijkt af"),"") | N41: =IF(Q1_2025[[#This Row],[Prijstype]]="Artikelprijs",Q1_2025[[#This Row],[Artikelprijs]],Q1_2025[[#This Row],[Stuksprijs]]) -> 113.3 | O41: =IF(Q1_2025[[#This Row],[Prijstype]]="Artikelprijs",Q1_2025[[#This Row],[Artikelprijs]] * Q1_2025[[#This Row],[Besteld]],Q1_2025[[#This Row],[Brutobedrag]]) -> 566.5 | P41: =IF(Q1_2025[[#This Row],[Prijstype]] = "Artikelprijs",Q1_2025[[#This Row],[Brutobedrag 2]]*(100-Q1_2025[[#This Row],[Relatiekorting percentage]])/100,Q1_2025[[#This Row],[Bruto - Rel.korting]]) -> 396.55
A42: AAO 2025.xls | B42: 5031053 | C42: Prolyte truss H30V 3 meter alu | D42: 3 | E42: 113.3 | F42: 339.9 | G42: 237.93 | H42: 30 | I42: =_xlfn.XLOOKUP(Q1_2025[[#This Row],[Artikelnr]],Artikel_prijzen[Artnr],Artikel_prijzen[Groep],"") | J42: =_xlfn.XLOOKUP(Q1_2025[[#This Row],[Artikelnr]],Artikel_prijzen[Artnr],Artikel_prijzen[Prijs 2025],"") | K42: =IF(Q1_2025[[#This Row],[Artikelprijs]]<>"",IF(Q1_2025[[#This Row],[Stuksprijs]]=Q1_2025[[#This Row],[Artikelprijs]],"Prijs gelijk","Prijs wijkt af"),"") | N42: =IF(Q1_2025[[#This Row],[Prijstype]]="Artikelprijs",Q1_2025[[#This Row],[Artikelprijs]],Q1_2025[[#This Row],[Stuksprijs]]) -> 113.3 | O42: =IF(Q1_2025[[#This Row],[Prijstype]]="Artikelprijs",Q1_2025[[#This Row],[Artikelprijs]] * Q1_2025[[#This Row],[Besteld]],Q1_2025[[#This Row],[Brutobedrag]]) -> 339.9 | P42: =IF(Q1_2025[[#This Row],[Prijstype]] = "Artikelprijs",Q1_2025[[#This Row],[Brutobedrag 2]]*(100-Q1_2025[[#This Row],[Relatiekorting percentage]])/100,Q1_2025[[#This Row],[Bruto - Rel.korting]]) -> 237.93
A43: AAO 2025.xls | B43: 5030005 | C43: Voedingskabel via dak (van ophangpunt naar zijkant hal) | D43: 1 | E43: 200.85 | F43: 200.85 | G43: 140.59 | H43: 30 | I43: =_xlfn.XLOOKUP(Q1_2025[[#This Row],[Artikelnr]],Artikel_prijzen[Artnr],Artikel_prijzen[Groep],"") -> Rigging | J43: =_xlfn.XLOOKUP(Q1_2025[[#This Row],[Artikelnr]],Artikel_prijzen[Artnr],Artikel_prijzen[Prijs 2025],"") -> 195 | K43: =IF(Q1_2025[[#This Row],[Artikelprijs]]<>"",IF(Q1_2025[[#This Row],[Stuksprijs]]=Q1_2025[[#This Row],[Artikelprijs]],"Prijs gelijk","Prijs wijkt af"),"") -> Prijs wijkt af | M43: Artikelprijs | N43: =IF(Q1_2025[[#This Row],[Prijstype]]="Artikelprijs",Q1_2025[[#This Row],[Artikelprijs]],Q1_2025[[#This Row],[Stuksprijs]]) -> 195 | O43: =IF(Q1_2025[[#This Row],[Prijstype]]="Artikelprijs",Q1_2025[[#This Row],[Artikelprijs]] * Q1_2025[[#This Row],[Besteld]],Q1_2025[[#This Row],[Brutobedrag]]) -> 195 | P43: =IF(Q1_2025[[#This Row],[Prijstype]] = "Artikelprijs",Q1_2025[[#This Row],[Brutobedrag 2]]*(100-Q1_2025[[#This Row],[Relatiekorting percentage]])/100,Q1_2025[[#This Row],[Bruto - Rel.korting]]) -> 136.5
A44: AAO 2025.xls | B44: 1007028 | C44: LED Breedstraler Fenon100w | D44: 2 | E44: 115 | F44: 230 | G44: 172.5 | H44: 25 | I44: =_xlfn.XLOOKUP(Q1_2025[[#This Row],[Artikelnr]],Artikel_prijzen[Artnr],Artikel_prijzen[Groep],"") | J44: =_xlfn.XLOOKUP(Q1_2025[[#This Row],[Artikelnr]],Artikel_prijzen[Artnr],Artikel_prijzen[Prijs 2025],"") | K44: =IF(Q1_2025[[#This Row],[Artikelprijs]]<>"",IF(Q1_2025[[#This Row],[Stuksprijs]]=Q1_2025[[#This Row],[Artikelprijs]],"Prijs gelijk","Prijs wijkt af"),"") | N44: =IF(Q1_2025[[#This Row],[Prijstype]]="Artikelprijs",Q1_2025[[#This Row],[Artikelprijs]],Q1_2025[[#This Row],[Stuksprijs]]) -> 115 | O44: =IF(Q1_2025[[#This Row],[Prijstype]]="Artikelprijs",Q1_2025[[#This Row],[Artikelprijs]] * Q1_2025[[#This Row],[Besteld]],Q1_2025[[#This Row],[Brutobedrag]]) -> 230 | P44: =IF(Q1_2025[[#This Row],[Prijstype]] = "Artikelprijs",Q1_2025[[#This Row],[Brutobedrag 2]]*(100-Q1_2025[[#This Row],[Relatiekorting percentage]])/100,Q1_2025[[#This Row],[Bruto - Rel.korting]]) -> 172.5
A45: AAO 2025.xls | B45: 2002095 | C45: Prolyte truss H30V 3 meter | D45: 63 | E45: 89.25 | F45: 5622.75 | G45: 3935.92 | H45: 30 | I45: =_xlfn.XLOOKUP(Q1_2025[[#This Row],[Artikelnr]],Artikel_prijzen[Artnr],Artikel_prijzen[Groep],"") | J45: =_xlfn.XLOOKUP(Q1_2025[[#This Row],[Artikelnr]],Artikel_prijzen[Artnr],Artikel_prijzen[Prijs 2025],"") | K45: =IF(Q1_2025[[#This Row],[Artikelprijs]]<>"",IF(Q1_2025[[#This Row],[Stuksprijs]]=Q1_2025[[#This Row],[Artikelprijs]],"Prijs gelijk","Prijs wijkt af"),"") | N45: =IF(Q1_2025[[#This Row],[Prijstype]]="Artikelprijs",Q1_2025[[#This Row],[Artikelprijs]],Q1_2025[[#This Row],[Stuksprijs]]) -> 89.25 | O45: =IF(Q1_2025[[#This Row],[Prijstype]]="Artikelprijs",Q1_2025[[#This Row],[Artikelprijs]] * Q1_2025[[#This Row],[Besteld]],Q1_2025[[#This Row],[Brutobedrag]]) -> 5622.75 | P45: =IF(Q1_2025[[#This Row],[Prijstype]] = "Artikelprijs",Q1_2025[[#This Row],[Brutobedrag 2]]*(100-Q1_2025[[#This Row],[Relatiekorting percentage]])/100,Q1_2025[[#This Row],[Bruto - Rel.korting]]) -> 3935.92
A46: AAO 2025.xls | B46: 5031052 | C46: Prolyte truss H30V 2 meter alu | D46: 2 | E46: 88.07 | F46: 176.14 | G46: 123.3 | H46: 30 | I46: =_xlfn.XLOOKUP(Q1_2025[[#This Row],[Artikelnr]],Artikel_prijzen[Artnr],Artikel_prijzen[Groep],"") | J46: =_xlfn.XLOOKUP(Q1_2025[[#This Row],[Artikelnr]],Artikel_prijzen[Artnr],Artikel_prijzen[Prijs 2025],"") | K46: =IF(Q1_2025[[#This Row],[Artikelprijs]]<>"",IF(Q1_2025[[#This Row],[Stuksprijs]]=Q1_2025[[#This Row],[Artikelprijs]],"Prijs gelijk","Prijs wijkt af"),"") | N46: =IF(Q1_2025[[#This Row],[Prijstype]]="Artikelprijs",Q1_2025[[#This Row],[Artikelprijs]],Q1_2025[[#This Row],[Stuksprijs]]) -> 88.07 | O46: =IF(Q1_2025[[#This Row],[Prijstype]]="Artikelprijs",Q1_2025[[#This Row],[Artikelprijs]] * Q1_2025[[#This Row],[Besteld]],Q1_2025[[#This Row],[Brutobedrag]]) -> 176.14 | P46: =IF(Q1_2025[[#This Row],[Prijstype]] = "Artikelprijs",Q1_2025[[#This Row],[Brutobedrag 2]]*(100-Q1_2025[[#This Row],[Relatiekorting percentage]])/100,Q1_2025[[#This Row],[Bruto - Rel.korting]]) -> 123.3
A47: AAO 2025.xls | B47: 5031052 | C47: Prolyte truss H30V 2 meter alu | D47: 4 | E47: 88.07 | F47: 352.28 | G47: 246.6 | H47: 30 | I47: =_xlfn.XLOOKUP(Q1_2025[[#This Row],[Artikelnr]],Artikel_prijzen[Artnr],Artikel_prijzen[Groep],"") | J47: =_xlfn.XLOOKUP(Q1_2025[[#This Row],[Artikelnr]],Artikel_prijzen[Artnr],Artikel_prijzen[Prijs 2025],"") | K47: =IF(Q1_2025[[#This Row],[Artikelprijs]]<>"",IF(Q1_2025[[#This Row],[Stuksprijs]]=Q1_2025[[#This Row],[Artikelprijs]],"Prijs gelijk","Prijs wijkt af"),"") | N47: =IF(Q1_2025[[#This Row],[Prijstype]]="Artikelprijs",Q1_2025[[#This Row],[Artikelprijs]],Q1_2025[[#This Row],[Stuksprijs]]) -> 88.07 | O47: =IF(Q1_2025[[#This Row],[Prijstype]]="Artikelprijs",Q1_2025[[#This Row],[Artikelprijs]] * Q1_2025[[#This Row],[Besteld]],Q1_2025[[#This Row],[Brutobedrag]]) -> 352.28 | P47: =IF(Q1_2025[[#This Row],[Prijstype]] = "Artikelprijs",Q1_2025[[#This Row],[Brutobedrag 2]]*(100-Q1_2025[[#This Row],[Relatiekorting percentage]])/100,Q1_2025[[#This Row],[Bruto - Rel.korting]]) -> 246.6
A48: AAO 2025.xls | B48: 2002096 | C48: Prolyte truss H30V 1 meter | D48: 4 | E48: 29.75 | F48: 119 | G48: 83.3 | H48: 30 | I48: =_xlfn.XLOOKUP(Q1_2025[[#This Row],[Artikelnr]],Artikel_prijzen[Artnr],Artikel_prijzen[Groep],"") | J48: =_xlfn.XLOOKUP(Q1_2025[[#This Row],[Artikelnr]],Artikel_prijzen[Artnr],Artikel_prijzen[Prijs 2025],"") | K48: =IF(Q1_2025[[#This Row],[Artikelprijs]]<>"",IF(Q1_2025[[#This Row],[Stuksprijs]]=Q1_2025[[#This Row],[Artikelprijs]],"Prijs gelijk","Prijs wijkt af"),"") | N48: =IF(Q1_2025[[#This Row],[Prijstype]]="Artikelprijs",Q1_2025[[#This Row],[Artikelprijs]],Q1_2025[[#This Row],[Stuksprijs]]) -> 29.75 | O48: =IF(Q1_2025[[#This Row],[Prijstype]]="Artikelprijs",Q1_2025[[#This Row],[Artikelprijs]] * Q1_2025[[#This Row],[Besteld]],Q1_2025[[#This Row],[Brutobedrag]]) -> 119 | P48: =IF(Q1_2025[[#This Row],[Prijstype]] = "Artikelprijs",Q1_2025[[#This Row],[Brutobedrag 2]]*(100-Q1_2025[[#This Row],[Relatiekorting percentage]])/100,Q1_2025[[#This Row],[Bruto - Rel.korting]]) -> 83.3
A49: AAO 2025.xls | B49: 5031049 | C49: Prolyte truss H30V 0,5 meter alu | D49: 4 | E49: 35.02 | F49: 140.08 | G49: 98.06 | H49: 30 | I49: =_xlfn.XLOOKUP(Q1_2025[[#This Row],[Artikelnr]],Artikel_prijzen[Artnr],Artikel_prijzen[Groep],"") | J49: =_xlfn.XLOOKUP(Q1_2025[[#This Row],[Artikelnr]],Artikel_prijzen[Artnr],Artikel_prijzen[Prijs 2025],"") | K49: =IF(Q1_2025[[#This Row],[Artikelprijs]]<>"",IF(Q1_2025[[#This Row],[Stuksprijs]]=Q1_2025[[#This Row],[Artikelprijs]],"Prijs gelijk","Prijs wijkt af"),"") | N49: =IF(Q1_2025[[#This Row],[Prijstype]]="Artikelprijs",Q1_2025[[#This Row],[Artikelprijs]],Q1_2025[[#This Row],[Stuksprijs]]) -> 35.02 | O49: =IF(Q1_2025[[#This Row],[Prijstype]]="Artikelprijs",Q1_2025[[#This Row],[Artikelprijs]] * Q1_2025[[#This Row],[Besteld]],Q1_2025[[#This Row],[Brutobedrag]]) -> 140.08 | P49: =IF(Q1_2025[[#This Row],[Prijstype]] = "Artikelprijs",Q1_2025[[#This Row],[Brutobedrag 2]]*(100-Q1_2025[[#This Row],[Relatiekorting percentage]])/100,Q1_2025[[#This Row],[Bruto - Rel.korting]]) -> 98.06
A50: AAO 2025.xls | B50: 5031047 | C50: Prolyte truss H30V 0,29 meter alu | D50: 1 | E50: 35.02 | F50: 35.02 | G50: 24.51 | H50: 30 | I50: =_xlfn.XLOOKUP(Q1_2025[[#This Row],[Artikelnr]],Artikel_prijzen[Artnr],Artikel_prijzen[Groep],"") | J50: =_xlfn.XLOOKUP(Q1_2025[[#This Row],[Artikelnr]],Artikel_prijzen[Artnr],Artikel_prijzen[Prijs 2025],"") | K50: =IF(Q1_2025[[#This Row],[Artikelprijs]]<>"",IF(Q1_2025[[#This Row],[Stuksprijs]]=Q1_2025[[#This Row],[Artikelprijs]],"Prijs gelijk","Prijs wijkt af"),"") | N50: =IF(Q1_2025[[#This Row],[Prijstype]]="Artikelprijs",Q1_2025[[#This Row],[Artikelprijs]],Q1_2025[[#This Row],[Stuksprijs]]) -> 35.02 | O50: =IF(Q1_2025[[#This Row],[Prijstype]]="Artikelprijs",Q1_2025[[#This Row],[Artikelprijs]] * Q1_2025[[#This Row],[Besteld]],Q1_2025[[#This Row],[Brutobedrag]]) -> 35.02 | P50: =IF(Q1_2025[[#This Row],[Prijstype]] = "Artikelprijs",Q1_2025[[#This Row],[Brutobedrag 2]]*(100-Q1_2025[[#This Row],[Relatiekorting percentage]])/100,Q1_2025[[#This Row],[Bruto - Rel.korting]]) -> 24.51
A51: AAO 2025.xls | B51: 5031056 | C51: Prolyte truss H30V Hoek V003 alu | D51: 4 | E51: 69.78 | F51: 279.12 | G51: 195.38 | H51: 30 | I51: =_xlfn.XLOOKUP(Q1_2025[[#This Row],[Artikelnr]],Artikel_prijzen[Artnr],Artikel_prijzen[Groep],"") | J51: =_xlfn.XLOOKUP(Q1_2025[[#This Row],[Artikelnr]],Artikel_prijzen[Artnr],Artikel_prijzen[Prijs 2025],"") | K51: =IF(Q1_2025[[#This Row],[Artikelprijs]]<>"",IF(Q1_2025[[#This Row],[Stuksprijs]]=Q1_2025[[#This Row],[Artikelprijs]],"Prijs gelijk","Prijs wijkt af"),"") | N51: =IF(Q1_2025[[#This Row],[Prijstype]]="Artikelprijs",Q1_2025[[#This Row],[Artikelprijs]],Q1_2025[[#This Row],[Stuksprijs]]) -> 69.78 | O51: =IF(Q1_2025[[#This Row],[Prijstype]]="Artikelprijs",Q1_2025[[#This Row],[Artikelprijs]] * Q1_2025[[#This Row],[Besteld]],Q1_2025[[#This Row],[Brutobedrag]]) -> 279.12 | P51: =IF(Q1_2025[[#This Row],[Prijstype]] = "Artikelprijs",Q1_2025[[#This Row],[Brutobedrag 2]]*(100-Q1_2025[[#This Row],[Relatiekorting percentage]])/100,Q1_2025[[#This Row],[Bruto - Rel.korting]]) -> 195.38
A52: AAO 2025.xls | B52: 5031059 | C52: Prolyte truss H30V Hoek V017 alu | D52: 3 | E52: 69.78 | F52: 209.34 | G52: 146.54 | H52: 30 | I52: =_xlfn.XLOOKUP(Q1_2025[[#This Row],[Artikelnr]],Artikel_prijzen[Artnr],Artikel_prijzen[Groep],"") | J52: =_xlfn.XLOOKUP(Q1_2025[[#This Row],[Artikelnr]],Artikel_prijzen[Artnr],Artikel_prijzen[Prijs 2025],"") | K52: =IF(Q1_2025[[#This Row],[Artikelprijs]]<>"",IF(Q1_2025[[#This Row],[Stuksprijs]]=Q1_2025[[#This Row],[Artikelprijs]],"Prijs gelijk","Prijs wijkt af"),"") | N52: =IF(Q1_2025[[#This Row],[Prijstype]]="Artikelprijs",Q1_2025[[#This Row],[Artikelprijs]],Q1_2025[[#This Row],[Stuksprijs]]) -> 69.78 | O52: =IF(Q1_2025[[#This Row],[Prijstype]]="Artikelprijs",Q1_2025[[#This Row],[Artikelprijs]] * Q1_2025[[#This Row],[Besteld]],Q1_2025[[#This Row],[Brutobedrag]]) -> 209.34 | P52: =IF(Q1_2025[[#This Row],[Prijstype]] = "Artikelprijs",Q1_2025[[#This Row],[Brutobedrag 2]]*(100-Q1_2025[[#This Row],[Relatiekorting percentage]])/100,Q1_2025[[#This Row],[Bruto - Rel.korting]]) -> 146.54
A53: AAO 2025.xls | B53: 5030229 | C53: Motortakel incl. ophangpunt + montage max 250kg | D53: 21 | E53: 303.85 | F53: 6380.85 | G53: 4466.59 | H53: 30 | I53: =_xlfn.XLOOKUP(Q1_2025[[#This Row],[Artikelnr]],Artikel_prijzen[Artnr],Artikel_prijzen[Groep],"") -> Rigging | J53: =_xlfn.XLOOKUP(Q1_2025[[#This Row],[Artikelnr]],Artikel_prijzen[Artnr],Artikel_prijzen[Prijs 2025],"") -> 295 | K53: =IF(Q1_2025[[#This Row],[Artikelprijs]]<>"",IF(Q1_2025[[#This Row],[Stuksprijs]]=Q1_2025[[#This Row],[Artikelprijs]],"Prijs gelijk","Prijs wijkt af"),"") -> Prijs wijkt af | M53: Artikelprijs | N53: =IF(Q1_2025[[#This Row],[Prijstype]]="Artikelprijs",Q1_2025[[#This Row],[Artikelprijs]],Q1_2025[[#This Row],[Stuksprijs]]) -> 295 | O53: =IF(Q1_2025[[#This Row],[Prijstype]]="Artikelprijs",Q1_2025[[#This Row],[Artikelprijs]] * Q1_2025[[#This Row],[Besteld]],Q1_2025[[#This Row],[Brutobedrag]]) -> 6195 | P53: =IF(Q1_2025[[#This Row],[Prijstype]] = "Artikelprijs",Q1_2025[[#This Row],[Brutobedrag 2]]*(100-Q1_2025[[#This Row],[Relatiekorting percentage]])/100,Q1_2025[[#This Row],[Bruto - Rel.korting]]) -> 4336.5
A54: AAO 2025.xls | B54: 5031053 | C54: Prolyte truss H30V 3 meter alu | D54: 64 | E54: 113.3 | F54: 7251.2 | G54: 5075.84 | H54: 30 | I54: =_xlfn.XLOOKUP(Q1_2025[[#This Row],[Artikelnr]],Artikel_prijzen[Artnr],Artikel_prijzen[Groep],"") | J54: =_xlfn.XLOOKUP(Q1_2025[[#This Row],[Artikelnr]],Artikel_prijzen[Artnr],Artikel_prijzen[Prijs 2025],"") | K54: =IF(Q1_2025[[#This Row],[Artikelprijs]]<>"",IF(Q1_2025[[#This Row],[Stuksprijs]]=Q1_2025[[#This Row],[Artikelprijs]],"Prijs gelijk","Prijs wijkt af"),"") | N54: =IF(Q1_2025[[#This Row],[Prijstype]]="Artikelprijs",Q1_2025[[#This Row],[Artikelprijs]],Q1_2025[[#This Row],[Stuksprijs]]) -> 113.3 | O54: =IF(Q1_2025[[#This Row],[Prijstype]]="Artikelprijs",Q1_2025[[#This Row],[Artikelprijs]] * Q1_2025[[#This Row],[Besteld]],Q1_2025[[#This Row],[Brutobedrag]]) -> 7251.2 | P54: =IF(Q1_2025[[#This Row],[Prijstype]] = "Artikelprijs",Q1_2025[[#This Row],[Brutobedrag 2]]*(100-Q1_2025[[#This Row],[Relatiekorting percentage]])/100,Q1_2025[[#This Row],[Bruto - Rel.korting]]) -> 5075.84
A55: AAO 2025.xls | B55: 5031052 | C55: Prolyte truss H30V 2 meter alu | D55: 5 | E55: 88.07 | F55: 440.35 | G55: 308.24 | H55: 30 | I55: =_xlfn.XLOOKUP(Q1_2025[[#This Row],[Artikelnr]],Artikel_prijzen[Artnr],Artikel_prijzen[Groep],"") | J55: =_xlfn.XLOOKUP(Q1_2025[[#This Row],[Artikelnr]],Artikel_prijzen[Artnr],Artikel_prijzen[Prijs 2025],"") | K55: =IF(Q1_2025[[#This Row],[Artikelprijs]]<>"",IF(Q1_2025[[#This Row],[Stuksprijs]]=Q1_2025[[#This Row],[Artikelprijs]],"Prijs gelijk","Prijs wijkt af"),"") | N55: =IF(Q1_2025[[#This Row],[Prijstype]]="Artikelprijs",Q1_2025[[#This Row],[Artikelprijs]],Q1_2025[[#This Row],[Stuksprijs]]) -> 88.07 | O55: =IF(Q1_2025[[#This Row],[Prijstype]]="Artikelprijs",Q1_2025[[#This Row],[Artikelprijs]] * Q1_2025[[#This Row],[Besteld]],Q1_2025[[#This Row],[Brutobedrag]]) -> 440.35 | P55: =IF(Q1_2025[[#This Row],[Prijstype]] = "Artikelprijs",Q1_2025[[#This Row],[Brutobedrag 2]]*(100-Q1_2025[[#This Row],[Relatiekorting percentage]])/100,Q1_2025[[#This Row],[Bruto - Rel.korting]]) -> 308.24
A56: AAO 2025.xls | B56: 5031051 | C56: Prolyte truss H30V 1 meter alu | D56: 4 | E56: 52.79 | F56: 211.16 | G56: 147.81 | H56: 30 | I56: =_xlfn.XLOOKUP(Q1_2025[[#This Row],[Artikelnr]],Artikel_prijzen[Artnr],Artikel_prijzen[Groep],"") | J56: =_xlfn.XLOOKUP(Q1_2025[[#This Row],[Artikelnr]],Artikel_prijzen[Artnr],Artikel_prijzen[Prijs 2025],"") | K56: =IF(Q1_2025[[#This Row],[Artikelprijs]]<>"",IF(Q1_2025[[#This Row],[Stuksprijs]]=Q1_2025[[#This Row],[Artikelprijs]],"Prijs gelijk","Prijs wijkt af"),"") | N56: =IF(Q1_2025[[#This Row],[Prijstype]]="Artikelprijs",Q1_2025[[#This Row],[Artikelprijs]],Q1_2025[[#This Row],[Stuksprijs]]) -> 52.79 | O56: =IF(Q1_2025[[#This Row],[Prijstype]]="Artikelprijs",Q1_2025[[#This Row],[Artikelprijs]] * Q1_2025[[#This Row],[Besteld]],Q1_2025[[#This Row],[Brutobedrag]]) -> 211.16 | P56: =IF(Q1_2025[[#This Row],[Prijstype]] = "Artikelprijs",Q1_2025[[#This Row],[Brutobedrag 2]]*(100-Q1_2025[[#This Row],[Relatiekorting percentage]])/100,Q1_2025[[#This Row],[Bruto - Rel.korting]]) -> 147.81
A57: AAO 2025.xls | B57: 5031047 | C57: Prolyte truss H30V 0,29 meter alu | D57: 3 | E57: 35.02 | F57: 105.06 | G57: 73.54 | H57: 30 | I57: =_xlfn.XLOOKUP(Q1_2025[[#This Row],[Artikelnr]],Artikel_prijzen[Artnr],Artikel_prijzen[Groep],"") | J57: =_xlfn.XLOOKUP(Q1_2025[[#This Row],[Artikelnr]],Artikel_prijzen[Artnr],Artikel_prijzen[Prijs 2025],"") | K57: =IF(Q1_2025[[#This Row],[Artikelprijs]]<>"",IF(Q1_2025[[#This Row],[Stuksprijs]]=Q1_2025[[#This Row],[Artikelprijs]],"Prijs gelijk","Prijs wijkt af"),"") | N57: =IF(Q1_2025[[#This Row],[Prijstype]]="Artikelprijs",Q1_2025[[#This Row],[Artikelprijs]],Q1_2025[[#This Row],[Stuksprijs]]) -> 35.02 | O57: =IF(Q1_2025[[#This Row],[Prijstype]]="Artikelprijs",Q1_2025[[#This Row],[Artikelprijs]] * Q1_2025[[#This Row],[Besteld]],Q1_2025[[#This Row],[Brutobedrag]]) -> 105.06 | P57: =IF(Q1_2025[[#This Row],[Prijstype]] = "Artikelprijs",Q1_2025[[#This Row],[Brutobedrag 2]]*(100-Q1_2025[[#This Row],[Relatiekorting percentage]])/100,Q1_2025[[#This Row],[Bruto - Rel.korting]]) -> 73.54
A58: AAO 2025.xls | B58: 5031049 | C58: Prolyte truss H30V 0,5 meter alu | D58: 2 | E58: 35.02 | F58: 70.04 | G58: 49.03 | H58: 30 | I58: =_xlfn.XLOOKUP(Q1_2025[[#This Row],[Artikelnr]],Artikel_prijzen[Artnr],Artikel_prijzen[Groep],"") | J58: =_xlfn.XLOOKUP(Q1_2025[[#This Row],[Artikelnr]],Artikel_prijzen[Artnr],Artikel_prijzen[Prijs 2025],"") | K58: =IF(Q1_2025[[#This Row],[Artikelprijs]]<>"",IF(Q1_2025[[#This Row],[Stuksprijs]]=Q1_2025[[#This Row],[Artikelprijs]],"Prijs gelijk","Prijs wijkt af"),"") | N58: =IF(Q1_2025[[#This Row],[Prijstype]]="Artikelprijs",Q1_2025[[#This Row],[Artikelprijs]],Q1_2025[[#This Row],[Stuksprijs]]) -> 35.02 | O58: =IF(Q1_2025[[#This Row],[Prijstype]]="Artikelprijs",Q1_2025[[#This Row],[Artikelprijs]] * Q1_2025[[#This Row],[Besteld]],Q1_2025[[#This Row],[Brutobedrag]]) -> 70.04 | P58: =IF(Q1_2025[[#This Row],[Prijstype]] = "Artikelprijs",Q1_2025[[#This Row],[Brutobedrag 2]]*(100-Q1_2025[[#This Row],[Relatiekorting percentage]])/100,Q1_2025[[#This Row],[Bruto - Rel.korting]]) -> 49.03
A59: AAO 2025.xls | B59: 5031056 | C59: Prolyte truss H30V Hoek V003 alu | D59: 4 | E59: 69.78 | F59: 279.12 | G59: 195.38 | H59: 30 | I59: =_xlfn.XLOOKUP(Q1_2025[[#This Row],[Artikelnr]],Artikel_prijzen[Artnr],Artikel_prijzen[Groep],"") | J59: =_xlfn.XLOOKUP(Q1_2025[[#This Row],[Artikelnr]],Artikel_prijzen[Artnr],Artikel_prijzen[Prijs 2025],"") | K59: =IF(Q1_2025[[#This Row],[Artikelprijs]]<>"",IF(Q1_2025[[#This Row],[Stuksprijs]]=Q1_2025[[#This Row],[Artikelprijs]],"Prijs gelijk","Prijs wijkt af"),"") | N59: =IF(Q1_2025[[#This Row],[Prijstype]]="Artikelprijs",Q1_2025[[#This Row],[Artikelprijs]],Q1_2025[[#This Row],[Stuksprijs]]) -> 69.78 | O59: =IF(Q1_2025[[#This Row],[Prijstype]]="Artikelprijs",Q1_2025[[#This Row],[Artikelprijs]] * Q1_2025[[#This Row],[Besteld]],Q1_2025[[#This Row],[Brutobedrag]]) -> 279.12 | P59: =IF(Q1_2025[[#This Row],[Prijstype]] = "Artikelprijs",Q1_2025[[#This Row],[Brutobedrag 2]]*(100-Q1_2025[[#This Row],[Relatiekorting percentage]])/100,Q1_2025[[#This Row],[Bruto - Rel.korting]]) -> 195.38
A60: AAO 2025.xls | B60: 5031059 | C60: Prolyte truss H30V Hoek V017 alu | D60: 3 | E60: 69.78 | F60: 209.34 | G60: 146.54 | H60: 30 | I60: =_xlfn.XLOOKUP(Q1_2025[[#This Row],[Artikelnr]],Artikel_prijzen[Artnr],Artikel_prijzen[Groep],"") | J60: =_xlfn.XLOOKUP(Q1_2025[[#This Row],[Artikelnr]],Artikel_prijzen[Artnr],Artikel_prijzen[Prijs 2025],"") | K60: =IF(Q1_2025[[#This Row],[Artikelprijs]]<>"",IF(Q1_2025[[#This Row],[Stuksprijs]]=Q1_2025[[#This Row],[Artikelprijs]],"Prijs gelijk","Prijs wijkt af"),"") | N60: =IF(Q1_2025[[#This Row],[Prijstype]]="Artikelprijs",Q1_2025[[#This Row],[Artikelprijs]],Q1_2025[[#This Row],[Stuksprijs]]) -> 69.78 | O60: =IF(Q1_2025[[#This Row],[Prijstype]]="Artikelprijs",Q1_2025[[#This Row],[Artikelprijs]] * Q1_2025[[#This Row],[Besteld]],Q1_2025[[#This Row],[Brutobedrag]]) -> 209.34 | P60: =IF(Q1_2025[[#This Row],[Prijstype]] = "Artikelprijs",Q1_2025[[#This Row],[Brutobedrag 2]]*(100-Q1_2025[[#This Row],[Relatiekorting percentage]])/100,Q1_2025[[#This Row],[Bruto - Rel.korting]]) -> 146.54
A61: AAO 2025.xls | B61: 5030229 | C61: Motortakel incl. ophangpunt + montage max 250kg | D61: 21 | E61: 303.85 | F61: 6380.85 | G61: 4466.59 | H61: 30 | I61: =_xlfn.XLOOKUP(Q1_2025[[#This Row],[Artikelnr]],Artikel_prijzen[Artnr],Artikel_prijzen[Groep],"") -> Rigging | J61: =_xlfn.XLOOKUP(Q1_2025[[#This Row],[Artikelnr]],Artikel_prijzen[Artnr],Artikel_prijzen[Prijs 2025],"") -> 295 | K61: =IF(Q1_2025[[#This Row],[Artikelprijs]]<>"",IF(Q1_2025[[#This Row],[Stuksprijs]]=Q1_2025[[#This Row],[Artikelprijs]],"Prijs gelijk","Prijs wijkt af"),"") -> Prijs wijkt af | M61: Artikelprijs | N61: =IF(Q1_2025[[#This Row],[Prijstype]]="Artikelprijs",Q1_2025[[#This Row],[Artikelprijs]],Q1_2025[[#This Row],[Stuksprijs]]) -> 295 | O61: =IF(Q1_2025[[#This Row],[Prijstype]]="Artikelprijs",Q1_2025[[#This Row],[Artikelprijs]] * Q1_2025[[#This Row],[Besteld]],Q1_2025[[#This Row],[Brutobedrag]]) -> 6195 | P61: =IF(Q1_2025[[#This Row],[Prijstype]] = "Artikelprijs",Q1_2025[[#This Row],[Brutobedrag 2]]*(100-Q1_2025[[#This Row],[Relatiekorting percentage]])/100,Q1_2025[[#This Row],[Bruto - Rel.korting]]) -> 4336.5
A62: AAO 2025.xls | B62: 5031036 | C62: Prolyte truss H30V 0,5 meter zwart | D62: 8 | E62: 45.32 | F62: 362.56 | G62: 253.79 | H62: 30 | I62: =_xlfn.XLOOKUP(Q1_2025[[#This Row],[Artikelnr]],Artikel_prijzen[Artnr],Artikel_prijzen[Groep],"") | J62: =_xlfn.XLOOKUP(Q1_2025[[#This Row],[Artikelnr]],Artikel_prijzen[Artnr],Artikel_prijzen[Prijs 2025],"") | K62: =IF(Q1_2025[[#This Row],[Artikelprijs]]<>"",IF(Q1_2025[[#This Row],[Stuksprijs]]=Q1_2025[[#This Row],[Artikelprijs]],"Prijs gelijk","Prijs wijkt af"),"") | N62: =IF(Q1_2025[[#This Row],[Prijstype]]="Artikelprijs",Q1_2025[[#This Row],[Artikelprijs]],Q1_2025[[#This Row],[Stuksprijs]]) -> 45.32 | O62: =IF(Q1_2025[[#This Row],[Prijstype]]="Artikelprijs",Q1_2025[[#This Row],[Artikelprijs]] * Q1_2025[[#This Row],[Besteld]],Q1_2025[[#This Row],[Brutobedrag]]) -> 362.56 | P62: =IF(Q1_2025[[#This Row],[Prijstype]] = "Artikelprijs",Q1_2025[[#This Row],[Brutobedrag 2]]*(100-Q1_2025[[#This Row],[Relatiekorting percentage]])/100,Q1_2025[[#This Row],[Bruto - Rel.korting]]) -> 253.79
A63: AAO 2025.xls | B63: 5031038 | C63: Prolyte truss H30V 1 meter zwart | D63: 8 | E63: 68.5 | F63: 548 | G63: 383.6 | H63: 30 | I63: =_xlfn.XLOOKUP(Q1_2025[[#This Row],[Artikelnr]],Artikel_prijzen[Artnr],Artikel_prijzen[Groep],"") | J63: =_xlfn.XLOOKUP(Q1_2025[[#This Row],[Artikelnr]],Artikel_prijzen[Artnr],Artikel_prijzen[Prijs 2025],"") | K63: =IF(Q1_2025[[#This Row],[Artikelprijs]]<>"",IF(Q1_2025[[#This Row],[Stuksprijs]]=Q1_2025[[#This Row],[Artikelprijs]],"Prijs gelijk","Prijs wijkt af"),"") | N63: =IF(Q1_2025[[#This Row],[Prijstype]]="Artikelprijs",Q1_2025[[#This Row],[Artikelprijs]],Q1_2025[[#This Row],[Stuksprijs]]) -> 68.5 | O63: =IF(Q1_2025[[#This Row],[Prijstype]]="Artikelprijs",Q1_2025[[#This Row],[Artikelprijs]] * Q1_2025[[#This Row],[Besteld]],Q1_2025[[#This Row],[Brutobedrag]]) -> 548 | P63: =IF(Q1_2025[[#This Row],[Prijstype]] = "Artikelprijs",Q1_2025[[#This Row],[Brutobedrag 2]]*(100-Q1_2025[[#This Row],[Relatiekorting percentage]])/100,Q1_2025[[#This Row],[Bruto - Rel.korting]]) -> 383.6
A64: AAO 2025.xls | B64: 5031040 | C64: Prolyte truss H30V 3 meter zwart | D64: 8 | E64: 147.81 | F64: 1182.48 | G64: 827.74 | H64: 30 | I64: =_xlfn.XLOOKUP(Q1_2025[[#This Row],[Artikelnr]],Artikel_prijzen[Artnr],Artikel_prijzen[Groep],"") | J64: =_xlfn.XLOOKUP(Q1_2025[[#This Row],[Artikelnr]],Artikel_prijzen[Artnr],Artikel_prijzen[Prijs 2025],"") | K64: =IF(Q1_2025[[#This Row],[Artikelprijs]]<>"",IF(Q1_2025[[#This Row],[Stuksprijs]]=Q1_2025[[#This Row],[Artikelprijs]],"Prijs gelijk","Prijs wijkt af"),"") | N64: =IF(Q1_2025[[#This Row],[Prijstype]]="Artikelprijs",Q1_2025[[#This Row],[Artikelprijs]],Q1_2025[[#This Row],[Stuksprijs]]) -> 147.81 | O64: =IF(Q1_2025[[#This Row],[Prijstype]]="Artikelprijs",Q1_2025[[#This Row],[Artikelprijs]] * Q1_2025[[#This Row],[Besteld]],Q1_2025[[#This Row],[Brutobedrag]]) -> 1182.48 | P64: =IF(Q1_2025[[#This Row],[Prijstype]] = "Artikelprijs",Q1_2025[[#This Row],[Brutobedrag 2]]*(100-Q1_2025[[#This Row],[Relatiekorting percentage]])/100,Q1_2025[[#This Row],[Bruto - Rel.korting]]) -> 827.74
A65: AAO 2025.xls | B65: 2002009 | C65: Prolyte truss H30V Heavy duty Base plate | D65: 8 | E65: 38.93 | F65: 311.44 | G65: 218.01 | H65: 30 | I65: =_xlfn.XLOOKUP(Q1_2025[[#This Row],[Artikelnr]],Artikel_prijzen[Artnr],Artikel_prijzen[Groep],"") | J65: =_xlfn.XLOOKUP(Q1_2025[[#This Row],[Artikelnr]],Artikel_prijzen[Artnr],Artikel_prijzen[Prijs 2025],"") | K65: =IF(Q1_2025[[#This Row],[Artikelprijs]]<>"",IF(Q1_2025[[#This Row],[Stuksprijs]]=Q1_2025[[#This Row],[Artikelprijs]],"Prijs gelijk","Prijs wijkt af"),"") | N65: =IF(Q1_2025[[#This Row],[Prijstype]]="Artikelprijs",Q1_2025[[#This Row],[Artikelprijs]],Q1_2025[[#This Row],[Stuksprijs]]) -> 38.93 | O65: =IF(Q1_2025[[#This Row],[Prijstype]]="Artikelprijs",Q1_2025[[#This Row],[Artikelprijs]] * Q1_2025[[#This Row],[Besteld]],Q1_2025[[#This Row],[Brutobedrag]]) -> 311.44 | P65: =IF(Q1_2025[[#This Row],[Prijstype]] = "Artikelprijs",Q1_2025[[#This Row],[Brutobedrag 2]]*(100-Q1_2025[[#This Row],[Relatiekorting percentage]])/100,Q1_2025[[#This Row],[Bruto - Rel.korting]]) -> 218.01
A66: AAO 2025.xls | B66: 2004040 | C66: Aluminium Buis 1,5 meter Zwart | D66: 4 | E66: 11.03 | F66: 44.12 | G66: 30.88 | H66: 30 | I66: =_xlfn.XLOOKUP(Q1_2025[[#This Row],[Artikelnr]],Artikel_prijzen[Artnr],Artikel_prijzen[Groep],"") | J66: =_xlfn.XLOOKUP(Q1_2025[[#This Row],[Artikelnr]],Artikel_prijzen[Artnr],Artikel_prijzen[Prijs 2025],"") | K66: =IF(Q1_2025[[#This Row],[Artikelprijs]]<>"",IF(Q1_2025[[#This Row],[Stuksprijs]]=Q1_2025[[#This Row],[Artikelprijs]],"Prijs gelijk","Prijs wijkt af"),"") | N66: =IF(Q1_2025[[#This Row],[Prijstype]]="Artikelprijs",Q1_2025[[#This Row],[Artikelprijs]],Q1_2025[[#This Row],[Stuksprijs]]) -> 11.03 | O66: =IF(Q1_2025[[#This Row],[Prijstype]]="Artikelprijs",Q1_2025[[#This Row],[Artikelprijs]] * Q1_2025[[#This Row],[Besteld]],Q1_2025[[#This Row],[Brutobedrag]]) -> 44.12 | P66: =IF(Q1_2025[[#This Row],[Prijstype]] = "Artikelprijs",Q1_2025[[#This Row],[Brutobedrag 2]]*(100-Q1_2025[[#This Row],[Relatiekorting percentage]])/100,Q1_2025[[#This Row],[Bruto - Rel.korting]]) -> 30.88
A67: AAO 2025.xls | B67: 2004064 | C67: Aluminium Buis 4 meter Zwart | D67: 16 | E67: 19.3 | F67: 308.8 | G67: 216.16 | H67: 30 | I67: =_xlfn.XLOOKUP(Q1_2025[[#This Row],[Artikelnr]],Artikel_prijzen[Artnr],Artikel_prijzen[Groep],"") | J67: =_xlfn.XLOOKUP(Q1_2025[[#This Row],[Artikelnr]],Artikel_prijzen[Artnr],Artikel_prijzen[Prijs 2025],"") | K67: =IF(Q1_2025[[#This Row],[Artikelprijs]]<>"",IF(Q1_2025[[#This Row],[Stuksprijs]]=Q1_2025[[#This Row],[Artikelprijs]],"Prijs gelijk","Prijs wijkt af"),"") | N67: =IF(Q1_2025[[#This Row],[Prijstype]]="Artikelprijs",Q1_2025[[#This Row],[Artikelprijs]],Q1_2025[[#This Row],[Stuksprijs]]) -> 19.3 | O67: =IF(Q1_2025[[#This Row],[Prijstype]]="Artikelprijs",Q1_2025[[#This Row],[Artikelprijs]] * Q1_2025[[#This Row],[Besteld]],Q1_2025[[#This Row],[Brutobedrag]]) -> 308.8 | P67: =IF(Q1_2025[[#This Row],[Prijstype]] = "Artikelprijs",Q1_2025[[#This Row],[Brutobedrag 2]]*(100-Q1_2025[[#This Row],[Relatiekorting percentage]])/100,Q1_2025[[#This Row],[Bruto - Rel.korting]]) -> 216.16
A68: AAO 2025.xls | B68: 2004032 | C68: Double C-clamp Zwart | D68: 32 | E68: 16.22 | F68: 519.04 | G68: 363.33 | H68: 30 | I68: =_xlfn.XLOOKUP(Q1_2025[[#This Row],[Artikelnr]],Artikel_prijzen[Artnr],Artikel_prijzen[Groep],"") | J68: =_xlfn.XLOOKUP(Q1_2025[[#This Row],[Artikelnr]],Artikel_prijzen[Artnr],Artikel_prijzen[Prijs 2025],"") | K68: =IF(Q1_2025[[#This Row],[Artikelprijs]]<>"",IF(Q1_2025[[#This Row],[Stuksprijs]]=Q1_2025[[#This Row],[Artikelprijs]],"Prijs gelijk","Prijs wijkt af"),"") | N68: =IF(Q1_2025[[#This Row],[Prijstype]]="Artikelprijs",Q1_2025[[#This Row],[Artikelprijs]],Q1_2025[[#This Row],[Stuksprijs]]) -> 16.22 | O68: =IF(Q1_2025[[#This Row],[Prijstype]]="Artikelprijs",Q1_2025[[#This Row],[Artikelprijs]] * Q1_2025[[#This Row],[Besteld]],Q1_2025[[#This Row],[Brutobedrag]]) -> 519.04 | P68: =IF(Q1_2025[[#This Row],[Prijstype]] = "Artikelprijs",Q1_2025[[#This Row],[Brutobedrag 2]]*(100-Q1_2025[[#This Row],[Relatiekorting percentage]])/100,Q1_2025[[#This Row],[Bruto - Rel.korting]]) -> 363.33
A69: AAO 2025.xls | B69: 2004021 | C69: Double C-clamp | D69: 8 | E69: 16.22 | F69: 129.76 | G69: 90.83 | H69: 30 | I69: =_xlfn.XLOOKUP(Q1_2025[[#This Row],[Artikelnr]],Artikel_prijzen[Artnr],Artikel_prijzen[Groep],"") | J69: =_xlfn.XLOOKUP(Q1_2025[[#This Row],[Artikelnr]],Artikel_prijzen[Artnr],Artikel_prijzen[Prijs 2025],"") | K69: =IF(Q1_2025[[#This Row],[Artikelprijs]]<>"",IF(Q1_2025[[#This Row],[Stuksprijs]]=Q1_2025[[#This Row],[Artikelprijs]],"Prijs gelijk","Prijs wijkt af"),"") | N69: =IF(Q1_2025[[#This Row],[Prijstype]]="Artikelprijs",Q1_2025[[#This Row],[Artikelprijs]],Q1_2025[[#This Row],[Stuksprijs]]) -> 16.22 | O69: =IF(Q1_2025[[#This Row],[Prijstype]]="Artikelprijs",Q1_2025[[#This Row],[Artikelprijs]] * Q1_2025[[#This Row],[Besteld]],Q1_2025[[#This Row],[Brutobedrag]]) -> 129.76 | P69: =IF(Q1_2025[[#This Row],[Prijstype]] = "Artikelprijs",Q1_2025[[#This Row],[Brutobedrag 2]]*(100-Q1_2025[[#This Row],[Relatiekorting percentage]])/100,Q1_2025[[#This Row],[Bruto - Rel.korting]]) -> 90.83
A70: AAO 2025.xls | B70: 5022009 | C70: Stroomtoevoerleiding 3 kW | D70: 6 | E70: 103.75 | F70: 622.5 | G70: 498 | H70: 20 | I70: =_xlfn.XLOOKUP(Q1_2025[[#This Row],[Artikelnr]],Artikel_prijzen[Artnr],Artikel_prijzen[Groep],"") -> Elektra | J70: =_xlfn.XLOOKUP(Q1_2025[[#This Row],[Artikelnr]],Artikel_prijzen[Artnr],Artikel_prijzen[Prijs 2025],"") -> 106.8625 | K70: =IF(Q1_2025[[#This Row],[Artikelprijs]]<>"",IF(Q1_2025[[#This Row],[Stuksprijs]]=Q1_2025[[#This Row],[Artikelprijs]],"Prijs gelijk","Prijs wijkt af"),"") -> Prijs wijkt af | M70: Artikelprijs | N70: =IF(Q1_2025[[#This Row],[Prijstype]]="Artikelprijs",Q1_2025[[#This Row],[Artikelprijs]],Q1_2025[[#This Row],[Stuksprijs]]) -> 106.8625 | O70: =IF(Q1_2025[[#This Row],[Prijstype]]="Artikelprijs",Q1_2025[[#This Row],[Artikelprijs]] * Q1_2025[[#This Row],[Besteld]],Q1_2025[[#This Row],[Brutobedrag]]) -> 641.175 | P70: =IF(Q1_2025[[#This Row],[Prijstype]] = "Artikelprijs",Q1_2025[[#This Row],[Brutobedrag 2]]*(100-Q1_2025[[#This Row],[Relatiekorting percentage]])/100,Q1_2025[[#This Row],[Bruto - Rel.korting]]) -> 512.94
A71: AAO 2025.xls | B71: 5020001 | C71: Wandcontactdoos 1kW | D71: 6 | E71: 29.35 | F71: 176.1 | G71: 132.07 | H71: 25 | I71: =_xlfn.XLOOKUP(Q1_2025[[#This Row],[Artikelnr]],Artikel_prijzen[Artnr],Artikel_prijzen[Groep],"") | J71: =_xlfn.XLOOKUP(Q1_2025[[#This Row],[Artikelnr]],Artikel_prijzen[Artnr],Artikel_prijzen[Prijs 2025],"") | K71: =IF(Q1_2025[[#This Row],[Artikelprijs]]<>"",IF(Q1_2025[[#This Row],[Stuksprijs]]=Q1_2025[[#This Row],[Artikelprijs]],"Prijs gelijk","Prijs wijkt af"),"") | N71: =IF(Q1_2025[[#This Row],[Prijstype]]="Artikelprijs",Q1_2025[[#This Row],[Artikelprijs]],Q1_2025[[#This Row],[Stuksprijs]]) -> 29.35 | O71: =IF(Q1_2025[[#This Row],[Prijstype]]="Artikelprijs",Q1_2025[[#This Row],[Artikelprijs]] * Q1_2025[[#This Row],[Besteld]],Q1_2025[[#This Row],[Brutobedrag]]) -> 176.1 | P71: =IF(Q1_2025[[#This Row],[Prijstype]] = "Artikelprijs",Q1_2025[[#This Row],[Brutobedrag 2]]*(100-Q1_2025[[#This Row],[Relatiekorting percentage]])/100,Q1_2025[[#This Row],[Bruto - Rel.korting]]) -> 132.07
A72: AAO 2025.xls | B72: 5022009 | C72: Stroomtoevoerleiding 3 kW | D72: 4 | E72: 103.75 | F72: 415 | G72: 332 | H72: 20 | I72: =_xlfn.XLOOKUP(Q1_2025[[#This Row],[Artikelnr]],Artikel_prijzen[Artnr],Artikel_prijzen[Groep],"") -> Elektra | J72: =_xlfn.XLOOKUP(Q1_2025[[#This Row],[Artikelnr]],Artikel_prijzen[Artnr],Artikel_prijzen[Prijs 2025],"") -> 106.8625 | K72: =IF(Q1_2025[[#This Row],[Artikelprijs]]<>"",IF(Q1_2025[[#This Row],[Stuksprijs]]=Q1_2025[[#This Row],[Artikelprijs]],"Prijs gelijk","Prijs wijkt af"),"") -> Prijs wijkt af | M72: Artikelprijs | N72: =IF(Q1_2025[[#This Row],[Prijstype]]="Artikelprijs",Q1_2025[[#This Row],[Artikelprijs]],Q1_2025[[#This Row],[Stuksprijs]]) -> 106.8625 | O72: =IF(Q1_2025[[#This Row],[Prijstype]]="Artikelprijs",Q1_2025[[#This Row],[Artikelprijs]] * Q1_2025[[#This Row],[Besteld]],Q1_2025[[#This Row],[Brutobedrag]]) -> 427.45 | P72: =IF(Q1_2025[[#This Row],[Prijstype]] = "Artikelprijs",Q1_2025[[#This Row],[Brutobedrag 2]]*(100-Q1_2025[[#This Row],[Relatiekorting percentage]])/100,Q1_2025[[#This Row],[Bruto - Rel.korting]]) -> 341.96
A73: AAO 2025.xls | B73: 5020001 | C73: Wandcontactdoos 1kW | D73: 6 | E73: 29.35 | F73: 176.1 | G73: 132.07 | H73: 25 | I73: =_xlfn.XLOOKUP(Q1_2025[[#This Row],[Artikelnr]],Artikel_prijzen[Artnr],Artikel_prijzen[Groep],"") | J73: =_xlfn.XLOOKUP(Q1_2025[[#This Row],[Artikelnr]],Artikel_prijzen[Artnr],Artikel_prijzen[Prijs 2025],"") | K73: =IF(Q1_2025[[#This Row],[Artikelprijs]]<>"",IF(Q1_2025[[#This Row],[Stuksprijs]]=Q1_2025[[#This Row],[Artikelprijs]],"Prijs gelijk","Prijs wijkt af"),"") | N73: =IF(Q1_2025[[#This Row],[Prijstype]]="Artikelprijs",Q1_2025[[#This Row],[Artikelprijs]],Q1_2025[[#This Row],[Stuksprijs]]) -> 29.35 | O73: =IF(Q1_2025[[#This Row],[Prijstype]]="Artikelprijs",Q1_2025[[#This Row],[Artikelprijs]] * Q1_2025[[#This Row],[Besteld]],Q1_2025[[#This Row],[Brutobedrag]]) -> 176.1 | P73: =IF(Q1_2025[[#This Row],[Prijstype]] = "Artikelprijs",Q1_2025[[#This Row],[Brutobedrag 2]]*(100-Q1_2025[[#This Row],[Relatiekorting percentage]])/100,Q1_2025[[#This Row],[Bruto - Rel.korting]]) -> 132.07
A74: AAO 2025.xls | B74: 3098016 | C74: Vloerkabelbrug Rubber 2K 98x24x5 zwart geel | D74: 4 | E74: 21 | F74: 84 | G74: 67.2 | H74: 20 | I74: =_xlfn.XLOOKUP(Q1_2025[[#This Row],[Artikelnr]],Artikel_prijzen[Artnr],Artikel_prijzen[Groep],"") | J74: =_xlfn.XLOOKUP(Q1_2025[[#This Row],[Artikelnr]],Artikel_prijzen[Artnr],Artikel_prijzen[Prijs 2025],"") | K74: =IF(Q1_2025[[#This Row],[Artikelprijs]]<>"",IF(Q1_2025[[#This Row],[Stuksprijs]]=Q1_2025[[#This Row],[Artikelprijs]],"Prijs gelijk","Prijs wijkt af"),"") | N74: =IF(Q1_2025[[#This Row],[Prijstype]]="Artikelprijs",Q1_2025[[#This Row],[Artikelprijs]],Q1_2025[[#This Row],[Stuksprijs]]) -> 21 | O74: =IF(Q1_2025[[#This Row],[Prijstype]]="Artikelprijs",Q1_2025[[#This Row],[Artikelprijs]] * Q1_2025[[#This Row],[Besteld]],Q1_2025[[#This Row],[Brutobedrag]]) -> 84 | P74: =IF(Q1_2025[[#This Row],[Prijstype]] = "Artikelprijs",Q1_2025[[#This Row],[Brutobedrag 2]]*(100-Q1_2025[[#This Row],[Relatiekorting percentage]])/100,Q1_2025[[#This Row],[Bruto - Rel.korting]]) -> 67.2
A75: AAO 2025.xls | B75: 5022009 | C75: Stroomtoevoerleiding 3 kW | D75: 4 | E75: 103.75 | F75: 415 | G75: 332 | H75: 20 | I75: =_xlfn.XLOOKUP(Q1_2025[[#This Row],[Artikelnr]],Artikel_prijzen[Artnr],Artikel_prijzen[Groep],"") -> Elektra | J75: =_xlfn.XLOOKUP(Q1_2025[[#This Row],[Artikelnr]],Artikel_prijzen[Artnr],Artikel_prijzen[Prijs 2025],"") -> 106.8625 | K75: =IF(Q1_2025[[#This Row],[Artikelprijs]]<>"",IF(Q1_2025[[#This Row],[Stuksprijs]]=Q1_2025[[#This Row],[Artikelprijs]],"Prijs gelijk","Prijs wijkt af"),"") -> Prijs wijkt af | M75: Artikelprijs | N75: =IF(Q1_2025[[#This Row],[Prijstype]]="Artikelprijs",Q1_2025[[#This Row],[Artikelprijs]],Q1_2025[[#This Row],[Stuksprijs]]) -> 106.8625 | O75: =IF(Q1_2025[[#This Row],[Prijstype]]="Artikelprijs",Q1_2025[[#This Row],[Artikelprijs]] * Q1_2025[[#This Row],[Besteld]],Q1_2025[[#This Row],[Brutobedrag]]) -> 427.45 | P75: =IF(Q1_2025[[#This Row],[Prijstype]] = "Artikelprijs",Q1_2025[[#This Row],[Brutobedrag 2]]*(100-Q1_2025[[#This Row],[Relatiekorting percentage]])/100,Q1_2025[[#This Row],[Bruto - Rel.korting]]) -> 341.96
A76: AAO 2025.xls | B76: 5020001 | C76: Wandcontactdoos 1kW | D76: 4 | E76: 29.35 | F76: 117.4 | G76: 88.05 | H76: 25 | I76: =_xlfn.XLOOKUP(Q1_2025[[#This Row],[Artikelnr]],Artikel_prijzen[Artnr],Artikel_prijzen[Groep],"") | J76: =_xlfn.XLOOKUP(Q1_2025[[#This Row],[Artikelnr]],Artikel_prijzen[Artnr],Artikel_prijzen[Prijs 2025],"") | K76: =IF(Q1_2025[[#This Row],[Artikelprijs]]<>"",IF(Q1_2025[[#This Row],[Stuksprijs]]=Q1_2025[[#This Row],[Artikelprijs]],"Prijs gelijk","Prijs wijkt af"),"") | N76: =IF(Q1_2025[[#This Row],[Prijstype]]="Artikelprijs",Q1_2025[[#This Row],[Artikelprijs]],Q1_2025[[#This Row],[Stuksprijs]]) -> 29.35 | O76: =IF(Q1_2025[[#This Row],[Prijstype]]="Artikelprijs",Q1_2025[[#This Row],[Artikelprijs]] * Q1_2025[[#This Row],[Besteld]],Q1_2025[[#This Row],[Brutobedrag]]) -> 117.4 | P76: =IF(Q1_2025[[#This Row],[Prijstype]] = "Artikelprijs",Q1_2025[[#This Row],[Brutobedrag 2]]*(100-Q1_2025[[#This Row],[Relatiekorting percentage]])/100,Q1_2025[[#This Row],[Bruto - Rel.korting]]) -> 88.05
A77: AAO 2025.xls | B77: 5022009 | C77: Stroomtoevoerleiding 3 kW | D77: 2 | E77: 103.75 | F77: 207.5 | G77: 166 | H77: 20 | I77: =_xlfn.XLOOKUP(Q1_2025[[#This Row],[Artikelnr]],Artikel_prijzen[Artnr],Artikel_prijzen[Groep],"") -> Elektra | J77: =_xlfn.XLOOKUP(Q1_2025[[#This Row],[Artikelnr]],Artikel_prijzen[Artnr],Artikel_prijzen[Prijs 2025],"") -> 106.8625 | K77: =IF(Q1_2025[[#This Row],[Artikelprijs]]<>"",IF(Q1_2025[[#This Row],[Stuksprijs]]=Q1_2025[[#This Row],[Artikelprijs]],"Prijs gelijk","Prijs wijkt af"),"") -> Prijs wijkt af | M77: Artikelprijs | N77: =IF(Q1_2025[[#This Row],[Prijstype]]="Artikelprijs",Q1_2025[[#This Row],[Artikelprijs]],Q1_2025[[#This Row],[Stuksprijs]]) -> 106.8625 | O77: =IF(Q1_2025[[#This Row],[Prijstype]]="Artikelprijs",Q1_2025[[#This Row],[Artikelprijs]] * Q1_2025[[#This Row],[Besteld]],Q1_2025[[#This Row],[Brutobedrag]]) -> 213.725 | P77: =IF(Q1_2025[[#This Row],[Prijstype]] = "Artikelprijs",Q1_2025[[#This Row],[Brutobedrag 2]]*(100-Q1_2025[[#This Row],[Relatiekorting percentage]])/100,Q1_2025[[#This Row],[Bruto - Rel.korting]]) -> 170.98
A78: AAO 2025.xls | B78: 5020001 | C78: Wandcontactdoos 1kW | D78: 4 | E78: 29.35 | F78: 117.4 | G78: 88.05 | H78: 25 | I78: =_xlfn.XLOOKUP(Q1_2025[[#This Row],[Artikelnr]],Artikel_prijzen[Artnr],Artikel_prijzen[Groep],"") | J78: =_xlfn.XLOOKUP(Q1_2025[[#This Row],[Artikelnr]],Artikel_prijzen[Artnr],Artikel_prijzen[Prijs 2025],"") | K78: =IF(Q1_2025[[#This Row],[Artikelprijs]]<>"",IF(Q1_2025[[#This Row],[Stuksprijs]]=Q1_2025[[#This Row],[Artikelprijs]],"Prijs gelijk","Prijs wijkt af"),"") | N78: =IF(Q1_2025[[#This Row],[Prijstype]]="Artikelprijs",Q1_2025[[#This Row],[Artikelprijs]],Q1_2025[[#This Row],[Stuksprijs]]) -> 29.35 | O78: =IF(Q1_2025[[#This Row],[Prijstype]]="Artikelprijs",Q1_2025[[#This Row],[Artikelprijs]] * Q1_2025[[#This Row],[Besteld]],Q1_2025[[#This Row],[Brutobedrag]]) -> 117.4 | P78: =IF(Q1_2025[[#This Row],[Prijstype]] = "Artikelprijs",Q1_2025[[#This Row],[Brutobedrag 2]]*(100-Q1_2025[[#This Row],[Relatiekorting percentage]])/100,Q1_2025[[#This Row],[Bruto - Rel.korting]]) -> 88.05
A79: AAO 2025.xls | B79: 5021007 | C79: Stroomtoevoerleiding 12 kW (incl. CEE 32A) | D79: 8 | E79: 339.9 | F79: 2719.2 | G79: 2175.36 | H79: 20 | I79: =_xlfn.XLOOKUP(Q1_2025[[#This Row],[Artikelnr]],Artikel_prijzen[Artnr],Artikel_prijzen[Groep],"") -> Elektra | J79: =_xlfn.XLOOKUP(Q1_2025[[#This Row],[Artikelnr]],Artikel_prijzen[Artnr],Artikel_prijzen[Prijs 2025],"") -> 339.9 | K79: =IF(Q1_2025[[#This Row],[Artikelprijs]]<>"",IF(Q1_2025[[#This Row],[Stuksprijs]]=Q1_2025[[#This Row],[Artikelprijs]],"Prijs gelijk","Prijs wijkt af"),"") -> Prijs gelijk | M79: Artikelprijs | N79: =IF(Q1_2025[[#This Row],[Prijstype]]="Artikelprijs",Q1_2025[[#This Row],[Artikelprijs]],Q1_2025[[#This Row],[Stuksprijs]]) -> 339.9 | O79: =IF(Q1_2025[[#This Row],[Prijstype]]="Artikelprijs",Q1_2025[[#This Row],[Artikelprijs]] * Q1_2025[[#This Row],[Besteld]],Q1_2025[[#This Row],[Brutobedrag]]) -> 2719.2 | P79: =IF(Q1_2025[[#This Row],[Prijstype]] = "Artikelprijs",Q1_2025[[#This Row],[Brutobedrag 2]]*(100-Q1_2025[[#This Row],[Relatiekorting percentage]])/100,Q1_2025[[#This Row],[Bruto - Rel.korting]]) -> 2175.36
A80: AAO 2025.xls | B80: 5021009 | C80: Stroomtoevoerleiding 15 kW (incl. CEE 32A) | D80: 2 | E80: 386.25 | F80: 772.5 | G80: 618 | H80: 20 | I80: =_xlfn.XLOOKUP(Q1_2025[[#This Row],[Artikelnr]],Artikel_prijzen[Artnr],Artikel_prijzen[Groep],"") -> Elektra | J80: =_xlfn.XLOOKUP(Q1_2025[[#This Row],[Artikelnr]],Artikel_prijzen[Artnr],Artikel_prijzen[Prijs 2025],"") -> 386.25 | K80: =IF(Q1_2025[[#This Row],[Artikelprijs]]<>"",IF(Q1_2025[[#This Row],[Stuksprijs]]=Q1_2025[[#This Row],[Artikelprijs]],"Prijs gelijk","Prijs wijkt af"),"") -> Prijs gelijk | M80: Artikelprijs | N80: =IF(Q1_2025[[#This Row],[Prijstype]]="Artikelprijs",Q1_2025[[#This Row],[Artikelprijs]],Q1_2025[[#This Row],[Stuksprijs]]) -> 386.25 | O80: =IF(Q1_2025[[#This Row],[Prijstype]]="Artikelprijs",Q1_2025[[#This Row],[Artikelprijs]] * Q1_2025[[#This Row],[Besteld]],Q1_2025[[#This Row],[Brutobedrag]]) -> 772.5 | P80: =IF(Q1_2025[[#This Row],[Prijstype]] = "Artikelprijs",Q1_2025[[#This Row],[Brutobedrag 2]]*(100-Q1_2025[[#This Row],[Relatiekorting percentage]])/100,Q1_2025[[#This Row],[Bruto - Rel.korting]]) -> 618
A81: AAO 2025.xls | B81: 5021016 | C81: Stroomtoevoerleiding 30 kW (incl. CEE 63A) | D81: 6 | E81: 602.55 | F81: 3615.3 | G81: 2892.24 | H81: 20 | I81: =_xlfn.XLOOKUP(Q1_2025[[#This Row],[Artikelnr]],Artikel_prijzen[Artnr],Artikel_prijzen[Groep],"") -> Elektra | J81: =_xlfn.XLOOKUP(Q1_2025[[#This Row],[Artikelnr]],Artikel_prijzen[Artnr],Artikel_prijzen[Prijs 2025],"") -> 585 | K81: =IF(Q1_2025[[#This Row],[Artikelprijs]]<>"",IF(Q1_2025[[#This Row],[Stuksprijs]]=Q1_2025[[#This Row],[Artikelprijs]],"Prijs gelijk","Prijs wijkt af"),"") -> Prijs wijkt af | M81: Artikelprijs | N81: =IF(Q1_2025[[#This Row],[Prijstype]]="Artikelprijs",Q1_2025[[#This Row],[Artikelprijs]],Q1_2025[[#This Row],[Stuksprijs]]) -> 585 | O81: =IF(Q1_2025[[#This Row],[Prijstype]]="Artikelprijs",Q1_2025[[#This Row],[Artikelprijs]] * Q1_2025[[#This Row],[Besteld]],Q1_2025[[#This Row],[Brutobedrag]]) -> 3510 | P81: =IF(Q1_2025[[#This Row],[Prijstype]] = "Artikelprijs",Q1_2025[[#This Row],[Brutobedrag 2]]*(100-Q1_2025[[#This Row],[Relatiekorting percentage]])/100,Q1_2025[[#This Row],[Bruto - Rel.korting]]) -> 2808
A82: AAO 2025.xls | B82: 5021007 | C82: Stroomtoevoerleiding 12 kW (incl. CEE 32A) | D82: 4 | E82: 339.9 | F82: 1359.6 | G82: 1087.68 | H82: 20 | I82: =_xlfn.XLOOKUP(Q1_2025[[#This Row],[Artikelnr]],Artikel_prijzen[Artnr],Artikel_prijzen[Groep],"") -> Elektra | J82: =_xlfn.XLOOKUP(Q1_2025[[#This Row],[Artikelnr]],Artikel_prijzen[Artnr],Artikel_prijzen[Prijs 2025],"") -> 339.9 | K82: =IF(Q1_2025[[#This Row],[Artikelprijs]]<>"",IF(Q1_2025[[#This Row],[Stuksprijs]]=Q1_2025[[#This Row],[Artikelprijs]],"Prijs gelijk","Prijs wijkt af"),"") -> Prijs gelijk | M82: Artikelprijs | N82: =IF(Q1_2025[[#This Row],[Prijstype]]="Artikelprijs",Q1_2025[[#This Row],[Artikelprijs]],Q1_2025[[#This Row],[Stuksprijs]]) -> 339.9 | O82: =IF(Q1_2025[[#This Row],[Prijstype]]="Artikelprijs",Q1_2025[[#This Row],[Artikelprijs]] * Q1_2025[[#This Row],[Besteld]],Q1_2025[[#This Row],[Brutobedrag]]) -> 1359.6 | P82: =IF(Q1_2025[[#This Row],[Prijstype]] = "Artikelprijs",Q1_2025[[#This Row],[Brutobedrag 2]]*(100-Q1_2025[[#This Row],[Relatiekorting percentage]])/100,Q1_2025[[#This Row],[Bruto - Rel.korting]]) -> 1087.68
A83: AAO 2025.xls | B83: 5022009 | C83: Stroomtoevoerleiding 3 kW | D83: 1 | E83: 103.75 | F83: 103.75 | G83: 83 | H83: 20 | I83: =_xlfn.XLOOKUP(Q1_2025[[#This Row],[Artikelnr]],Artikel_prijzen[Artnr],Artikel_prijzen[Groep],"") -> Elektra | J83: =_xlfn.XLOOKUP(Q1_2025[[#This Row],[Artikelnr]],Artikel_prijzen[Artnr],Artikel_prijzen[Prijs 2025],"") -> 106.8625 | K83: =IF(Q1_2025[[#This Row],[Artikelprijs]]<>"",IF(Q1_2025[[#This Row],[Stuksprijs]]=Q1_2025[[#This Row],[Artikelprijs]],"Prijs gelijk","Prijs wijkt af"),"") -> Prijs wijkt af | M83: Artikelprijs | N83: =IF(Q1_2025[[#This Row],[Prijstype]]="Artikelprijs",Q1_2025[[#This Row],[Artikelprijs]],Q1_2025[[#This Row],[Stuksprijs]]) -> 106.8625 | O83: =IF(Q1_2025[[#This Row],[Prijstype]]="Artikelprijs",Q1_2025[[#This Row],[Artikelprijs]] * Q1_2025[[#This Row],[Besteld]],Q1_2025[[#This Row],[Brutobedrag]]) -> 106.8625 | P83: =IF(Q1_2025[[#This Row],[Prijstype]] = "Artikelprijs",Q1_2025[[#This Row],[Brutobedrag 2]]*(100-Q1_2025[[#This Row],[Relatiekorting percentage]])/100,Q1_2025[[#This Row],[Bruto - Rel.korting]]) -> 85.49
A84: AAO 2025.xls | B84: 5020001 | C84: Wandcontactdoos 1kW | D84: 1 | E84: 29.35 | F84: 29.35 | G84: 22.01 | H84: 25 | I84: =_xlfn.XLOOKUP(Q1_2025[[#This Row],[Artikelnr]],Artikel_prijzen[Artnr],Artikel_prijzen[Groep],"") | J84: =_xlfn.XLOOKUP(Q1_2025[[#This Row],[Artikelnr]],Artikel_prijzen[Artnr],Artikel_prijzen[Prijs 2025],"") | K84: =IF(Q1_2025[[#This Row],[Artikelprijs]]<>"",IF(Q1_2025[[#This Row],[Stuksprijs]]=Q1_2025[[#This Row],[Artikelprijs]],"Prijs gelijk","Prijs wijkt af"),"") | N84: =IF(Q1_2025[[#This Row],[Prijstype]]="Artikelprijs",Q1_2025[[#This Row],[Artikelprijs]],Q1_2025[[#This Row],[Stuksprijs]]) -> 29.35 | O84: =IF(Q1_2025[[#This Row],[Prijstype]]="Artikelprijs",Q1_2025[[#This Row],[Artikelprijs]] * Q1_2025[[#This Row],[Besteld]],Q1_2025[[#This Row],[Brutobedrag]]) -> 29.35 | P84: =IF(Q1_2025[[#This Row],[Prijstype]] = "Artikelprijs",Q1_2025[[#This Row],[Brutobedrag 2]]*(100-Q1_2025[[#This Row],[Relatiekorting percentage]])/100,Q1_2025[[#This Row],[Bruto - Rel.korting]]) -> 22.01
A85: AAO 2025.xls | B85: 5022009 | C85: Stroomtoevoerleiding 3 kW | D85: 1 | E85: 103.75 | F85: 103.75 | G85: 83 | H85: 20 | I85: =_xlfn.XLOOKUP(Q1_2025[[#This Row],[Artikelnr]],Artikel_prijzen[Artnr],Artikel_prijzen[Groep],"") -> Elektra | J85: =_xlfn.XLOOKUP(Q1_2025[[#This Row],[Artikelnr]],Artikel_prijzen[Artnr],Artikel_prijzen[Prijs 2025],"") -> 106.8625 | K85: =IF(Q1_2025[[#This Row],[Artikelprijs]]<>"",IF(Q1_2025[[#This Row],[Stuksprijs]]=Q1_2025[[#This Row],[Artikelprijs]],"Prijs gelijk","Prijs wijkt af"),"") -> Prijs wijkt af | M85: Artikelprijs | N85: =IF(Q1_2025[[#This Row],[Prijstype]]="Artikelprijs",Q1_2025[[#This Row],[Artikelprijs]],Q1_2025[[#This Row],[Stuksprijs]]) -> 106.8625 | O85: =IF(Q1_2025[[#This Row],[Prijstype]]="Artikelprijs",Q1_2025[[#This Row],[Artikelprijs]] * Q1_2025[[#This Row],[Besteld]],Q1_2025[[#This Row],[Brutobedrag]]) -> 106.8625 | P85: =IF(Q1_2025[[#This Row],[Prijstype]] = "Artikelprijs",Q1_2025[[#This Row],[Brutobedrag 2]]*(100-Q1_2025[[#This Row],[Relatiekorting percentage]])/100,Q1_2025[[#This Row],[Bruto - Rel.korting]]) -> 85.49
A86: AAO 2025.xls | B86: 5020001 | C86: Wandcontactdoos 1kW | D86: 1 | E86: 29.35 | F86: 29.35 | G86: 22.01 | H86: 25 | I86: =_xlfn.XLOOKUP(Q1_2025[[#This Row],[Artikelnr]],Artikel_prijzen[Artnr],Artikel_prijzen[Groep],"") | J86: =_xlfn.XLOOKUP(Q1_2025[[#This Row],[Artikelnr]],Artikel_prijzen[Artnr],Artikel_prijzen[Prijs 2025],"") | K86: =IF(Q1_2025[[#This Row],[Artikelprijs]]<>"",IF(Q1_2025[[#This Row],[Stuksprijs]]=Q1_2025[[#This Row],[Artikelprijs]],"Prijs gelijk","Prijs wijkt af"),"") | N86: =IF(Q1_2025[[#This Row],[Prijstype]]="Artikelprijs",Q1_2025[[#This Row],[Artikelprijs]],Q1_2025[[#This Row],[Stuksprijs]]) -> 29.35 | O86: =IF(Q1_2025[[#This Row],[Prijstype]]="Artikelprijs",Q1_2025[[#This Row],[Artikelprijs]] * Q1_2025[[#This Row],[Besteld]],Q1_2025[[#This Row],[Brutobedrag]]) -> 29.35 | P86: =IF(Q1_2025[[#This Row],[Prijstype]] = "Artikelprijs",Q1_2025[[#This Row],[Brutobedrag 2]]*(100-Q1_2025[[#This Row],[Relatiekorting percentage]])/100,Q1_2025[[#This Row],[Bruto - Rel.korting]]) -> 22.01
A87: AAO 2025.xls | B87: 5022009 | C87: Stroomtoevoerleiding 3 kW | D87: 6 | E87: 103.75 | F87: 622.5 | G87: 498 | H87: 20 | I87: =_xlfn.XLOOKUP(Q1_2025[[#This Row],[Artikelnr]],Artikel_prijzen[Artnr],Artikel_prijzen[Groep],"") -> Elektra | J87: =_xlfn.XLOOKUP(Q1_2025[[#This Row],[Artikelnr]],Artikel_prijzen[Artnr],Artikel_prijzen[Prijs 2025],"") -> 106.8625 | K87: =IF(Q1_2025[[#This Row],[Artikelprijs]]<>"",IF(Q1_2025[[#This Row],[Stuksprijs]]=Q1_2025[[#This Row],[Artikelprijs]],"Prijs gelijk","Prijs wijkt af"),"") -> Prijs wijkt af | M87: Artikelprijs | N87: =IF(Q1_2025[[#This Row],[Prijstype]]="Artikelprijs",Q1_2025[[#This Row],[Artikelprijs]],Q1_2025[[#This Row],[Stuksprijs]]) -> 106.8625 | O87: =IF(Q1_2025[[#This Row],[Prijstype]]="Artikelprijs",Q1_2025[[#This Row],[Artikelprijs]] * Q1_2025[[#This Row],[Besteld]],Q1_2025[[#This Row],[Brutobedrag]]) -> 641.175 | P87: =IF(Q1_2025[[#This Row],[Prijstype]] = "Artikelprijs",Q1_2025[[#This Row],[Brutobedrag 2]]*(100-Q1_2025[[#This Row],[Relatiekorting percentage]])/100,Q1_2025[[#This Row],[Bruto - Rel.korting]]) -> 512.94
A88: AAO 2025.xls | B88: 5020001 | C88: Wandcontactdoos 1kW | D88: 6 | E88: 29.35 | F88: 176.1 | G88: 132.07 | H88: 25 | I88: =_xlfn.XLOOKUP(Q1_2025[[#This Row],[Artikelnr]],Artikel_prijzen[Artnr],Artikel_prijzen[Groep],"") | J88: =_xlfn.XLOOKUP(Q1_2025[[#This Row],[Artikelnr]],Artikel_prijzen[Artnr],Artikel_prijzen[Prijs 2025],"") | K88: =IF(Q1_2025[[#This Row],[Artikelprijs]]<>"",IF(Q1_2025[[#This Row],[Stuksprijs]]=Q1_2025[[#This Row],[Artikelprijs]],"Prijs gelijk","Prijs wijkt af"),"") | N88: =IF(Q1_2025[[#This Row],[Prijstype]]="Artikelprijs",Q1_2025[[#This Row],[Artikelprijs]],Q1_2025[[#This Row],[Stuksprijs]]) -> 29.35 | O88: =IF(Q1_2025[[#This Row],[Prijstype]]="Artikelprijs",Q1_2025[[#This Row],[Artikelprijs]] * Q1_2025[[#This Row],[Besteld]],Q1_2025[[#This Row],[Brutobedrag]]) -> 176.1 | P88: =IF(Q1_2025[[#This Row],[Prijstype]] = "Artikelprijs",Q1_2025[[#This Row],[Brutobedrag 2]]*(100-Q1_2025[[#This Row],[Relatiekorting percentage]])/100,Q1_2025[[#This Row],[Bruto - Rel.korting]]) -> 132.07
A89: AAO 2025.xls | B89: 3098016 | C89: Vloerkabelbrug Rubber 2K 98x24x5 zwart geel | D89: 5 | E89: 21 | F89: 105 | G89: 84 | H89: 20 | I89: =_xlfn.XLOOKUP(Q1_2025[[#This Row],[Artikelnr]],Artikel_prijzen[Artnr],Artikel_prijzen[Groep],"") | J89: =_xlfn.XLOOKUP(Q1_2025[[#This Row],[Artikelnr]],Artikel_prijzen[Artnr],Artikel_prijzen[Prijs 2025],"") | K89: =IF(Q1_2025[[#This Row],[Artikelprijs]]<>"",IF(Q1_2025[[#This Row],[Stuksprijs]]=Q1_2025[[#This Row],[Artikelprijs]],"Prijs gelijk","Prijs wijkt af"),"") | N89: =IF(Q1_2025[[#This Row],[Prijstype]]="Artikelprijs",Q1_2025[[#This Row],[Artikelprijs]],Q1_2025[[#This Row],[Stuksprijs]]) -> 21 | O89: =IF(Q1_2025[[#This Row],[Prijstype]]="Artikelprijs",Q1_2025[[#This Row],[Artikelprijs]] * Q1_2025[[#This Row],[Besteld]],Q1_2025[[#This Row],[Brutobedrag]]) -> 105 | P89: =IF(Q1_2025[[#This Row],[Prijstype]] = "Artikelprijs",Q1_2025[[#This Row],[Brutobedrag 2]]*(100-Q1_2025[[#This Row],[Relatiekorting percentage]])/100,Q1_2025[[#This Row],[Bruto - Rel.korting]]) -> 84
A90: AAO 2025.xls | B90: 5022009 | C90: Stroomtoevoerleiding 3 kW | D90: 6 | E90: 103.75 | F90: 622.5 | G90: 498 | H90: 20 | I90: =_xlfn.XLOOKUP(Q1_2025[[#This Row],[Artikelnr]],Artikel_prijzen[Artnr],Artikel_prijzen[Groep],"") -> Elektra | J90: =_xlfn.XLOOKUP(Q1_2025[[#This Row],[Artikelnr]],Artikel_prijzen[Artnr],Artikel_prijzen[Prijs 2025],"") -> 106.8625 | K90: =IF(Q1_2025[[#This Row],[Artikelprijs]]<>"",IF(Q1_2025[[#This Row],[Stuksprijs]]=Q1_2025[[#This Row],[Artikelprijs]],"Prijs gelijk","Prijs wijkt af"),"") -> Prijs wijkt af | M90: Artikelprijs | N90: =IF(Q1_2025[[#This Row],[Prijstype]]="Artikelprijs",Q1_2025[[#This Row],[Artikelprijs]],Q1_2025[[#This Row],[Stuksprijs]]) -> 106.8625 | O90: =IF(Q1_2025[[#This Row],[Prijstype]]="Artikelprijs",Q1_2025[[#This Row],[Artikelprijs]] * Q1_2025[[#This Row],[Besteld]],Q1_2025[[#This Row],[Brutobedrag]]) -> 641.175 | P90: =IF(Q1_2025[[#This Row],[Prijstype]] = "Artikelprijs",Q1_2025[[#This Row],[Brutobedrag 2]]*(100-Q1_2025[[#This Row],[Relatiekorting percentage]])/100,Q1_2025[[#This Row],[Bruto - Rel.korting]]) -> 512.94
A91: AAO 2025.xls | B91: 5020001 | C91: Wandcontactdoos 1kW | D91: 6 | E91: 29.35 | F91: 176.1 | G91: 132.07 | H91: 25 | I91: =_xlfn.XLOOKUP(Q1_2025[[#This Row],[Artikelnr]],Artikel_prijzen[Artnr],Artikel_prijzen[Groep],"") | J91: =_xlfn.XLOOKUP(Q1_2025[[#This Row],[Artikelnr]],Artikel_prijzen[Artnr],Artikel_prijzen[Prijs 2025],"") | K91: =IF(Q1_2025[[#This Row],[Artikelprijs]]<>"",IF(Q1_2025[[#This Row],[Stuksprijs]]=Q1_2025[[#This Row],[Artikelprijs]],"Prijs gelijk","Prijs wijkt af"),"") | N91: =IF(Q1_2025[[#This Row],[Prijstype]]="Artikelprijs",Q1_2025[[#This Row],[Artikelprijs]],Q1_2025[[#This Row],[Stuksprijs]]) -> 29.35 | O91: =IF(Q1_2025[[#This Row],[Prijstype]]="Artikelprijs",Q1_2025[[#This Row],[Artikelprijs]] * Q1_2025[[#This Row],[Besteld]],Q1_2025[[#This Row],[Brutobedrag]]) -> 176.1 | P91: =IF(Q1_2025[[#This Row],[Prijstype]] = "Artikelprijs",Q1_2025[[#This Row],[Brutobedrag 2]]*(100-Q1_2025[[#This Row],[Relatiekorting percentage]])/100,Q1_2025[[#This Row],[Bruto - Rel.korting]]) -> 132.07
A92: AAO 2025.xls | B92: 5022009 | C92: Stroomtoevoerleiding 3 kW | D92: 4 | E92: 103.75 | F92: 415 | G92: 332 | H92: 20 | I92: =_xlfn.XLOOKUP(Q1_2025[[#This Row],[Artikelnr]],Artikel_prijzen[Artnr],Artikel_prijzen[Groep],"") -> Elektra | J92: =_xlfn.XLOOKUP(Q1_2025[[#This Row],[Artikelnr]],Artikel_prijzen[Artnr],Artikel_prijzen[Prijs 2025],"") -> 106.8625 | K92: =IF(Q1_2025[[#This Row],[Artikelprijs]]<>"",IF(Q1_2025[[#This Row],[Stuksprijs]]=Q1_2025[[#This Row],[Artikelprijs]],"Prijs gelijk","Prijs wijkt af"),"") -> Prijs wijkt af | M92: Artikelprijs | N92: =IF(Q1_2025[[#This Row],[Prijstype]]="Artikelprijs",Q1_2025[[#This Row],[Artikelprijs]],Q1_2025[[#This Row],[Stuksprijs]]) -> 106.8625 | O92: =IF(Q1_2025[[#This Row],[Prijstype]]="Artikelprijs",Q1_2025[[#This Row],[Artikelprijs]] * Q1_2025[[#This Row],[Besteld]],Q1_2025[[#This Row],[Brutobedrag]]) -> 427.45 | P92: =IF(Q1_2025[[#This Row],[Prijstype]] = "Artikelprijs",Q1_2025[[#This Row],[Brutobedrag 2]]*(100-Q1_2025[[#This Row],[Relatiekorting percentage]])/100,Q1_2025[[#This Row],[Bruto - Rel.korting]]) -> 341.96
A93: AAO 2025.xls | B93: 5020001 | C93: Wandcontactdoos 1kW | D93: 4 | E93: 29.35 | F93: 117.4 | G93: 88.05 | H93: 25 | I93: =_xlfn.XLOOKUP(Q1_2025[[#This Row],[Artikelnr]],Artikel_prijzen[Artnr],Artikel_prijzen[Groep],"") | J93: =_xlfn.XLOOKUP(Q1_2025[[#This Row],[Artikelnr]],Artikel_prijzen[Artnr],Artikel_prijzen[Prijs 2025],"") | K93: =IF(Q1_2025[[#This Row],[Artikelprijs]]<>"",IF(Q1_2025[[#This Row],[Stuksprijs]]=Q1_2025[[#This Row],[Artikelprijs]],"Prijs gelijk","Prijs wijkt af"),"") | N93: =IF(Q1_2025[[#This Row],[Prijstype]]="Artikelprijs",Q1_2025[[#This Row],[Artikelprijs]],Q1_2025[[#This Row],[Stuksprijs]]) -> 29.35 | O93: =IF(Q1_2025[[#This Row],[Prijstype]]="Artikelprijs",Q1_2025[[#This Row],[Artikelprijs]] * Q1_2025[[#This Row],[Besteld]],Q1_2025[[#This Row],[Brutobedrag]]) -> 117.4 | P93: =IF(Q1_2025[[#This Row],[Prijstype]] = "Artikelprijs",Q1_2025[[#This Row],[Brutobedrag 2]]*(100-Q1_2025[[#This Row],[Relatiekorting percentage]])/100,Q1_2025[[#This Row],[Bruto - Rel.korting]]) -> 88.05
A94: AAO 2025.xls | B94: 3098016 | C94: Vloerkabelbrug Rubber 2K 98x24x5 zwart geel | D94: 4 | E94: 21 | F94: 84 | G94: 67.2 | H94: 20 | I94: =_xlfn.XLOOKUP(Q1_2025[[#This Row],[Artikelnr]],Artikel_prijzen[Artnr],Artikel_prijzen[Groep],"") | J94: =_xlfn.XLOOKUP(Q1_2025[[#This Row],[Artikelnr]],Artikel_prijzen[Artnr],Artikel_prijzen[Prijs 2025],"") | K94: =IF(Q1_2025[[#This Row],[Artikelprijs]]<>"",IF(Q1_2025[[#This Row],[Stuksprijs]]=Q1_2025[[#This Row],[Artikelprijs]],"Prijs gelijk","Prijs wijkt af"),"") | N94: =IF(Q1_2025[[#This Row],[Prijstype]]="Artikelprijs",Q1_2025[[#This Row],[Artikelprijs]],Q1_2025[[#This Row],[Stuksprijs]]) -> 21 | O94: =IF(Q1_2025[[#This Row],[Prijstype]]="Artikelprijs",Q1_2025[[#This Row],[Artikelprijs]] * Q1_2025[[#This Row],[Besteld]],Q1_2025[[#This Row],[Brutobedrag]]) -> 84 | P94: =IF(Q1_2025[[#This Row],[Prijstype]] = "Artikelprijs",Q1_2025[[#This Row],[Brutobedrag 2]]*(100-Q1_2025[[#This Row],[Relatiekorting percentage]])/100,Q1_2025[[#This Row],[Bruto - Rel.korting]]) -> 67.2
A95: AAO 2025.xls | B95: 5021009 | C95: Stroomtoevoerleiding 15 kW (incl. CEE 32A) | D95: 1 | E95: 386.25 | F95: 386.25 | G95: 309 | H95: 20 | I95: =_xlfn.XLOOKUP(Q1_2025[[#This Row],[Artikelnr]],Artikel_prijzen[Artnr],Artikel_prijzen[Groep],"") -> Elektra | J95: =_xlfn.XLOOKUP(Q1_2025[[#This Row],[Artikelnr]],Artikel_prijzen[Artnr],Artikel_prijzen[Prijs 2025],"") -> 386.25 | K95: =IF(Q1_2025[[#This Row],[Artikelprijs]]<>"",IF(Q1_2025[[#This Row],[Stuksprijs]]=Q1_2025[[#This Row],[Artikelprijs]],"Prijs gelijk","Prijs wijkt af"),"") -> Prijs gelijk | M95: Artikelprijs | N95: =IF(Q1_2025[[#This Row],[Prijstype]]="Artikelprijs",Q1_2025[[#This Row],[Artikelprijs]],Q1_2025[[#This Row],[Stuksprijs]]) -> 386.25 | O95: =IF(Q1_2025[[#This Row],[Prijstype]]="Artikelprijs",Q1_2025[[#This Row],[Artikelprijs]] * Q1_2025[[#This Row],[Besteld]],Q1_2025[[#This Row],[Brutobedrag]]) -> 386.25 | P95: =IF(Q1_2025[[#This Row],[Prijstype]] = "Artikelprijs",Q1_2025[[#This Row],[Brutobedrag 2]]*(100-Q1_2025[[#This Row],[Relatiekorting percentage]])/100,Q1_2025[[#This Row],[Bruto - Rel.korting]]) -> 309
A96: AAO 2025.xls | B96: 3098016 | C96: Vloerkabelbrug Rubber 2K 98x24x5 zwart geel | D96: 5 | E96: 21 | F96: 105 | G96: 84 | H96: 20 | I96: =_xlfn.XLOOKUP(Q1_2025[[#This Row],[Artikelnr]],Artikel_prijzen[Artnr],Artikel_prijzen[Groep],"") | J96: =_xlfn.XLOOKUP(Q1_2025[[#This Row],[Artikelnr]],Artikel_prijzen[Artnr],Artikel_prijzen[Prijs 2025],"") | K96: =IF(Q1_2025[[#This Row],[Artikelprijs]]<>"",IF(Q1_2025[[#This Row],[Stuksprijs]]=Q1_2025[[#This Row],[Artikelprijs]],"Prijs gelijk","Prijs wijkt af"),"") | N96: =IF(Q1_2025[[#This Row],[Prijstype]]="Artikelprijs",Q1_2025[[#This Row],[Artikelprijs]],Q1_2025[[#This Row],[Stuksprijs]]) -> 21 | O96: =IF(Q1_2025[[#This Row],[Prijstype]]="Artikelprijs",Q1_2025[[#This Row],[Artikelprijs]] * Q1_2025[[#This Row],[Besteld]],Q1_2025[[#This Row],[Brutobedrag]]) -> 105 | P96: =IF(Q1_2025[[#This Row],[Prijstype]] = "Artikelprijs",Q1_2025[[#This Row],[Brutobedrag 2]]*(100-Q1_2025[[#This Row],[Relatiekorting percentage]])/100,Q1_2025[[#This Row],[Bruto - Rel.korting]]) -> 84
A97: AAO 2025.xls | B97: 5022009 | C97: Stroomtoevoerleiding 3 kW | D97: 1 | E97: 103.75 | F97: 103.75 | G97: 83 | H97: 20 | I97: =_xlfn.XLOOKUP(Q1_2025[[#This Row],[Artikelnr]],Artikel_prijzen[Artnr],Artikel_prijzen[Groep],"") -> Elektra | J97: =_xlfn.XLOOKUP(Q1_2025[[#This Row],[Artikelnr]],Artikel_prijzen[Artnr],Artikel_prijzen[Prijs 2025],"") -> 106.8625 | K97: =IF(Q1_2025[[#This Row],[Artikelprijs]]<>"",IF(Q1_2025[[#This Row],[Stuksprijs]]=Q1_2025[[#This Row],[Artikelprijs]],"Prijs gelijk","Prijs wijkt af"),"") -> Prijs wijkt af | M97: Artikelprijs | N97: =IF(Q1_2025[[#This Row],[Prijstype]]="Artikelprijs",Q1_2025[[#This Row],[Artikelprijs]],Q1_2025[[#This Row],[Stuksprijs]]) -> 106.8625 | O97: =IF(Q1_2025[[#This Row],[Prijstype]]="Artikelprijs",Q1_2025[[#This Row],[Artikelprijs]] * Q1_2025[[#This Row],[Besteld]],Q1_2025[[#This Row],[Brutobedrag]]) -> 106.8625 | P97: =IF(Q1_2025[[#This Row],[Prijstype]] = "Artikelprijs",Q1_2025[[#This Row],[Brutobedrag 2]]*(100-Q1_2025[[#This Row],[Relatiekorting percentage]])/100,Q1_2025[[#This Row],[Bruto - Rel.korting]]) -> 85.49
A98: AAO 2025.xls | B98: 5020001 | C98: Wandcontactdoos 1kW | D98: 1 | E98: 29.35 | F98: 29.35 | G98: 22.01 | H98: 25 | I98: =_xlfn.XLOOKUP(Q1_2025[[#This Row],[Artikelnr]],Artikel_prijzen[Artnr],Artikel_prijzen[Groep],"") | J98: =_xlfn.XLOOKUP(Q1_2025[[#This Row],[Artikelnr]],Artikel_prijzen[Artnr],Artikel_prijzen[Prijs 2025],"") | K98: =IF(Q1_2025[[#This Row],[Artikelprijs]]<>"",IF(Q1_2025[[#This Row],[Stuksprijs]]=Q1_2025[[#This Row],[Artikelprijs]],"Prijs gelijk","Prijs wijkt af"),"") | N98: =IF(Q1_2025[[#This Row],[Prijstype]]="Artikelprijs",Q1_2025[[#This Row],[Artikelprijs]],Q1_2025[[#This Row],[Stuksprijs]]) -> 29.35 | O98: =IF(Q1_2025[[#This Row],[Prijstype]]="Artikelprijs",Q1_2025[[#This Row],[Artikelprijs]] * Q1_2025[[#This Row],[Besteld]],Q1_2025[[#This Row],[Brutobedrag]]) -> 29.35 | P98: =IF(Q1_2025[[#This Row],[Prijstype]] = "Artikelprijs",Q1_2025[[#This Row],[Brutobedrag 2]]*(100-Q1_2025[[#This Row],[Relatiekorting percentage]])/100,Q1_2025[[#This Row],[Bruto - Rel.korting]]) -> 22.01
A99: AAO 2025.xls | B99: 5020008 | C99: Rail + 2 spots LED 20W tri color - 3000K/4000K | D99: 8 | E99: 32.96 | F99: 263.68 | G99: 197.76 | H99: 25 | I99: =_xlfn.XLOOKUP(Q1_2025[[#This Row],[Artikelnr]],Artikel_prijzen[Artnr],Artikel_prijzen[Groep],"") | J99: =_xlfn.XLOOKUP(Q1_2025[[#This Row],[Artikelnr]],Artikel_prijzen[Artnr],Artikel_prijzen[Prijs 2025],"") | K99: =IF(Q1_2025[[#This Row],[Artikelprijs]]<>"",IF(Q1_2025[[#This Row],[Stuksprijs]]=Q1_2025[[#This Row],[Artikelprijs]],"Prijs gelijk","Prijs wijkt af"),"") | N99: =IF(Q1_2025[[#This Row],[Prijstype]]="Artikelprijs",Q1_2025[[#This Row],[Artikelprijs]],Q1_2025[[#This Row],[Stuksprijs]]) -> 32.96 | O99: =IF(Q1_2025[[#This Row],[Prijstype]]="Artikelprijs",Q1_2025[[#This Row],[Artikelprijs]] * Q1_2025[[#This Row],[Besteld]],Q1_2025[[#This Row],[Brutobedrag]]) -> 263.68 | P99: =IF(Q1_2025[[#This Row],[Prijstype]] = "Artikelprijs",Q1_2025[[#This Row],[Brutobedrag 2]]*(100-Q1_2025[[#This Row],[Relatiekorting percentage]])/100,Q1_2025[[#This Row],[Bruto - Rel.korting]]) -> 197.76
A100: AAO 2025.xls | B100: 5020008 | C100: Rail + 2 spots LED 20W tri color - 3000K/4000K | D100: 14 | E100: 32.96 | F100: 461.44 | G100: 346.08 | H100: 25 | I100: =_xlfn.XLOOKUP(Q1_2025[[#This Row],[Artikelnr]],Artikel_prijzen[Artnr],Artikel_prijzen[Groep],"") | J100: =_xlfn.XLOOKUP(Q1_2025[[#This Row],[Artikelnr]],Artikel_prijzen[Artnr],Artikel_prijzen[Prijs 2025],"") | K100: =IF(Q1_2025[[#This Row],[Artikelprijs]]<>"",IF(Q1_2025[[#This Row],[Stuksprijs]]=Q1_2025[[#This Row],[Artikelprijs]],"Prijs gelijk","Prijs wijkt af"),"") | N100: =IF(Q1_2025[[#This Row],[Prijstype]]="Artikelprijs",Q1_2025[[#This Row],[Artikelprijs]],Q1_2025[[#This Row],[Stuksprijs]]) -> 32.96 | O100: =IF(Q1_2025[[#This Row],[Prijstype]]="Artikelprijs",Q1_2025[[#This Row],[Artikelprijs]] * Q1_2025[[#This Row],[Besteld]],Q1_2025[[#This Row],[Brutobedrag]]) -> 461.44 | P100: =IF(Q1_2025[[#This Row],[Prijstype]] = "Artikelprijs",Q1_2025[[#This Row],[Brutobedrag 2]]*(100-Q1_2025[[#This Row],[Relatiekorting percentage]])/100,Q1_2025[[#This Row],[Bruto - Rel.korting]]) -> 346.08
...

Sheet Q1 Provisie
B1: Provisie berekening Q1 2025
B4: Provisie | C4: Percentage | D4: Omzet | E4: Provisie
B5: Elektra | C5: 0.23 | D5: =C34 -> 352164.59 | E5: =C5*D5 -> 80997.857
B6: Rigging | C6: 0.16 | D6: =D34 -> 284656.04 | E6: =C6*D6 -> 45544.966
B7: AV | C7: 0.15 | D7: =E34 -> 33369.99 | E7: =C7*D7 -> 5005.4985
B8: Omzet Q1 | C8: 0.05 | D8: =G34 -> 1139176.7 | E8: =D8*C8 -> 56958.835
B9: Omzet voor het jaar | D9: =D8 -> 1139176.7
B10: Omzetstaffels 6,5% en 8% worden in Q4 verrekend
B11: TOTALE PROVISIE | E11: =SUM(E5:E10) -> 188507.16
B14: Evenementen Q1 2025 | C14: Elektra omzet | D14: Rigging omzet | E14: AV omzet | F14: Geen groep omzet | G14: Totaal Omzet | H14: Elektra provisie | I14: Rigging provisie | J14: AV Provisie
B15: {=_xlfn.UNIQUE(Q1_2025[Evenement])} -> 4AM Festival.xls | C15: =SUMIFS(Q1_2025[Bruto-Rel. korting 2],Q1_2025[Evenement],B15,Q1_2025[Groep],$B$5) -> 417.15 | D15: =SUMIFS(Q1_2025[Bruto-Rel. korting 2],Q1_2025[Evenement],B15,Q1_2025[Groep],$B$6) -> 0 | E15: =SUMIFS(Q1_2025[Bruto-Rel. korting 2],Q1_2025[Evenement],B15,Q1_2025[Groep],$B$7) -> 0 | F15: =SUMIFS(Q1_2025[Bruto-Rel. korting 2],Q1_2025[Evenement],B15,Q1_2025[Groep],"") -> 0 | G15: =SUM(C15:F15) -> 417.15 | H15: =C15*$C$5 -> 95.9445 | I15: =D15*$C$6 -> 0 | J15: =E15*$C$7 -> 0
B16: AAO 2025.xls | C16: =SUMIFS(Q1_2025[Bruto-Rel. korting 2],Q1_2025[Evenement],B16,Q1_2025[Groep],$B$5) -> 51534.646 | D16: =SUMIFS(Q1_2025[Bruto-Rel. korting 2],Q1_2025[Evenement],B16,Q1_2025[Groep],$B$6) -> 82566.6 | E16: =SUMIFS(Q1_2025[Bruto-Rel. korting 2],Q1_2025[Evenement],B16,Q1_2025[Groep],$B$7) -> 0 | F16: =SUMIFS(Q1_2025[Bruto-Rel. korting 2],Q1_2025[Evenement],B16,Q1_2025[Groep],"") -> 242117.48 | G16: =SUM(C16:F16) -> 376218.73 | H16: =C16*$C$5 -> 11852.969 | I16: =D16*$C$6 -> 13210.656 | J16: =E16*$C$7 -> 0
B17: Art Rotterdam 2025.xls | C17: =SUMIFS(Q1_2025[Bruto-Rel. korting 2],Q1_2025[Evenement],B17,Q1_2025[Groep],$B$5) -> 29774.6 | D17: =SUMIFS(Q1_2025[Bruto-Rel. korting 2],Q1_2025[Evenement],B17,Q1_2025[Groep],$B$6) -> 29483.75 | E17: =SUMIFS(Q1_2025[Bruto-Rel. korting 2],Q1_2025[Evenement],B17,Q1_2025[Groep],$B$7) -> 0 | F17: =SUMIFS(Q1_2025[Bruto-Rel. korting 2],Q1_2025[Evenement],B17,Q1_2025[Groep],"") -> 45506.49 | G17: =SUM(C17:F17) -> 104764.84 | H17: =C17*$C$5 -> 6848.158 | I17: =D17*$C$6 -> 4717.4 | J17: =E17*$C$7 -> 0
B18: C2C Festival 2025.xls | C18: =SUMIFS(Q1_2025[Bruto-Rel. korting 2],Q1_2025[Evenement],B18,Q1_2025[Groep],$B$5) -> 2207.79 | D18: =SUMIFS(Q1_2025[Bruto-Rel. korting 2],Q1_2025[Evenement],B18,Q1_2025[Groep],$B$6) -> 0 | E18: =SUMIFS(Q1_2025[Bruto-Rel. korting 2],Q1_2025[Evenement],B18,Q1_2025[Groep],$B$7) -> 0 | F18: =SUMIFS(Q1_2025[Bruto-Rel. korting 2],Q1_2025[Evenement],B18,Q1_2025[Groep],"") -> 0 | G18: =SUM(C18:F18) -> 2207.79 | H18: =C18*$C$5 -> 507.7917 | I18: =D18*$C$6 -> 0 | J18: =E18*$C$7 -> 0
B19: Comic Film & Manga Fest 2025.xls | C19: =SUMIFS(Q1_2025[Bruto-Rel. korting 2],Q1_2025[Evenement],B19,Q1_2025[Groep],$B$5) -> 2412.775 | D19: =SUMIFS(Q1_2025[Bruto-Rel. korting 2],Q1_2025[Evenement],B19,Q1_2025[Groep],$B$6) -> 0 | E19: =SUMIFS(Q1_2025[Bruto-Rel. korting 2],Q1_2025[Evenement],B19,Q1_2025[Groep],$B$7) -> 0 | F19: =SUMIFS(Q1_2025[Bruto-Rel. korting 2],Q1_2025[Evenement],B19,Q1_2025[Groep],"") -> 0 | G19: =SUM(C19:F19) -> 2412.775 | H19: =C19*$C$5 -> 554.93825 | I19: =D19*$C$6 -> 0 | J19: =E19*$C$7 -> 0
B20: Holiday on Ice 2025.xls | C20: =SUMIFS(Q1_2025[Bruto-Rel. korting 2],Q1_2025[Evenement],B20,Q1_2025[Groep],$B$5) -> 5265.44 | D20: =SUMIFS(Q1_2025[Bruto-Rel. korting 2],Q1_2025[Evenement],B20,Q1_2025[Groep],$B$6) -> 0 | E20: =SUMIFS(Q1_2025[Bruto-Rel. korting 2],Q1_2025[Evenement],B20,Q1_2025[Groep],$B$7) -> 0 | F20: =SUMIFS(Q1_2025[Bruto-Rel. korting 2],Q1_2025[Evenement],B20,Q1_2025[Groep],"") -> 6481.26 | G20: =SUM(C20:F20) -> 11746.7 | H20: =C20*$C$5 -> 1211.0512 | I20: =D20*$C$6 -> 0 | J20: =E20*$C$7 -> 0
B21: Hyrox 2025.xls | C21: =SUMIFS(Q1_2025[Bruto-Rel. korting 2],Q1_2025[Evenement],B21,Q1_2025[Groep],$B$5) -> 12116 | D21: =SUMIFS(Q1_2025[Bruto-Rel. korting 2],Q1_2025[Evenement],B21,Q1_2025[Groep],$B$6) -> 0 | E21: =SUMIFS(Q1_2025[Bruto-Rel. korting 2],Q1_2025[Evenement],B21,Q1_2025[Groep],$B$7) -> 0 | F21: =SUMIFS(Q1_2025[Bruto-Rel. korting 2],Q1_2025[Evenement],B21,Q1_2025[Groep],"") -> 704.85 | G21: =SUM(C21:F21) -> 12820.85 | H21: =C21*$C$5 -> 2786.68 | I21: =D21*$C$6 -> 0 | J21: =E21*$C$7 -> 0
B22: Infratech 2025 - Elektra.xls | C22: =SUMIFS(Q1_2025[Bruto-Rel. korting 2],Q1_2025[Evenement],B22,Q1_2025[Groep],$B$5) -> 89237.79 | D22: =SUMIFS(Q1_2025[Bruto-Rel. korting 2],Q1_2025[Evenement],B22,Q1_2025[Groep],$B$6) -> 0 | E22: =SUMIFS(Q1_2025[Bruto-Rel. korting 2],Q1_2025[Evenement],B22,Q1_2025[Groep],$B$7) -> 18480 | F22: =SUMIFS(Q1_2025[Bruto-Rel. korting 2],Q1_2025[Evenement],B22,Q1_2025[Groep],"") -> 14861.99 | G22: =SUM(C22:F22) -> 122579.78 | H22: =C22*$C$5 -> 20524.692 | I22: =D22*$C$6 -> 0 | J22: =E22*$C$7 -> 2772
B23: Infratech 2025 - Rigging.xls | C23: =SUMIFS(Q1_2025[Bruto-Rel. korting 2],Q1_2025[Evenement],B23,Q1_2025[Groep],$B$5) -> 700 | D23: =SUMIFS(Q1_2025[Bruto-Rel. korting 2],Q1_2025[Evenement],B23,Q1_2025[Groep],$B$6) -> 106779.4 | E23: =SUMIFS(Q1_2025[Bruto-Rel. korting 2],Q1_2025[Evenement],B23,Q1_2025[Groep],$B$7) -> 0 | F23: =SUMIFS(Q1_2025[Bruto-Rel. korting 2],Q1_2025[Evenement],B23,Q1_2025[Groep],"") -> 3635.49 | G23: =SUM(C23:F23) -> 111114.89 | H23: =C23*$C$5 -> 161 | I23: =D23*$C$6 -> 17084.704 | J23: =E23*$C$7 -> 0
B24: Infratech 2025 - Stands.xls | C24: =SUMIFS(Q1_2025[Bruto-Rel. korting 2],Q1_2025[Evenement],B24,Q1_2025[Groep],$B$5) -> 12190.05 | D24: =SUMIFS(Q1_2025[Bruto-Rel. korting 2],Q1_2025[Evenement],B24,Q1_2025[Groep],$B$6) -> 21567 | E24: =SUMIFS(Q1_2025[Bruto-Rel. korting 2],Q1_2025[Evenement],B24,Q1_2025[Groep],$B$7) -> 8693 | F24: =SUMIFS(Q1_2025[Bruto-Rel. korting 2],Q1_2025[Evenement],B24,Q1_2025[Groep],"") -> 117399.71 | G24: =SUM(C24:F24) -> 159849.76 | H24: =C24*$C$5 -> 2803.7115 | I24: =D24*$C$6 -> 3450.72 | J24: =E24*$C$7 -> 1303.95
B25: Record & CD Fair 2025.xls | C25: =SUMIFS(Q1_2025[Bruto-Rel. korting 2],Q1_2025[Evenement],B25,Q1_2025[Groep],$B$5) -> 154.5 | D25: =SUMIFS(Q1_2025[Bruto-Rel. korting 2],Q1_2025[Evenement],B25,Q1_2025[Groep],$B$6) -> 0 | E25: =SUMIFS(Q1_2025[Bruto-Rel. korting 2],Q1_2025[Evenement],B25,Q1_2025[Groep],$B$7) -> 0 | F25: =SUMIFS(Q1_2025[Bruto-Rel. korting 2],Q1_2025[Evenement],B25,Q1_2025[Groep],"") -> 0 | G25: =SUM(C25:F25) -> 154.5 | H25: =C25*$C$5 -> 35.535 | I25: =D25*$C$6 -> 0 | J25: =E25*$C$7 -> 0
B26: Rotterdam Rave 2025.xls | C26: =SUMIFS(Q1_2025[Bruto-Rel. korting 2],Q1_2025[Evenement],B26,Q1_2025[Groep],$B$5) -> 4990.03 | D26: =SUMIFS(Q1_2025[Bruto-Rel. korting 2],Q1_2025[Evenement],B26,Q1_2025[Groep],$B$6) -> 0 | E26: =SUMIFS(Q1_2025[Bruto-Rel. korting 2],Q1_2025[Evenement],B26,Q1_2025[Groep],$B$7) -> 0 | F26: =SUMIFS(Q1_2025[Bruto-Rel. korting 2],Q1_2025[Evenement],B26,Q1_2025[Groep],"") -> 2607.52 | G26: =SUM(C26:F26) -> 7597.55 | H26: =C26*$C$5 -> 1147.7069 | I26: =D26*$C$6 -> 0 | J26: =E26*$C$7 -> 0
B27: Rotterdam Tattoo Convention 2025.xls | C27: =SUMIFS(Q1_2025[Bruto-Rel. korting 2],Q1_2025[Evenement],B27,Q1_2025[Groep],$B$5) -> 19611.56 | D27: =SUMIFS(Q1_2025[Bruto-Rel. korting 2],Q1_2025[Evenement],B27,Q1_2025[Groep],$B$6) -> 1215.4 | E27: =SUMIFS(Q1_2025[Bruto-Rel. korting 2],Q1_2025[Evenement],B27,Q1_2025[Groep],$B$7) -> 0 | F27: =SUMIFS(Q1_2025[Bruto-Rel. korting 2],Q1_2025[Evenement],B27,Q1_2025[Groep],"") -> 0 | G27: =SUM(C27:F27) -> 20826.96 | H27: =C27*$C$5 -> 4510.6588 | I27: =D27*$C$6 -> 194.464 | J27: =E27*$C$7 -> 0
... B33: VVAL 2025.xls | C33: =SUMIFS(Q1_2025[Bruto-Rel. korting 2],Q1_2025[Evenement],B33,Q1_2025[Groep],$B$5) -> 19826.212 | D33: =SUMIFS(Q1_2025[Bruto-Rel. korting 2],Q1_2025[Evenement],B33,Q1_2025[Groep],$B$6) -> 0 | E33: =SUMIFS(Q1_2025[Bruto-Rel. korting 2],Q1_2025[Evenement],B33,Q1_2025[Groep],$B$7) -> 0 | F33: =SUMIFS(Q1_2025[Bruto-Rel. korting 2],Q1_2025[Evenement],B33,Q1_2025[Groep],"") -> 20454.06 | G33: =SUM(C33:F33) -> 40280.272 | H33: =C33*$C$5 -> 4560.0289 | I33: =D33*$C$6 -> 0 | J33: =E33*$C$7 -> 0
B34: TOTAAL | C34: =SUM(C15:C33) -> 352164.59 | D34: =SUM(D15:D33) -> 284656.04 | E34: =SUM(E15:E33) -> 33369.99 | F34: =SUM(F15:F33) -> 473681.12 | G34: 1139176.7 | H34: =SUM(H15:H33) -> 80997.857 | I34: =SUM(I15:I33) -> 45544.966 | J34: =SUM(J15:J33) -> 5005.4985

Sheet Q1 PT
A3: Evenement | B3: Artikelnr | C3: Omschrijving | D3: Groep | E3: Som van Besteld
A4: 4AM Festival.xls | B4: 5021001 | C4: Stroomaansl. 3kW + WCD + Verbruik 1d | D4: Elektra | E4: 3
A5: AAO 2025.xls | B5: 1001013 | C5: Railspot Lumina LED 20w tri color zilver | E5: 20
B6: 1001021 | C6: Railspot Milano LED 30w 3000K zwart dimbaar | E6: 83
B7: 1001028 | C7: Railspot Lumina LED 20w tri color zilver | E7: 20
B8: 1001031 | C8: Railspot Lumina LED 30w 4000K zwart | E8: 6
B9: 1002019 | C9: Pendel LED Luxa 30 watt/ 3000K zilver | E9: 10
B10: 1002020 | C10: Pendel LED Luxa 30 watt/ 4000K zilver | E10: 10
B11: 1002032 | C11: Pendel LED Luxa 30 watt tri color zilver | E11: 22
B12: 1003011 | C12: Inbouwspot Lika LED 9W 4000K Ø 83mm wit | E12: 17
B13: 1003012 | C13: Inbouwspot Lika LED 9W 3000K Ø 83mm wit | E13: 3
B14: 1003030 | C14: Inbouwspot Vivaro LED 5W 4000K Ø 75mm wit | E14: 4
B15: 1005013 | C15: Hanglamp Kooldraad LED | E15: 50
B16: 1005015 | C16: Hanglamp enkelt vitting E27 zwart | E16: 10
B17: 1007023 | C17: Prikkabel 10m LED wit | E17: 2
... B28: 1098001 | C28: Blacklight armatuur | E28: 4
C29: Luxibel BPar180RGBW v2 | E29: 67
C30: Magneten tbv spanningsrail | E30: 50
B31: 1098002 | C31: Credit factuur | E31: 1
B32: 1099009 | C32: Spectral M800 LED 65 watt RGBW | E32: 1
B33: 2001027 | C33: Prolyte truss Spacer 3 cm | E33: 4
B34: 2001041 | C34: Prolyte truss X30D 0,29 meter zwart | E34: 2
B35: 2001045 | C35: Prolyte truss X30D 2 meter zwart | E35: 34
B36: 2001048 | C36: Prolyte truss X30D Hoek D003 zwart | E36: 4
B37: 2001088 | C37: Prolyte cirkeltruss X30D 8 meter zwart | E37: 1
B38: 2001089 | C38: Prolyte truss X30D 3 meter zwart | E38: 62
B39: 2001090 | C39: Prolyte truss X30D 3 meter zwart | E39: 34
B40: 2002005 | C40: Prolyte truss H30V 1 meter | E40: 1
B41: 2002006 | C41: Prolyte truss H30V 2 meter | E41: 9
B42: 2002007 | C42: Prolyte truss H30V 3 meter | E42: 14
... B77: 2098001 | C77: Gordijnen 3 x 6 mtr. | E77: 4
C78: Gordijnen 3 x 8 mtr. | E78: 25
C79: TRNH34-T(M) - (50x50 T-stuk) | E79: 4
B80: 3001025 | C80: Verlengkabel shuko 3x2.5mm² 10 meter | E80: 11
B81: 3001031 | C81: Verloop 32A/63A | E81: 4
B82: 3001035 | C82: Wieland verlengkabel 1 meter 3x 1,5mm² | E82: 476
B83: 3001036 | C83: Wieland verlengkabel 2 meter 3x 1,5mm² | E83: 740
B84: 3001037 | C84: Wieland verlengkabel 3 meter 3x 1,5mm² | E84: 770
B85: 3001038 | C85: Wieland verlengkabel 5 meter 3x 1,5mm² | E85: 742
B86: 3001039 | C86: Wieland verlengkabel 7,5 meter 3x 1,5mm² | E86: 45
B87: 3001040 | C87: Wieland verlengkabel 10 meter 3x 1,5mm² | E87: 325
B88: 3001041 | C88: Wieland verlengkabel (vloerkabel) 10 meter 3x 2,5mm² | E88: 37
B89: 3001042 | C89: Wieland verlengkabel (vloerkabel) 15 meter 3x 2,5mm² | E89: 41
B90: 3001043 | C90: Wieland verlengkabel (vloerkabel) 25 meter 3x 2,5mm² | E90: 45
B91: 3001044 | C91: Wieland wandcontactdoos tot 3 Kw | E91: 174
... B112: 3002022 | C112: Groepenkast (wieland) 32A tot 20 kw 9x230V 1x 400V/16A | E112: 8
C113: Groepenkast 32A tot 20 kw 9x230V 1x 400V/16A | E113: 19
B114: 3002024 | C114: Groepenkast 63A tot 40 kw 12x230V/1x400V/16A 1x400V/32A | E114: 1
B115: 3002029 | C115: Groepenkast (hangkast) 32A tot 20 kw 6xCEE 230V | E115: 19
B116: 3002030 | C116: Groepenkast (Cubes) 32A tot 20 kw 6xCEE 230V | E116: 13
B117: 3002031 | C117: Verdeelslof (SA blok) 32A --> 1x 230V/16A | E117: 55
B118: 3002032 | C118: Groepenkast (Cubes) 63A tot 40 kw | E118: 9
B119: 3002033 | C119: Groepenkast (Cubes) 125A tot 80kw 2x63A, 4x32A, 6x230V/CEE | E119: 2
B120: 3002039 | C120: VDK(Cube) 32A/20kW 6x230V-CEE | E120: 3
B121: 3098001 | C121: Floodlight HQI - 2000W Asym. | E121: 40
C122: LED Moving Head Clay Paky Sharpy X-Frame | E122: 12
C123: Luxibel wash BP9Z | E123: 24
C124: Whole hog Licht regeltafel | E124: 1
B125: 3098016 | C125: Vloerkabelbrug Rubber 2K 98x24x5 zwart geel | E125: 25
B126: 4001058 | C126: Apple i-Pad Air2 64Gb Space Gray | E126: 1
B127: 4001071 | C127: Versterker Crown XLi800 800w 2 kanaal | E127: 1
B128: 4001131 | C128: Lichttafel showtec SDC 6 | E128: 6
C129: Lichttafel showtec SDS 6 | E129: 1
B130: 4001223 | C130: DMX Booster DB1-8/ 3p | E130: 1
B131: 4001224 | C131: DMX Booster DB1-4/ 3-5p | E131: 12
B132: 4001227 | C132: Wired hand microfoon Sennheiser e835s | E132: 2
B133: 4001282 | C133: Speaker Amate audio N26P | E133: 6
B134: 4098001 | C134: Audio - Centrale regie | E134: 1
C135: Audio bekabeling | E135: 3
C136: Audio cables | E136: 2
C137: DB technologies DVX DM15 als dj monitor | E137: 1
C138: EV ZX1 + trussmount | E138: 6
C139: Grand MA3 Licht regeltafel | E139: 1
C140: Labgruppen FP2600, versterker | E140: 1
C141: L-acoustics LA4X incl. AES card | E141: 3
C142: L-acoustics SB18m | E142: 1
C143: L-acoustics X12 | E143: 6
C144: L-acoustics xl12 longbracket x12 | E144: 6
C145: Pioneer CDJ-3000 | E145: 2
C146: Pioneer DJM-900 nexus2 | E146: 1
... C151: Streamdeck XL incl. Hp laptop | E151: 1
B152: 4801003 | C152: Nooduitgang verlichting | E152: 10
B153: 5010001 | C153: Bekabeling armaturen | E153: 4
C154: Camita LED Light, 24 gr, 15W.,3000K | E154: 526
C155: CLF - Ares Led wash 43gr | E155: 50
C156: ETC S4 - Junior Profile 575W 25-50° zoom | E156: 12
C157: Grand MA3 Licht regeltafel | E157: 1
C158: Hanglamp enkelt vitting E27 zwart | E158: 56
C159: LED ARRI FRESNEL L7C P.O. - BLACK - 4 LEAF BARNDOOR | E159: 16
C160: Lichtbron Kooldraad LED | E160: 56
C161: Luxibel B PAR180RGBW | E161: 44
C162: Luxibel B Par180RGBW v2 | E162: 10
C163: Luxibel wash BP9Z | E163: 53
C164: Mini Led profile raillight - FELI0290 | E164: 34
C165: Railspot 3Sintra 15W 3000K zwart dimbaar | E165: 188
C166: Railspot Sintra LED 15w 3000K zwart | E166: 59
B167: 5010013 | C167: Railspot LED 30W tri color 3000K/4000K | E167: 36
B168: 5010016 | C168: Pendel LED Luxa 30 watt/ 3000K zilver | E168: 46
C169: Pendel LED Luxa 30W / 3000K zilver | E169: 32
B170: 5010017 | C170: Pendel LED Luxa 30W / 4000K zilver | E170: 148
...

Sheet Q2 2025
A1: Evenement | B1: Artikelnr | C1: Omschrijving | D1: Besteld | E1: Stuksprijs | F1: Brutobedrag | G1: Bruto - Rel.korting | H1: Relatiekorting percentage | I1: Groep | J1: Artikelprijs | K1: Vergelijk | L1: Relatie korting | M1: Prijs 2 | N1: Brutobedrag 2 | O1: Bruto-Rel. korting 2
A2: Alpe du Huez Elektra - 2025.xls | B2: 5022022 | C2: Power supply 80 kW (incl. CEE 125A & Power Consumption) 2d | D2: 1 | E2: 1655.72 | F2: 1655.72 | G2: 1241.79 | H2: 25 | I2: =_xlfn.XLOOKUP(Q2_2025[[#This Row],[Artikelnr]],Artikel_prijzen[Artnr],Artikel_prijzen[Groep],"") -> Elektra | J2: =_xlfn.XLOOKUP(Q2_2025[[#This Row],[Artikelnr]],Artikel_prijzen[Artnr],Artikel_prijzen[Prijs 2025],"") -> 1100 | K2: =IF(Q2_2025[[#This Row],[Artikelprijs]]<>"",IF(Q2_2025[[#This Row],[Stuksprijs]]=Q2_2025[[#This Row],[Artikelprijs]],"Prijs gelijk","Prijs wijkt af"),"") -> Prijs wijkt af | L2: =IF(Q2_2025[[#This Row],[Relatiekorting percentage]]=0, "Nvt", IF(Q2_2025[[#This Row],[Brutobedrag 2]] < Q2_2025[[#This Row],[Bruto - Rel.korting]], "Nee", "Ja")) -> Nee | M2: =IF(Q2_2025[[#This Row],[Artikelprijs]]<>"",Q2_2025[[#This Row],[Artikelprijs]],Q2_2025[[#This Row],[Stuksprijs]]) -> 1100 | N2: =Q2_2025[[#This Row],[Besteld]]*Q2_2025[[#This Row],[Prijs 2]] -> 1100 | O2: =IF(Q2_2025[[#This Row],[Brutobedrag 2]]<Q2_2025[[#This Row],[Bruto - Rel.korting]],Q2_2025[[#This Row],[Brutobedrag 2]],Q2_2025[[#This Row],[Brutobedrag 2]]*(100-Q2_2025[[#This Row],[Relatiekorting percentage]])/100) -> 1100
A3: Alpe du Huez Elektra - 2025.xls | B3: 5022014 | C3: Power supply 9 kW (incl. CEE 32A & Power Consumption) 2d | D3: 1 | E3: 377.11 | F3: 377.11 | G3: 282.83 | H3: 25 | I3: =_xlfn.XLOOKUP(Q2_2025[[#This Row],[Artikelnr]],Artikel_prijzen[Artnr],Artikel_prijzen[Groep],"") -> Elektra | J3: =_xlfn.XLOOKUP(Q2_2025[[#This Row],[Artikelnr]],Artikel_prijzen[Artnr],Artikel_prijzen[Prijs 2025],"") -> 298.7 | K3: =IF(Q2_2025[[#This Row],[Artikelprijs]]<>"",IF(Q2_2025[[#This Row],[Stuksprijs]]=Q2_2025[[#This Row],[Artikelprijs]],"Prijs gelijk","Prijs wijkt af"),"") -> Prijs wijkt af | L3: =IF(Q2_2025[[#This Row],[Relatiekorting percentage]]=0, "Nvt", IF(Q2_2025[[#This Row],[Brutobedrag 2]] < Q2_2025[[#This Row],[Bruto - Rel.korting]], "Nee", "Ja")) -> Ja | M3: =IF(Q2_2025[[#This Row],[Artikelprijs]]<>"",Q2_2025[[#This Row],[Artikelprijs]],Q2_2025[[#This Row],[Stuksprijs]]) -> 298.7 | N3: =Q2_2025[[#This Row],[Besteld]]*Q2_2025[[#This Row],[Prijs 2]] -> 298.7 | O3: =IF(Q2_2025[[#This Row],[Brutobedrag 2]]<Q2_2025[[#This Row],[Bruto - Rel.korting]],Q2_2025[[#This Row],[Brutobedrag 2]],Q2_2025[[#This Row],[Brutobedrag 2]]*(100-Q2_2025[[#This Row],[Relatiekorting percentage]])/100) -> 224.025
A4: Alpe du Huez Elektra - 2025.xls | B4: 5022017 | C4: Power supply 20 kW (incl. CEE 32A & Power Consumption) 2d | D4: 1 | E4: 632.59 | F4: 632.59 | G4: 474.44 | H4: 25 | I4: =_xlfn.XLOOKUP(Q2_2025[[#This Row],[Artikelnr]],Artikel_prijzen[Artnr],Artikel_prijzen[Groep],"") -> Elektra | J4: =_xlfn.XLOOKUP(Q2_2025[[#This Row],[Artikelnr]],Artikel_prijzen[Artnr],Artikel_prijzen[Prijs 2025],"") -> 458.35 | K4: =IF(Q2_2025[[#This Row],[Artikelprijs]]<>"",IF(Q2_2025[[#This Row],[Stuksprijs]]=Q2_2025[[#This Row],[Artikelprijs]],"Prijs gelijk","Prijs wijkt af"),"") -> Prijs wijkt af | L4: =IF(Q2_2025[[#This Row],[Relatiekorting percentage]]=0, "Nvt", IF(Q2_2025[[#This Row],[Brutobedrag 2]] < Q2_2025[[#This Row],[Bruto - Rel.korting]], "Nee", "Ja")) -> Nee | M4: =IF(Q2_2025[[#This Row],[Artikelprijs]]<>"",Q2_2025[[#This Row],[Artikelprijs]],Q2_2025[[#This Row],[Stuksprijs]]) -> 458.35 | N4: =Q2_2025[[#This Row],[Besteld]]*Q2_2025[[#This Row],[Prijs 2]] -> 458.35 | O4: =IF(Q2_2025[[#This Row],[Brutobedrag 2]]<Q2_2025[[#This Row],[Bruto - Rel.korting]],Q2_2025[[#This Row],[Brutobedrag 2]],Q2_2025[[#This Row],[Brutobedrag 2]]*(100-Q2_2025[[#This Row],[Relatiekorting percentage]])/100) -> 458.35
A5: Alpe du Huez Elektra - 2025.xls | B5: 5021001 | C5: Stroomaansl. 3kW + WCD + Verbruik 1d | D5: 1 | E5: 154.5 | F5: 154.5 | G5: 115.87 | H5: 25 | I5: =_xlfn.XLOOKUP(Q2_2025[[#This Row],[Artikelnr]],Artikel_prijzen[Artnr],Artikel_prijzen[Groep],"") -> Elektra | J5: =_xlfn.XLOOKUP(Q2_2025[[#This Row],[Artikelnr]],Artikel_prijzen[Artnr],Artikel_prijzen[Prijs 2025],"") -> 106.8625 | K5: =IF(Q2_2025[[#This Row],[Artikelprijs]]<>"",IF(Q2_2025[[#This Row],[Stuksprijs]]=Q2_2025[[#This Row],[Artikelprijs]],"Prijs gelijk","Prijs wijkt af"),"") -> Prijs wijkt af | L5: =IF(Q2_2025[[#This Row],[Relatiekorting percentage]]=0, "Nvt", IF(Q2_2025[[#This Row],[Brutobedrag 2]] < Q2_2025[[#This Row],[Bruto - Rel.korting]], "Nee", "Ja")) -> Nee | M5: =IF(Q2_2025[[#This Row],[Artikelprijs]]<>"",Q2_2025[[#This Row],[Artikelprijs]],Q2_2025[[#This Row],[Stuksprijs]]) -> 106.8625 | N5: =Q2_2025[[#This Row],[Besteld]]*Q2_2025[[#This Row],[Prijs 2]] -> 106.8625 | O5: =IF(Q2_2025[[#This Row],[Brutobedrag 2]]<Q2_2025[[#This Row],[Bruto - Rel.korting]],Q2_2025[[#This Row],[Brutobedrag 2]],Q2_2025[[#This Row],[Brutobedrag 2]]*(100-Q2_2025[[#This Row],[Relatiekorting percentage]])/100) -> 106.8625
A6: Alpe du Huez Elektra - 2025.xls | B6: 5021001 | C6: Stroomaansl. 3kW + WCD + Verbruik 1d | D6: 1 | E6: 154.5 | F6: 154.5 | G6: 115.87 | H6: 25 | I6: =_xlfn.XLOOKUP(Q2_2025[[#This Row],[Artikelnr]],Artikel_prijzen[Artnr],Artikel_prijzen[Groep],"") -> Elektra | J6: =_xlfn.XLOOKUP(Q2_2025[[#This Row],[Artikelnr]],Artikel_prijzen[Artnr],Artikel_prijzen[Prijs 2025],"") -> 106.8625 | K6: =IF(Q2_2025[[#This Row],[Artikelprijs]]<>"",IF(Q2_2025[[#This Row],[Stuksprijs]]=Q2_2025[[#This Row],[Artikelprijs]],"Prijs gelijk","Prijs wijkt af"),"") -> Prijs wijkt af | L6: =IF(Q2_2025[[#This Row],[Relatiekorting percentage]]=0, "Nvt", IF(Q2_2025[[#This Row],[Brutobedrag 2]] < Q2_2025[[#This Row],[Bruto - Rel.korting]], "Nee", "Ja")) -> Nee | M6: =IF(Q2_2025[[#This Row],[Artikelprijs]]<>"",Q2_2025[[#This Row],[Artikelprijs]],Q2_2025[[#This Row],[Stuksprijs]]) -> 106.8625 | N6: =Q2_2025[[#This Row],[Besteld]]*Q2_2025[[#This Row],[Prijs 2]] -> 106.8625 | O6: =IF(Q2_2025[[#This Row],[Brutobedrag 2]]<Q2_2025[[#This Row],[Bruto - Rel.korting]],Q2_2025[[#This Row],[Brutobedrag 2]],Q2_2025[[#This Row],[Brutobedrag 2]]*(100-Q2_2025[[#This Row],[Relatiekorting percentage]])/100) -> 106.8625
A7: Alpe du Huez Elektra - 2025.xls | B7: 5021001 | C7: Stroomaansl. 3kW + WCD + Verbruik 1d | D7: 4 | E7: 154.5 | F7: 618 | G7: 463.5 | H7: 25 | I7: =_xlfn.XLOOKUP(Q2_2025[[#This Row],[Artikelnr]],Artikel_prijzen[Artnr],Artikel_prijzen[Groep],"") -> Elektra | J7: =_xlfn.XLOOKUP(Q2_2025[[#This Row],[Artikelnr]],Artikel_prijzen[Artnr],Artikel_prijzen[Prijs 2025],"") -> 106.8625 | K7: =IF(Q2_2025[[#This Row],[Artikelprijs]]<>"",IF(Q2_2025[[#This Row],[Stuksprijs]]=Q2_2025[[#This Row],[Artikelprijs]],"Prijs gelijk","Prijs wijkt af"),"") -> Prijs wijkt af | L7: =IF(Q2_2025[[#This Row],[Relatiekorting percentage]]=0, "Nvt", IF(Q2_2025[[#This Row],[Brutobedrag 2]] < Q2_2025[[#This Row],[Bruto - Rel.korting]], "Nee", "Ja")) -> Nee | M7: =IF(Q2_2025[[#This Row],[Artikelprijs]]<>"",Q2_2025[[#This Row],[Artikelprijs]],Q2_2025[[#This Row],[Stuksprijs]]) -> 106.8625 | N7: =Q2_2025[[#This Row],[Besteld]]*Q2_2025[[#This Row],[Prijs 2]] -> 427.45 | O7: =IF(Q2_2025[[#This Row],[Brutobedrag 2]]<Q2_2025[[#This Row],[Bruto - Rel.korting]],Q2_2025[[#This Row],[Brutobedrag 2]],Q2_2025[[#This Row],[Brutobedrag 2]]*(100-Q2_2025[[#This Row],[Relatiekorting percentage]])/100) -> 427.45
A8: Alpe du Huez Elektra - 2025.xls | B8: 5021001 | C8: Stroomaansl. 3kW + WCD + Verbruik 1d | D8: 1 | E8: 154.5 | F8: 154.5 | G8: 115.87 | H8: 25 | I8: =_xlfn.XLOOKUP(Q2_2025[[#This Row],[Artikelnr]],Artikel_prijzen[Artnr],Artikel_prijzen[Groep],"") -> Elektra | J8: =_xlfn.XLOOKUP(Q2_2025[[#This Row],[Artikelnr]],Artikel_prijzen[Artnr],Artikel_prijzen[Prijs 2025],"") -> 106.8625 | K8: =IF(Q2_2025[[#This Row],[Artikelprijs]]<>"",IF(Q2_2025[[#This Row],[Stuksprijs]]=Q2_2025[[#This Row],[Artikelprijs]],"Prijs gelijk","Prijs wijkt af"),"") -> Prijs wijkt af | L8: =IF(Q2_2025[[#This Row],[Relatiekorting percentage]]=0, "Nvt", IF(Q2_2025[[#This Row],[Brutobedrag 2]] < Q2_2025[[#This Row],[Bruto - Rel.korting]], "Nee", "Ja")) -> Nee | M8: =IF(Q2_2025[[#This Row],[Artikelprijs]]<>"",Q2_2025[[#This Row],[Artikelprijs]],Q2_2025[[#This Row],[Stuksprijs]]) -> 106.8625 | N8: =Q2_2025[[#This Row],[Besteld]]*Q2_2025[[#This Row],[Prijs 2]] -> 106.8625 | O8: =IF(Q2_2025[[#This Row],[Brutobedrag 2]]<Q2_2025[[#This Row],[Bruto - Rel.korting]],Q2_2025[[#This Row],[Brutobedrag 2]],Q2_2025[[#This Row],[Brutobedrag 2]]*(100-Q2_2025[[#This Row],[Relatiekorting percentage]])/100) -> 106.8625
A9: Alpe du Huez Elektra - 2025.xls | B9: 5021001 | C9: Stroomaansl. 3kW + WCD + Verbruik 1d | D9: 1 | E9: 154.5 | F9: 154.5 | G9: 115.87 | H9: 25 | I9: =_xlfn.XLOOKUP(Q2_2025[[#This Row],[Artikelnr]],Artikel_prijzen[Artnr],Artikel_prijzen[Groep],"") -> Elektra | J9: =_xlfn.XLOOKUP(Q2_2025[[#This Row],[Artikelnr]],Artikel_prijzen[Artnr],Artikel_prijzen[Prijs 2025],"") -> 106.8625 | K9: =IF(Q2_2025[[#This Row],[Artikelprijs]]<>"",IF(Q2_2025[[#This Row],[Stuksprijs]]=Q2_2025[[#This Row],[Artikelprijs]],"Prijs gelijk","Prijs wijkt af"),"") -> Prijs wijkt af | L9: =IF(Q2_2025[[#This Row],[Relatiekorting percentage]]=0, "Nvt", IF(Q2_2025[[#This Row],[Brutobedrag 2]] < Q2_2025[[#This Row],[Bruto - Rel.korting]], "Nee", "Ja")) -> Nee | M9: =IF(Q2_2025[[#This Row],[Artikelprijs]]<>"",Q2_2025[[#This Row],[Artikelprijs]],Q2_2025[[#This Row],[Stuksprijs]]) -> 106.8625 | N9: =Q2_2025[[#This Row],[Besteld]]*Q2_2025[[#This Row],[Prijs 2]] -> 106.8625 | O9: =IF(Q2_2025[[#This Row],[Brutobedrag 2]]<Q2_2025[[#This Row],[Bruto - Rel.korting]],Q2_2025[[#This Row],[Brutobedrag 2]],Q2_2025[[#This Row],[Brutobedrag 2]]*(100-Q2_2025[[#This Row],[Relatiekorting percentage]])/100) -> 106.8625
A10: Alpe du Huez Elektra - 2025.xls | B10: 5021001 | C10: Stroomaansl. 3kW + WCD + Verbruik 1d | D10: 1 | E10: 154.5 | F10: 154.5 | G10: 115.87 | H10: 25 | I10: =_xlfn.XLOOKUP(Q2_2025[[#This Row],[Artikelnr]],Artikel_prijzen[Artnr],Artikel_prijzen[Groep],"") -> Elektra | J10: =_xlfn.XLOOKUP(Q2_2025[[#This Row],[Artikelnr]],Artikel_prijzen[Artnr],Artikel_prijzen[Prijs 2025],"") -> 106.8625 | K10: =IF(Q2_2025[[#This Row],[Artikelprijs]]<>"",IF(Q2_2025[[#This Row],[Stuksprijs]]=Q2_2025[[#This Row],[Artikelprijs]],"Prijs gelijk","Prijs wijkt af"),"") -> Prijs wijkt af | L10: =IF(Q2_2025[[#This Row],[Relatiekorting percentage]]=0, "Nvt", IF(Q2_2025[[#This Row],[Brutobedrag 2]] < Q2_2025[[#This Row],[Bruto - Rel.korting]], "Nee", "Ja")) -> Nee | M10: =IF(Q2_2025[[#This Row],[Artikelprijs]]<>"",Q2_2025[[#This Row],[Artikelprijs]],Q2_2025[[#This Row],[Stuksprijs]]) -> 106.8625 | N10: =Q2_2025[[#This Row],[Besteld]]*Q2_2025[[#This Row],[Prijs 2]] -> 106.8625 | O10: =IF(Q2_2025[[#This Row],[Brutobedrag 2]]<Q2_2025[[#This Row],[Bruto - Rel.korting]],Q2_2025[[#This Row],[Brutobedrag 2]],Q2_2025[[#This Row],[Brutobedrag 2]]*(100-Q2_2025[[#This Row],[Relatiekorting percentage]])/100) -> 106.8625
A11: Alpe du Huez Elektra - 2025.xls | B11: 5021001 | C11: Stroomaansl. 3kW + WCD + Verbruik 1d | D11: 1 | E11: 154.5 | F11: 154.5 | G11: 115.87 | H11: 25 | I11: =_xlfn.XLOOKUP(Q2_2025[[#This Row],[Artikelnr]],Artikel_prijzen[Artnr],Artikel_prijzen[Groep],"") -> Elektra | J11: =_xlfn.XLOOKUP(Q2_2025[[#This Row],[Artikelnr]],Artikel_prijzen[Artnr],Artikel_prijzen[Prijs 2025],"") -> 106.8625 | K11: =IF(Q2_2025[[#This Row],[Artikelprijs]]<>"",IF(Q2_2025[[#This Row],[Stuksprijs]]=Q2_2025[[#This Row],[Artikelprijs]],"Prijs gelijk","Prijs wijkt af"),"") -> Prijs wijkt af | L11: =IF(Q2_2025[[#This Row],[Relatiekorting percentage]]=0, "Nvt", IF(Q2_2025[[#This Row],[Brutobedrag 2]] < Q2_2025[[#This Row],[Bruto - Rel.korting]], "Nee", "Ja")) -> Nee | M11: =IF(Q2_2025[[#This Row],[Artikelprijs]]<>"",Q2_2025[[#This Row],[Artikelprijs]],Q2_2025[[#This Row],[Stuksprijs]]) -> 106.8625 | N11: =Q2_2025[[#This Row],[Besteld]]*Q2_2025[[#This Row],[Prijs 2]] -> 106.8625 | O11: =IF(Q2_2025[[#This Row],[Brutobedrag 2]]<Q2_2025[[#This Row],[Bruto - Rel.korting]],Q2_2025[[#This Row],[Brutobedrag 2]],Q2_2025[[#This Row],[Brutobedrag 2]]*(100-Q2_2025[[#This Row],[Relatiekorting percentage]])/100) -> 106.8625
A12: Alpe du Huez Elektra - 2025.xls | B12: 5022014 | C12: Power supply 9 kW (incl. CEE 32A & Power Consumption) 2d | D12: 1 | E12: 377.11 | F12: 377.11 | G12: 282.83 | H12: 25 | I12: =_xlfn.XLOOKUP(Q2_2025[[#This Row],[Artikelnr]],Artikel_prijzen[Artnr],Artikel_prijzen[Groep],"") -> Elektra | J12: =_xlfn.XLOOKUP(Q2_2025[[#This Row],[Artikelnr]],Artikel_prijzen[Artnr],Artikel_prijzen[Prijs 2025],"") -> 298.7 | K12: =IF(Q2_2025[[#This Row],[Artikelprijs]]<>"",IF(Q2_2025[[#This Row],[Stuksprijs]]=Q2_2025[[#This Row],[Artikelprijs]],"Prijs gelijk","Prijs wijkt af"),"") -> Prijs wijkt af | L12: =IF(Q2_2025[[#This Row],[Relatiekorting percentage]]=0, "Nvt", IF(Q2_2025[[#This Row],[Brutobedrag 2]] < Q2_2025[[#This Row],[Bruto - Rel.korting]], "Nee", "Ja")) -> Ja | M12: =IF(Q2_2025[[#This Row],[Artikelprijs]]<>"",Q2_2025[[#This Row],[Artikelprijs]],Q2_2025[[#This Row],[Stuksprijs]]) -> 298.7 | N12: =Q2_2025[[#This Row],[Besteld]]*Q2_2025[[#This Row],[Prijs 2]] -> 298.7 | O12: =IF(Q2_2025[[#This Row],[Brutobedrag 2]]<Q2_2025[[#This Row],[Bruto - Rel.korting]],Q2_2025[[#This Row],[Brutobedrag 2]],Q2_2025[[#This Row],[Brutobedrag 2]]*(100-Q2_2025[[#This Row],[Relatiekorting percentage]])/100) -> 224.025
A13: Alpe du Huez Elektra - 2025.xls | B13: 5021001 | C13: Stroomaansl. 3kW + WCD + Verbruik 1d | D13: 1 | E13: 154.5 | F13: 154.5 | G13: 115.87 | H13: 25 | I13: =_xlfn.XLOOKUP(Q2_2025[[#This Row],[Artikelnr]],Artikel_prijzen[Artnr],Artikel_prijzen[Groep],"") -> Elektra | J13: =_xlfn.XLOOKUP(Q2_2025[[#This Row],[Artikelnr]],Artikel_prijzen[Artnr],Artikel_prijzen[Prijs 2025],"") -> 106.8625 | K13: =IF(Q2_2025[[#This Row],[Artikelprijs]]<>"",IF(Q2_2025[[#This Row],[Stuksprijs]]=Q2_2025[[#This Row],[Artikelprijs]],"Prijs gelijk","Prijs wijkt af"),"") -> Prijs wijkt af | L13: =IF(Q2_2025[[#This Row],[Relatiekorting percentage]]=0, "Nvt", IF(Q2_2025[[#This Row],[Brutobedrag 2]] < Q2_2025[[#This Row],[Bruto - Rel.korting]], "Nee", "Ja")) -> Nee | M13: =IF(Q2_2025[[#This Row],[Artikelprijs]]<>"",Q2_2025[[#This Row],[Artikelprijs]],Q2_2025[[#This Row],[Stuksprijs]]) -> 106.8625 | N13: =Q2_2025[[#This Row],[Besteld]]*Q2_2025[[#This Row],[Prijs 2]] -> 106.8625 | O13: =IF(Q2_2025[[#This Row],[Brutobedrag 2]]<Q2_2025[[#This Row],[Bruto - Rel.korting]],Q2_2025[[#This Row],[Brutobedrag 2]],Q2_2025[[#This Row],[Brutobedrag 2]]*(100-Q2_2025[[#This Row],[Relatiekorting percentage]])/100) -> 106.8625
... A2321: WHS Stands - 2025.xls | B2321: 5040256 | C2321: Design stand (Smartmetals heavy) | D2321: 1 | E2321: 87.55 | F2321: 87.55 | G2321: 78.79 | H2321: 10 | I2321: =_xlfn.XLOOKUP(Q2_2025[[#This Row],[Artikelnr]],Artikel_prijzen[Artnr],Artikel_prijzen[Groep],"") | J2321: =_xlfn.XLOOKUP(Q2_2025[[#This Row],[Artikelnr]],Artikel_prijzen[Artnr],Artikel_prijzen[Prijs 2025],"") | K2321: =IF(Q2_2025[[#This Row],[Artikelprijs]]<>"",IF(Q2_2025[[#This Row],[Stuksprijs]]=Q2_2025[[#This Row],[Artikelprijs]],"Prijs gelijk","Prijs wijkt af"),"") | L2321: =IF(Q2_2025[[#This Row],[Relatiekorting percentage]]=0, "Nvt", IF(Q2_2025[[#This Row],[Brutobedrag 2]] < Q2_2025[[#This Row],[Bruto - Rel.korting]], "Nee", "Ja")) -> Ja | M2321: =IF(Q2_2025[[#This Row],[Artikelprijs]]<>"",Q2_2025[[#This Row],[Artikelprijs]],Q2_2025[[#This Row],[Stuksprijs]]) -> 87.55 | N2321: =Q2_2025[[#This Row],[Besteld]]*Q2_2025[[#This Row],[Prijs 2]] -> 87.55 | O2321: =IF(Q2_2025[[#This Row],[Brutobedrag 2]]<Q2_2025[[#This Row],[Bruto - Rel.korting]],Q2_2025[[#This Row],[Brutobedrag 2]],Q2_2025[[#This Row],[Brutobedrag 2]]*(100-Q2_2025[[#This Row],[Relatiekorting percentage]])/100) -> 78.795

Sheet Q2 Provisie 
B1: Provisie berekening Q2 2025
B4: Provisie | C4: Percentage | D4: Omzet | E4: Provisie
B5: Elektra | C5: 0.23 | D5: =C39 -> 364318.72 | E5: =C5*D5 -> 83793.305
B6: Rigging | C6: 0.16 | D6: =D39 -> 384435.9 | E6: =C6*D6 -> 61509.744
B7: AV | C7: 0.15 | D7: =E39 -> 108633.45 | E7: =C7*D7 -> 16295.017
B8: Omzet Q2 | C8: 0.05 | D8: =G39 -> 1136353.3 | E8: =D8*C8 -> 56817.667
B9: Omzet voor het jaar | D9: ='Q1 Provisie'!D9+D8 -> 2275530
B10: Omzetstaffels 6,5% en 8% worden in Q4 verrekend
B11: TOTALE PROVISIE | E11: =SUM(E5:E10) -> 218415.73
B14: Evenementen Q2 2025 | C14: Elektra omzet | D14: Rigging omzet | E14: AV omzet | F14: Geen groep omzet | G14: Totaal Omzet | H14: Elektra provisie | I14: Rigging provisie | J14: AV Provisie
B15: {=_xlfn.UNIQUE(Q2_2025[Evenement])} -> Alpe du Huez Elektra - 2025.xls | C15: =SUMIFS(Q2_2025[Bruto-Rel. korting 2],Q2_2025[Evenement],'Q2 Provisie '!B15,Q2_2025[Groep],'Q2 Provisie '!$B$5) -> 3288.75 | D15: =SUMIFS(Q2_2025[Bruto-Rel. korting 2],Q2_2025[Evenement],'Q2 Provisie '!B15,Q2_2025[Groep],'Q2 Provisie '!$B$6) -> 2829 | E15: =SUMIFS(Q2_2025[Bruto-Rel. korting 2],Q2_2025[Evenement],'Q2 Provisie '!B15,Q2_2025[Groep],'Q2 Provisie '!$B$7) -> 0 | F15: =SUMIFS(Q2_2025[Bruto-Rel. korting 2],Q2_2025[Evenement],'Q2 Provisie '!B15,Q2_2025[Groep],"") -> 0 | G15: =SUM(C15:F15) -> 6117.75 | H15: =C15*$C$5 -> 756.4125 | I15: =D15*$C$6 -> 452.64 | J15: =E15*$C$7 -> 0
B16: Breakbulk Elektra - 2025.xls | C16: =SUMIFS(Q2_2025[Bruto-Rel. korting 2],Q2_2025[Evenement],'Q2 Provisie '!B16,Q2_2025[Groep],'Q2 Provisie '!$B$5) -> 108731.6 | D16: =SUMIFS(Q2_2025[Bruto-Rel. korting 2],Q2_2025[Evenement],'Q2 Provisie '!B16,Q2_2025[Groep],'Q2 Provisie '!$B$6) -> 325 | E16: =SUMIFS(Q2_2025[Bruto-Rel. korting 2],Q2_2025[Evenement],'Q2 Provisie '!B16,Q2_2025[Groep],'Q2 Provisie '!$B$7) -> 41620.5 | F16: =SUMIFS(Q2_2025[Bruto-Rel. korting 2],Q2_2025[Evenement],'Q2 Provisie '!B16,Q2_2025[Groep],"") -> 41254.369 | G16: =SUM(C16:F16) -> 191931.47 | H16: =C16*$C$5 -> 25008.268 | I16: =D16*$C$6 -> 52 | J16: =E16*$C$7 -> 6243.075
B17: Breakbulk Rigging - 2025.xls | C17: =SUMIFS(Q2_2025[Bruto-Rel. korting 2],Q2_2025[Evenement],'Q2 Provisie '!B17,Q2_2025[Groep],'Q2 Provisie '!$B$5) -> 0 | D17: =SUMIFS(Q2_2025[Bruto-Rel. korting 2],Q2_2025[Evenement],'Q2 Provisie '!B17,Q2_2025[Groep],'Q2 Provisie '!$B$6) -> 154099 | E17: =SUMIFS(Q2_2025[Bruto-Rel. korting 2],Q2_2025[Evenement],'Q2 Provisie '!B17,Q2_2025[Groep],'Q2 Provisie '!$B$7) -> 0 | F17: =SUMIFS(Q2_2025[Bruto-Rel. korting 2],Q2_2025[Evenement],'Q2 Provisie '!B17,Q2_2025[Groep],"") -> 17055.62 | G17: =SUM(C17:F17) -> 171154.62 | H17: =C17*$C$5 -> 0 | I17: =D17*$C$6 -> 24655.84 | J17: =E17*$C$7 -> 0
B18: Breakbulk Stands - 2025.xls | C18: =SUMIFS(Q2_2025[Bruto-Rel. korting 2],Q2_2025[Evenement],'Q2 Provisie '!B18,Q2_2025[Groep],'Q2 Provisie '!$B$5) -> 1629.975 | D18: =SUMIFS(Q2_2025[Bruto-Rel. korting 2],Q2_2025[Evenement],'Q2 Provisie '!B18,Q2_2025[Groep],'Q2 Provisie '!$B$6) -> 2240 | E18: =SUMIFS(Q2_2025[Bruto-Rel. korting 2],Q2_2025[Evenement],'Q2 Provisie '!B18,Q2_2025[Groep],'Q2 Provisie '!$B$7) -> 24913.2 | F18: =SUMIFS(Q2_2025[Bruto-Rel. korting 2],Q2_2025[Evenement],'Q2 Provisie '!B18,Q2_2025[Groep],"") -> 23189.786 | G18: =SUM(C18:F18) -> 51972.961 | H18: =C18*$C$5 -> 374.89425 | I18: =D18*$C$6 -> 358.4 | J18: =E18*$C$7 -> 3736.98
B19: Brugklas Event Elektra - 2025.xls | C19: =SUMIFS(Q2_2025[Bruto-Rel. korting 2],Q2_2025[Evenement],'Q2 Provisie '!B19,Q2_2025[Groep],'Q2 Provisie '!$B$5) -> 3461.7625 | D19: =SUMIFS(Q2_2025[Bruto-Rel. korting 2],Q2_2025[Evenement],'Q2 Provisie '!B19,Q2_2025[Groep],'Q2 Provisie '!$B$6) -> 0 | E19: =SUMIFS(Q2_2025[Bruto-Rel. korting 2],Q2_2025[Evenement],'Q2 Provisie '!B19,Q2_2025[Groep],'Q2 Provisie '!$B$7) -> 0 | F19: =SUMIFS(Q2_2025[Bruto-Rel. korting 2],Q2_2025[Evenement],'Q2 Provisie '!B19,Q2_2025[Groep],"") -> 0 | G19: =SUM(C19:F19) -> 3461.7625 | H19: =C19*$C$5 -> 796.20538 | I19: =D19*$C$6 -> 0 | J19: =E19*$C$7 -> 0
B20: ECIO - 2025.xls | C20: =SUMIFS(Q2_2025[Bruto-Rel. korting 2],Q2_2025[Evenement],'Q2 Provisie '!B20,Q2_2025[Groep],'Q2 Provisie '!$B$5) -> 0 | D20: =SUMIFS(Q2_2025[Bruto-Rel. korting 2],Q2_2025[Evenement],'Q2 Provisie '!B20,Q2_2025[Groep],'Q2 Provisie '!$B$6) -> 0 | E20: =SUMIFS(Q2_2025[Bruto-Rel. korting 2],Q2_2025[Evenement],'Q2 Provisie '!B20,Q2_2025[Groep],'Q2 Provisie '!$B$7) -> 0 | F20: =SUMIFS(Q2_2025[Bruto-Rel. korting 2],Q2_2025[Evenement],'Q2 Provisie '!B20,Q2_2025[Groep],"") -> 437.544 | G20: =SUM(C20:F20) -> 437.544 | H20: =C20*$C$5 -> 0 | I20: =D20*$C$6 -> 0 | J20: =E20*$C$7 -> 0
B21: Guerilla Business Elektra - 2025.xls | C21: =SUMIFS(Q2_2025[Bruto-Rel. korting 2],Q2_2025[Evenement],'Q2 Provisie '!B21,Q2_2025[Groep],'Q2 Provisie '!$B$5) -> 0 | D21: =SUMIFS(Q2_2025[Bruto-Rel. korting 2],Q2_2025[Evenement],'Q2 Provisie '!B21,Q2_2025[Groep],'Q2 Provisie '!$B$6) -> 0 | E21: =SUMIFS(Q2_2025[Bruto-Rel. korting 2],Q2_2025[Evenement],'Q2 Provisie '!B21,Q2_2025[Groep],'Q2 Provisie '!$B$7) -> 0 | F21: =SUMIFS(Q2_2025[Bruto-Rel. korting 2],Q2_2025[Evenement],'Q2 Provisie '!B21,Q2_2025[Groep],"") -> 74.032 | G21: =SUM(C21:F21) -> 74.032 | H21: =C21*$C$5 -> 0 | I21: =D21*$C$6 -> 0 | J21: =E21*$C$7 -> 0
B22: Maintenance Elektra - 2025.xls | C22: =SUMIFS(Q2_2025[Bruto-Rel. korting 2],Q2_2025[Evenement],'Q2 Provisie '!B22,Q2_2025[Groep],'Q2 Provisie '!$B$5) -> 25852.6 | D22: =SUMIFS(Q2_2025[Bruto-Rel. korting 2],Q2_2025[Evenement],'Q2 Provisie '!B22,Q2_2025[Groep],'Q2 Provisie '!$B$6) -> 175 | E22: =SUMIFS(Q2_2025[Bruto-Rel. korting 2],Q2_2025[Evenement],'Q2 Provisie '!B22,Q2_2025[Groep],'Q2 Provisie '!$B$7) -> 12385 | F22: =SUMIFS(Q2_2025[Bruto-Rel. korting 2],Q2_2025[Evenement],'Q2 Provisie '!B22,Q2_2025[Groep],"") -> 1658.01 | G22: =SUM(C22:F22) -> 40070.61 | H22: =C22*$C$5 -> 5946.098 | I22: =D22*$C$6 -> 28 | J22: =E22*$C$7 -> 1857.75
B23: Maintenance Rigging - 2025.xls | C23: =SUMIFS(Q2_2025[Bruto-Rel. korting 2],Q2_2025[Evenement],'Q2 Provisie '!B23,Q2_2025[Groep],'Q2 Provisie '!$B$5) -> 0 | D23: =SUMIFS(Q2_2025[Bruto-Rel. korting 2],Q2_2025[Evenement],'Q2 Provisie '!B23,Q2_2025[Groep],'Q2 Provisie '!$B$6) -> 23656 | E23: =SUMIFS(Q2_2025[Bruto-Rel. korting 2],Q2_2025[Evenement],'Q2 Provisie '!B23,Q2_2025[Groep],'Q2 Provisie '!$B$7) -> 0 | F23: =SUMIFS(Q2_2025[Bruto-Rel. korting 2],Q2_2025[Evenement],'Q2 Provisie '!B23,Q2_2025[Groep],"") -> 2298.158 | G23: =SUM(C23:F23) -> 25954.158 | H23: =C23*$C$5 -> 0 | I23: =D23*$C$6 -> 3784.96 | J23: =E23*$C$7 -> 0
B24: Maintenance Stands - 2025.xls | C24: =SUMIFS(Q2_2025[Bruto-Rel. korting 2],Q2_2025[Evenement],'Q2 Provisie '!B24,Q2_2025[Groep],'Q2 Provisie '!$B$5) -> 18735.7 | D24: =SUMIFS(Q2_2025[Bruto-Rel. korting 2],Q2_2025[Evenement],'Q2 Provisie '!B24,Q2_2025[Groep],'Q2 Provisie '!$B$6) -> 6151 | E24: =SUMIFS(Q2_2025[Bruto-Rel. korting 2],Q2_2025[Evenement],'Q2 Provisie '!B24,Q2_2025[Groep],'Q2 Provisie '!$B$7) -> 6930 | F24: =SUMIFS(Q2_2025[Bruto-Rel. korting 2],Q2_2025[Evenement],'Q2 Provisie '!B24,Q2_2025[Groep],"") -> 33998.013 | G24: =SUM(C24:F24) -> 65814.713 | H24: =C24*$C$5 -> 4309.211 | I24: =D24*$C$6 -> 984.16 | J24: =E24*$C$7 -> 1039.5
B25: NK Turnen Elektra - 2025.xls | C25: =SUMIFS(Q2_2025[Bruto-Rel. korting 2],Q2_2025[Evenement],'Q2 Provisie '!B25,Q2_2025[Groep],'Q2 Provisie '!$B$5) -> 3371.5625 | D25: =SUMIFS(Q2_2025[Bruto-Rel. korting 2],Q2_2025[Evenement],'Q2 Provisie '!B25,Q2_2025[Groep],'Q2 Provisie '!$B$6) -> 0 | E25: =SUMIFS(Q2_2025[Bruto-Rel. korting 2],Q2_2025[Evenement],'Q2 Provisie '!B25,Q2_2025[Groep],'Q2 Provisie '!$B$7) -> 0 | F25: =SUMIFS(Q2_2025[Bruto-Rel. korting 2],Q2_2025[Evenement],'Q2 Provisie '!B25,Q2_2025[Groep],"") -> 82.4 | G25: =SUM(C25:F25) -> 3453.9625 | H25: =C25*$C$5 -> 775.45938 | I25: =D25*$C$6 -> 0 | J25: =E25*$C$7 -> 0
B26: Pasar Malam - 2025.xls | C26: =SUMIFS(Q2_2025[Bruto-Rel. korting 2],Q2_2025[Evenement],'Q2 Provisie '!B26,Q2_2025[Groep],'Q2 Provisie '!$B$5) -> 17253.2 | D26: =SUMIFS(Q2_2025[Bruto-Rel. korting 2],Q2_2025[Evenement],'Q2 Provisie '!B26,Q2_2025[Groep],'Q2 Provisie '!$B$6) -> 620 | E26: =SUMIFS(Q2_2025[Bruto-Rel. korting 2],Q2_2025[Evenement],'Q2 Provisie '!B26,Q2_2025[Groep],'Q2 Provisie '!$B$7) -> 0 | F26: =SUMIFS(Q2_2025[Bruto-Rel. korting 2],Q2_2025[Evenement],'Q2 Provisie '!B26,Q2_2025[Groep],"") -> 142.776 | G26: =SUM(C26:F26) -> 18015.976 | H26: =C26*$C$5 -> 3968.236 | I26: =D26*$C$6 -> 99.2 | J26: =E26*$C$7 -> 0
B27: SAP - 2025.xls | C27: =SUMIFS(Q2_2025[Bruto-Rel. korting 2],Q2_2025[Evenement],'Q2 Provisie '!B27,Q2_2025[Groep],'Q2 Provisie '!$B$5) -> 0 | D27: =SUMIFS(Q2_2025[Bruto-Rel. korting 2],Q2_2025[Evenement],'Q2 Provisie '!B27,Q2_2025[Groep],'Q2 Provisie '!$B$6) -> 0 | E27: =SUMIFS(Q2_2025[Bruto-Rel. korting 2],Q2_2025[Evenement],'Q2 Provisie '!B27,Q2_2025[Groep],'Q2 Provisie '!$B$7) -> 410 | F27: =SUMIFS(Q2_2025[Bruto-Rel. korting 2],Q2_2025[Evenement],'Q2 Provisie '!B27,Q2_2025[Groep],"") -> 0 | G27: =SUM(C27:F27) -> 410 | H27: =C27*$C$5 -> 0 | I27: =D27*$C$6 -> 0 | J27: =E27*$C$7 -> 61.5
... B38: WHS Stands - 2025.xls | C38: =SUMIFS(Q2_2025[Bruto-Rel. korting 2],Q2_2025[Evenement],'Q2 Provisie '!B38,Q2_2025[Groep],'Q2 Provisie '!$B$5) -> 3264.7 | D38: =SUMIFS(Q2_2025[Bruto-Rel. korting 2],Q2_2025[Evenement],'Q2 Provisie '!B38,Q2_2025[Groep],'Q2 Provisie '!$B$6) -> 6356 | E38: =SUMIFS(Q2_2025[Bruto-Rel. korting 2],Q2_2025[Evenement],'Q2 Provisie '!B38,Q2_2025[Groep],'Q2 Provisie '!$B$7) -> 11028.25 | F38: =SUMIFS(Q2_2025[Bruto-Rel. korting 2],Q2_2025[Evenement],'Q2 Provisie '!B38,Q2_2025[Groep],"") -> 51111.987 | G38: =SUM(C38:F38) -> 71760.937 | H38: =C38*$C$5 -> 750.881 | I38: =D38*$C$6 -> 1016.96 | J38: =E38*$C$7 -> 1654.2375
B39: TOTAAL | C39: =SUM(C15:C38) -> 364318.72 | D39: =SUM(D15:D38) -> 384435.9 | E39: =SUM(E15:E38) -> 108633.45 | F39: =SUM(F15:F38) -> 278965.27 | G39: =SUM(G15:G38) -> 1136353.3 | H39: =SUM(H15:H38) -> 83793.305 | I39: =SUM(I15:I38) -> 61509.744 | J39: =SUM(J15:J38) -> 16295.017

Sheet Q2 PT
A3: Evenement | B3: Artikelnr | C3: Omschrijving | D3: Groep | E3: Som van Besteld
A4: Alpe du Huez Elektra - 2025.xls | B4: 5021001 | C4: Stroomaansl. 3kW + WCD + Verbruik 1d | D4: Elektra | E4: 12
B5: 5022014 | C5: Power supply 9 kW (incl. CEE 32A & Power Consumption) 2d | D5: Elektra | E5: 2
B6: 5022017 | C6: Power supply 20 kW (incl. CEE 32A & Power Consumption) 2d | D6: Elektra | E6: 1
B7: 5022022 | C7: Power supply 80 kW (incl. CEE 125A & Power Consumption) 2d | D7: Elektra | E7: 1
B8: 5030001 | C8: Pre-Rigging P36R (per meter) | D8: Rigging | E8: 24
B9: 5030226 | C9: Ophangpunt t.b.v. takel tot 500kg | D9: Rigging | E9: 20
A10: Brugklas Event Elektra - 2025.xls | B10: 5021001 | C10: Stroomaansl. 3kW + WCD + Verbruik 1d | D10: Elektra | E10: 9
B11: 5022019 | C11: Power supply 40 kW (incl. CEE 63A & Power Consumption) 2d | D11: Elektra | E11: 2
B12: 5022022 | C12: Power supply 80 kW (incl. CEE 125A & Power Consumption) 2d | D12: Elektra | E12: 1
A13: ECIO - 2025.xls | B13: 5020008 | C13: Rail + 2 spots LED 20W tri color - 3000K/4000K | E13: 12
B14: 5020009 | C14: Rail + 3 spots LED 20W tri color - 3000K/4000K | E14: 2
A15: Guerilla Business Elektra - 2025.xls | B15: 4801003 | C15: Nooduitgang verlichting | E15: 2
A16: Maintenance Elektra - 2025.xls | B16: 1003012 | C16: Inbouwspot Lika LED 9W 3000K Ø 83mm wit | E16: 2
B17: 1098002 | C17: Credit op factuurnummer 2530385 | E17: 1
B18: 4001182 | C18: Design stand | E18: 2
B19: 5020001 | C19: Wall socket adapter 1kW | E19: 2
B20: 5020002 | C20: Wandcontactdoos 3kw | E20: 11
B21: 5020003 | C21: Contactdoos CEE 16A/400V | E21: 1
B22: 5020005 | C22: Rail + 1 spot LED 20W tri color - 3000K/4000K | E22: 4
B23: 5020009 | C23: Power rail + 3 raillight LED 20W tri color - 3000/4000K | E23: 5
C24: Rail + 3 spots LED 20W tri color - 3000K/4000K | E24: 6
B25: 5021030 | C25: Power connection 3kW + wall socket + consumption | D25: Elektra | E25: 4
C26: Stroomaansl. 3kW + WCD + Verbruik | D26: Elektra | E26: 9
C27: Stroomaansl. 3kW + WCD + Verbruik 3d | D27: Elektra | E27: 49
B28: 5021033 | C28: Stroomaansl. 2kW + WCD + Verbruik | D28: Elektra | E28: 2
B29: 5030234 | C29: Ophangen vlag/banner (max 3m / 20kg) | D29: Rigging | E29: 1
B30: 5040007 | C30: LCD LED Display 32" | D30: AV | E30: 2
B31: 5040008 | C31: LCD LED Display 43" | D31: AV | E31: 11
B32: 5040010 | C32: LCD LED Display 55" | D32: AV | E32: 14
B33: 5040011 | C33: LCD LED Display 65" | D33: AV | E33: 1
B34: 5040012 | C34: LCD LED Display 75" | D34: AV | E34: 1
B35: 5040015 | C35: Design stand | D35: AV | E35: 2
B36: 5040018 | C36: Design stand (Smartmetals light) !MAX 55 INCH! | E36: 11
B37: 5040219 | C37: Iiyama 43" touchscreen | D37: AV | E37: 1
B38: 5040256 | C38: Design stand (Smartmetals heavy) | E38: 1
B39: 5022023 | C39: Power supply 6 kW (incl. CEE 32A & Power Consumption) 3d | D39: Elektra | E39: 5
B40: 5022046 | C40: Power supply 6 kW (incl. 2x WCD 230V & Power Consumption) 3d | D40: Elektra | E40: 12
B41: 5022026 | C41: Power supply 9 kW (incl. CEE 32A & Power Consumption) 3d | D41: Elektra | E41: 4
B42: 5022030 | C42: Power supply 15 kW (incl. CEE 32A & Power Consumption) 3d | D42: Elektra | E42: 6
B43: 5022032 | C43: Power supply 20 kW (incl. CEE 32A & Power Consumption) 3d | D43: Elektra | E43: 1
B44: 5022038 | C44: Power supply 40 kW (incl. CEE 63A & Power Consumption) 3d | D44: Elektra | E44: 1
B45: 5022054 | C45: Power supply 20 kW (incl. 6x WCD 230V & Power Consumption)3d | D45: Elektra | E45: 1
B46: 5022048 | C46: Power supply 9 kW (incl. 3x WCD 230V & Power Consumption) 3d | D46: Elektra | E46: 12
B47: 5022052 | C47: Power supply 15 kW (incl. 5x WCD 230V & Power Consumption)3d | D47: Elektra | E47: 6
B48: 4604257 | C48: Design stand (Smartmetals heavy) | E48: 1
A49: Maintenance Rigging - 2025.xls | B49: 1002060 | C49: Pendel LED Novi 50 watt 3-colour | E49: 3
B50: 1007051 | C50: Multipar LED 150w DMX 3000-6500K | E50: 10
B51: 2004027 | C51: Softsteel 2 ton - 1.6 meter incl. harp 3,25 ton | E51: 4
B52: 2004082 | C52: Kabelset motortakels (set voor 4 takels) | E52: 2
B53: 5010002 | C53: Pendel LED Novi 50 watt 3-colour | E53: 5
B54: 5030001 | C54: Pre-Rigging P36R (per meter) | D54: Rigging | E54: 97
B55: 5030005 | C55: Voedingskabel via dak (van ophangpunt naar zijkant hal) | D55: Rigging | E55: 2
B56: 5030226 | C56: Ophangpunt t.b.v. takel tot 500kg | D56: Rigging | E56: 6
B57: 5030228 | C57: Handtakel incl. ophangpunt + montage max 250kg | D57: Rigging | E57: 53
C58: Manual chainhoist incl. riggingpoint + assembly max 250kg | D58: Rigging | E58: 2
B59: 5030229 | C59: Motortakel incl. ophangpunt + montage max 250kg | D59: Rigging | E59: 19
B60: 5030232 | C60: Voedingskabel via dak (van berging naar ophangpunt) | D60: Rigging | E60: 8
B61: 5030234 | C61: Ophangen vlag/banner (max 3m / 20kg) | D61: Rigging | E61: 2
B62: 5031039 | C62: Prolyte truss H30V 2 meter zwart | E62: 2
B63: 5031052 | C63: Prolyte truss H30V 2 meter alu | E63: 2
B64: 5031053 | C64: Prolyte truss H30V 3 meter alu | E64: 4
A65: NK Turnen Elektra - 2025.xls | B65: 3002030 | C65: Groepenkast (Cubes) 32A tot 20 kw 6xCEE 230V | E65: 1
B66: 5021026 | C66: Stroomaansl. 3kW + WCD + Verbruik | D66: Elektra | E66: 18
C67: Stroomaansl. 3kW + WCD + Verbruik 2d | D67: Elektra | E67: 7
B68: 5022019 | C68: Power supply 40 kW (incl. CEE 63A & Power Consumption) 2d | D68: Elektra | E68: 1
A69: Pasar Malam - 2025.xls | B69: 4801003 | C69: Nooduitgang verlichting | E69: 3
B70: 5021032 | C70: Stroomaansl. 1kW + WCD + Verbruik | D70: Elektra | E70: 24
C71: Stroomaansl. 1kW + WCD + Verbruik 4d | D71: Elektra | E71: 3
B72: 5021033 | C72: Stroomaansl. 2kW + WCD + Verbruik 4d | D72: Elektra | E72: 8
B73: 5021034 | C73: Stroomaansl. 3kW + WCD + Verbruik | D73: Elektra | E73: 8
C74: Stroomaansl. 3kW + WCD + Verbruik 4d | D74: Elektra | E74: 13
B75: 5022025 | C75: Power supply 6 kW (incl. CEE 32A & Power Consumption) 4d | D75: Elektra | E75: 2
B76: 5022027 | C76: Power supply 9 kW (incl. CEE 32A & Power Consumption) 4d | D76: Elektra | E76: 2
B77: 5022033 | C77: Power supply 20 kW (incl. CEE 32A & Power Consumption) 4d | D77: Elektra | E77: 8
B78: 5022039 | C78: Power supply 40 kW (incl. CEE 63A & Power Consumption) 4d | D78: Elektra | E78: 8
B79: 5022043 | C79: Power supply 60 kW (incl. CEE 125A & Power Consumption) 4d | D79: Elektra | E79: 1
B80: 5030226 | C80: Ophangpunt t.b.v. takel tot 500kg | D80: Rigging | E80: 4
A81: The Finals Elektra - 2025.xls | B81: 5020001 | C81: Wandcontactdoos 1kW | E81: 41
B82: 5021009 | C82: Stroomtoevoerleiding 15 kW (incl. CEE 32A) | D82: Elektra | E82: -1
B83: 5021016 | C83: Stroomtoevoerleiding 30 kW (incl. CEE 63A) | D83: Elektra | E83: 1
B84: 5022009 | C84: Stroomtoevoerleiding 3 kW | D84: Elektra | E84: 41
B85: 5030226 | C85: Ophangpunt t.b.v. takel tot 500kg | D85: Rigging | E85: 12
B86: 5030228 | C86: Handtakel incl. ophangpunt + montage max 250kg | D86: Rigging | E86: 10
B87: 5030234 | C87: Ophangen vlag/banner (max 3m / 20kg) | D87: Rigging | E87: 5
B88: 5031008 | C88: Prolyte truss X30D 2 meter zwart | E88: 25
A89: TOC Elektra - 2025.xls | B89: 3001013 | C89: Floor cable 3x2.5mm² | E89: 6
B90: 3002032 | C90: Groepenkast (Cubes) 63A tot 40 kw | E90: 1
B91: 5020002 | C91: Wall socket adapter 3kW | E91: 16
C92: Wandcontactdoos 3kw | E92: 5
B93: 5020003 | C93: Contactdoos CEE 16A/400V | E93: 1
C94: Socket CEE 16A/400V | E94: 1
B95: 5021030 | C95: Power connection 3kW + wall socket + consumption | D95: Elektra | E95: 19
C96: Stroomaansl. 3kW + WCD + Verbruik | D96: Elektra | E96: 95
C97: Stroomaansl. 3kW + WCD + Verbruik 3d | D97: Elektra | E97: 14
B98: 5021033 | C98: Power connection 2kW + wall socket + consumption | D98: Elektra | E98: -2
B99: 5022012 | C99: Verdeelblok 3v wcd | E99: 7
B100: 5022050 | C100: Power supply 12 kW (incl. 4x WCD 230V & Power Consumption)3d | D100: Elektra | E100: 1
B101: 5030005 | C101: Power supply line roof (from riggingpoint to side hall) | D101: Rigging | E101: 6
B102: 5030225 | C102: Riggingpoint steel cable 5mm up to 150kg | D102: Rigging | E102: 2
...

Sheet Q3 2025
A1: Evenement | B1: Artikelnr | C1: Omschrijving | D1: Besteld | E1: Stuksprijs | F1: Brutobedrag | G1: Bruto - Rel.korting | H1: Relatiekorting percentage | I1: Groep | J1: Artikelprijs | K1: Vergelijk | L1: Relatie korting | M1: Prijs 2 | N1: Brutobedrag 2 | O1: Bruto-Rel. korting 2
A2: Albeda College - 2025.xls | B2: 5022020 | C2: Power supply 50 kW (incl. CEE 125A & Power Consumption) 2d | D2: 1 | E2: 1177.93 | F2: 1177.93 | G2: 824.55 | H2: 30 | I2: =_xlfn.XLOOKUP(Q3_2025[[#This Row],[Artikelnr]],Artikel_prijzen[Artnr],Artikel_prijzen[Groep],"") -> Elektra | J2: =_xlfn.XLOOKUP(Q3_2025[[#This Row],[Artikelnr]],Artikel_prijzen[Artnr],Artikel_prijzen[Prijs 2025],"") -> 800 | K2: =IF(Q3_2025[[#This Row],[Artikelprijs]]<>"",IF(Q3_2025[[#This Row],[Stuksprijs]]=Q3_2025[[#This Row],[Artikelprijs]],"Prijs gelijk","Prijs wijkt af"),"") -> Prijs wijkt af | L2: =IF(Q3_2025[[#This Row],[Relatiekorting percentage]]=0, "Nvt", IF(Q3_2025[[#This Row],[Brutobedrag 2]] < Q3_2025[[#This Row],[Bruto - Rel.korting]], "Nee", "Ja")) -> Nee | M2: =IF(Q3_2025[[#This Row],[Artikelprijs]]<>"",Q3_2025[[#This Row],[Artikelprijs]],Q3_2025[[#This Row],[Stuksprijs]]) -> 800 | N2: =Q3_2025[[#This Row],[Besteld]]*Q3_2025[[#This Row],[Prijs 2]] -> 800 | O2: =IF(Q3_2025[[#This Row],[Brutobedrag 2]]<Q3_2025[[#This Row],[Bruto - Rel.korting]],Q3_2025[[#This Row],[Brutobedrag 2]],Q3_2025[[#This Row],[Brutobedrag 2]]*(100-Q3_2025[[#This Row],[Relatiekorting percentage]])/100) -> 800
A3: Albeda College - 2025.xls | B3: 5022015 | C3: Power supply 12 kW (incl. CEE 32A & Power Consumption) 2d | D3: 1 | E3: 444.44 | F3: 444.44 | G3: 311.11 | H3: 30 | I3: =_xlfn.XLOOKUP(Q3_2025[[#This Row],[Artikelnr]],Artikel_prijzen[Artnr],Artikel_prijzen[Groep],"") -> Elektra | J3: =_xlfn.XLOOKUP(Q3_2025[[#This Row],[Artikelnr]],Artikel_prijzen[Artnr],Artikel_prijzen[Prijs 2025],"") -> 339.9 | K3: =IF(Q3_2025[[#This Row],[Artikelprijs]]<>"",IF(Q3_2025[[#This Row],[Stuksprijs]]=Q3_2025[[#This Row],[Artikelprijs]],"Prijs gelijk","Prijs wijkt af"),"") -> Prijs wijkt af | L3: =IF(Q3_2025[[#This Row],[Relatiekorting percentage]]=0, "Nvt", IF(Q3_2025[[#This Row],[Brutobedrag 2]] < Q3_2025[[#This Row],[Bruto - Rel.korting]], "Nee", "Ja")) -> Ja | M3: =IF(Q3_2025[[#This Row],[Artikelprijs]]<>"",Q3_2025[[#This Row],[Artikelprijs]],Q3_2025[[#This Row],[Stuksprijs]]) -> 339.9 | N3: =Q3_2025[[#This Row],[Besteld]]*Q3_2025[[#This Row],[Prijs 2]] -> 339.9 | O3: =IF(Q3_2025[[#This Row],[Brutobedrag 2]]<Q3_2025[[#This Row],[Bruto - Rel.korting]],Q3_2025[[#This Row],[Brutobedrag 2]],Q3_2025[[#This Row],[Brutobedrag 2]]*(100-Q3_2025[[#This Row],[Relatiekorting percentage]])/100) -> 237.93
A4: Albeda College - 2025.xls | B4: 5022020 | C4: Power supply 50 kW (incl. CEE 125A & Power Consumption) 2d | D4: 1 | E4: 1177.93 | F4: 1177.93 | G4: 824.55 | H4: 30 | I4: =_xlfn.XLOOKUP(Q3_2025[[#This Row],[Artikelnr]],Artikel_prijzen[Artnr],Artikel_prijzen[Groep],"") -> Elektra | J4: =_xlfn.XLOOKUP(Q3_2025[[#This Row],[Artikelnr]],Artikel_prijzen[Artnr],Artikel_prijzen[Prijs 2025],"") -> 800 | K4: =IF(Q3_2025[[#This Row],[Artikelprijs]]<>"",IF(Q3_2025[[#This Row],[Stuksprijs]]=Q3_2025[[#This Row],[Artikelprijs]],"Prijs gelijk","Prijs wijkt af"),"") -> Prijs wijkt af | L4: =IF(Q3_2025[[#This Row],[Relatiekorting percentage]]=0, "Nvt", IF(Q3_2025[[#This Row],[Brutobedrag 2]] < Q3_2025[[#This Row],[Bruto - Rel.korting]], "Nee", "Ja")) -> Nee | M4: =IF(Q3_2025[[#This Row],[Artikelprijs]]<>"",Q3_2025[[#This Row],[Artikelprijs]],Q3_2025[[#This Row],[Stuksprijs]]) -> 800 | N4: =Q3_2025[[#This Row],[Besteld]]*Q3_2025[[#This Row],[Prijs 2]] -> 800 | O4: =IF(Q3_2025[[#This Row],[Brutobedrag 2]]<Q3_2025[[#This Row],[Bruto - Rel.korting]],Q3_2025[[#This Row],[Brutobedrag 2]],Q3_2025[[#This Row],[Brutobedrag 2]]*(100-Q3_2025[[#This Row],[Relatiekorting percentage]])/100) -> 800
A5: Albeda College - 2025.xls | B5: 5022015 | C5: Power supply 12 kW (incl. CEE 32A & Power Consumption) 2d | D5: 1 | E5: 444.44 | F5: 444.44 | G5: 311.11 | H5: 30 | I5: =_xlfn.XLOOKUP(Q3_2025[[#This Row],[Artikelnr]],Artikel_prijzen[Artnr],Artikel_prijzen[Groep],"") -> Elektra | J5: =_xlfn.XLOOKUP(Q3_2025[[#This Row],[Artikelnr]],Artikel_prijzen[Artnr],Artikel_prijzen[Prijs 2025],"") -> 339.9 | K5: =IF(Q3_2025[[#This Row],[Artikelprijs]]<>"",IF(Q3_2025[[#This Row],[Stuksprijs]]=Q3_2025[[#This Row],[Artikelprijs]],"Prijs gelijk","Prijs wijkt af"),"") -> Prijs wijkt af | L5: =IF(Q3_2025[[#This Row],[Relatiekorting percentage]]=0, "Nvt", IF(Q3_2025[[#This Row],[Brutobedrag 2]] < Q3_2025[[#This Row],[Bruto - Rel.korting]], "Nee", "Ja")) -> Ja | M5: =IF(Q3_2025[[#This Row],[Artikelprijs]]<>"",Q3_2025[[#This Row],[Artikelprijs]],Q3_2025[[#This Row],[Stuksprijs]]) -> 339.9 | N5: =Q3_2025[[#This Row],[Besteld]]*Q3_2025[[#This Row],[Prijs 2]] -> 339.9 | O5: =IF(Q3_2025[[#This Row],[Brutobedrag 2]]<Q3_2025[[#This Row],[Bruto - Rel.korting]],Q3_2025[[#This Row],[Brutobedrag 2]],Q3_2025[[#This Row],[Brutobedrag 2]]*(100-Q3_2025[[#This Row],[Relatiekorting percentage]])/100) -> 237.93
A6: Albeda College - 2025.xls | B6: 5022015 | C6: Power supply 12 kW (incl. CEE 32A & Power Consumption) 2d | D6: 1 | E6: 444.44 | F6: 444.44 | G6: 311.11 | H6: 30 | I6: =_xlfn.XLOOKUP(Q3_2025[[#This Row],[Artikelnr]],Artikel_prijzen[Artnr],Artikel_prijzen[Groep],"") -> Elektra | J6: =_xlfn.XLOOKUP(Q3_2025[[#This Row],[Artikelnr]],Artikel_prijzen[Artnr],Artikel_prijzen[Prijs 2025],"") -> 339.9 | K6: =IF(Q3_2025[[#This Row],[Artikelprijs]]<>"",IF(Q3_2025[[#This Row],[Stuksprijs]]=Q3_2025[[#This Row],[Artikelprijs]],"Prijs gelijk","Prijs wijkt af"),"") -> Prijs wijkt af | L6: =IF(Q3_2025[[#This Row],[Relatiekorting percentage]]=0, "Nvt", IF(Q3_2025[[#This Row],[Brutobedrag 2]] < Q3_2025[[#This Row],[Bruto - Rel.korting]], "Nee", "Ja")) -> Ja | M6: =IF(Q3_2025[[#This Row],[Artikelprijs]]<>"",Q3_2025[[#This Row],[Artikelprijs]],Q3_2025[[#This Row],[Stuksprijs]]) -> 339.9 | N6: =Q3_2025[[#This Row],[Besteld]]*Q3_2025[[#This Row],[Prijs 2]] -> 339.9 | O6: =IF(Q3_2025[[#This Row],[Brutobedrag 2]]<Q3_2025[[#This Row],[Bruto - Rel.korting]],Q3_2025[[#This Row],[Brutobedrag 2]],Q3_2025[[#This Row],[Brutobedrag 2]]*(100-Q3_2025[[#This Row],[Relatiekorting percentage]])/100) -> 237.93
A7: Albeda College - 2025.xls | B7: 3001102 | C7: Stroomaansl. 1kW + WCD + Verbruik 1d | D7: 3 | E7: 125.65 | F7: 376.95 | G7: 263.86 | H7: 30 | I7: =_xlfn.XLOOKUP(Q3_2025[[#This Row],[Artikelnr]],Artikel_prijzen[Artnr],Artikel_prijzen[Groep],"") -> Elektra | J7: =_xlfn.XLOOKUP(Q3_2025[[#This Row],[Artikelnr]],Artikel_prijzen[Artnr],Artikel_prijzen[Prijs 2025],"") -> 106.8625 | K7: =IF(Q3_2025[[#This Row],[Artikelprijs]]<>"",IF(Q3_2025[[#This Row],[Stuksprijs]]=Q3_2025[[#This Row],[Artikelprijs]],"Prijs gelijk","Prijs wijkt af"),"") -> Prijs wijkt af | L7: =IF(Q3_2025[[#This Row],[Relatiekorting percentage]]=0, "Nvt", IF(Q3_2025[[#This Row],[Brutobedrag 2]] < Q3_2025[[#This Row],[Bruto - Rel.korting]], "Nee", "Ja")) -> Ja | M7: =IF(Q3_2025[[#This Row],[Artikelprijs]]<>"",Q3_2025[[#This Row],[Artikelprijs]],Q3_2025[[#This Row],[Stuksprijs]]) -> 106.8625 | N7: =Q3_2025[[#This Row],[Besteld]]*Q3_2025[[#This Row],[Prijs 2]] -> 320.5875 | O7: =IF(Q3_2025[[#This Row],[Brutobedrag 2]]<Q3_2025[[#This Row],[Bruto - Rel.korting]],Q3_2025[[#This Row],[Brutobedrag 2]],Q3_2025[[#This Row],[Brutobedrag 2]]*(100-Q3_2025[[#This Row],[Relatiekorting percentage]])/100) -> 224.41125
A8: Albeda College - 2025.xls | B8: 3001102 | C8: Stroomaansl. 1kW + WCD + Verbruik 1d | D8: 1 | E8: 125.65 | F8: 125.65 | G8: 87.95 | H8: 30 | I8: =_xlfn.XLOOKUP(Q3_2025[[#This Row],[Artikelnr]],Artikel_prijzen[Artnr],Artikel_prijzen[Groep],"") -> Elektra | J8: =_xlfn.XLOOKUP(Q3_2025[[#This Row],[Artikelnr]],Artikel_prijzen[Artnr],Artikel_prijzen[Prijs 2025],"") -> 106.8625 | K8: =IF(Q3_2025[[#This Row],[Artikelprijs]]<>"",IF(Q3_2025[[#This Row],[Stuksprijs]]=Q3_2025[[#This Row],[Artikelprijs]],"Prijs gelijk","Prijs wijkt af"),"") -> Prijs wijkt af | L8: =IF(Q3_2025[[#This Row],[Relatiekorting percentage]]=0, "Nvt", IF(Q3_2025[[#This Row],[Brutobedrag 2]] < Q3_2025[[#This Row],[Bruto - Rel.korting]], "Nee", "Ja")) -> Ja | M8: =IF(Q3_2025[[#This Row],[Artikelprijs]]<>"",Q3_2025[[#This Row],[Artikelprijs]],Q3_2025[[#This Row],[Stuksprijs]]) -> 106.8625 | N8: =Q3_2025[[#This Row],[Besteld]]*Q3_2025[[#This Row],[Prijs 2]] -> 106.8625 | O8: =IF(Q3_2025[[#This Row],[Brutobedrag 2]]<Q3_2025[[#This Row],[Bruto - Rel.korting]],Q3_2025[[#This Row],[Brutobedrag 2]],Q3_2025[[#This Row],[Brutobedrag 2]]*(100-Q3_2025[[#This Row],[Relatiekorting percentage]])/100) -> 74.80375
A9: Albeda College - 2025.xls | B9: 5022015 | C9: Power supply 12 kW (incl. CEE 32A & Power Consumption) 2d | D9: 1 | E9: 444.44 | F9: 444.44 | G9: 311.11 | H9: 30 | I9: =_xlfn.XLOOKUP(Q3_2025[[#This Row],[Artikelnr]],Artikel_prijzen[Artnr],Artikel_prijzen[Groep],"") -> Elektra | J9: =_xlfn.XLOOKUP(Q3_2025[[#This Row],[Artikelnr]],Artikel_prijzen[Artnr],Artikel_prijzen[Prijs 2025],"") -> 339.9 | K9: =IF(Q3_2025[[#This Row],[Artikelprijs]]<>"",IF(Q3_2025[[#This Row],[Stuksprijs]]=Q3_2025[[#This Row],[Artikelprijs]],"Prijs gelijk","Prijs wijkt af"),"") -> Prijs wijkt af | L9: =IF(Q3_2025[[#This Row],[Relatiekorting percentage]]=0, "Nvt", IF(Q3_2025[[#This Row],[Brutobedrag 2]] < Q3_2025[[#This Row],[Bruto - Rel.korting]], "Nee", "Ja")) -> Ja | M9: =IF(Q3_2025[[#This Row],[Artikelprijs]]<>"",Q3_2025[[#This Row],[Artikelprijs]],Q3_2025[[#This Row],[Stuksprijs]]) -> 339.9 | N9: =Q3_2025[[#This Row],[Besteld]]*Q3_2025[[#This Row],[Prijs 2]] -> 339.9 | O9: =IF(Q3_2025[[#This Row],[Brutobedrag 2]]<Q3_2025[[#This Row],[Bruto - Rel.korting]],Q3_2025[[#This Row],[Brutobedrag 2]],Q3_2025[[#This Row],[Brutobedrag 2]]*(100-Q3_2025[[#This Row],[Relatiekorting percentage]])/100) -> 237.93
A10: Albeda College - 2025.xls | B10: 3001102 | C10: Stroomaansl. 1kW + WCD + Verbruik 1d | D10: 12 | E10: 125.65 | F10: 1507.8 | G10: 1055.46 | H10: 30 | I10: =_xlfn.XLOOKUP(Q3_2025[[#This Row],[Artikelnr]],Artikel_prijzen[Artnr],Artikel_prijzen[Groep],"") -> Elektra | J10: =_xlfn.XLOOKUP(Q3_2025[[#This Row],[Artikelnr]],Artikel_prijzen[Artnr],Artikel_prijzen[Prijs 2025],"") -> 106.8625 | K10: =IF(Q3_2025[[#This Row],[Artikelprijs]]<>"",IF(Q3_2025[[#This Row],[Stuksprijs]]=Q3_2025[[#This Row],[Artikelprijs]],"Prijs gelijk","Prijs wijkt af"),"") -> Prijs wijkt af | L10: =IF(Q3_2025[[#This Row],[Relatiekorting percentage]]=0, "Nvt", IF(Q3_2025[[#This Row],[Brutobedrag 2]] < Q3_2025[[#This Row],[Bruto - Rel.korting]], "Nee", "Ja")) -> Ja | M10: =IF(Q3_2025[[#This Row],[Artikelprijs]]<>"",Q3_2025[[#This Row],[Artikelprijs]],Q3_2025[[#This Row],[Stuksprijs]]) -> 106.8625 | N10: =Q3_2025[[#This Row],[Besteld]]*Q3_2025[[#This Row],[Prijs 2]] -> 1282.35 | O10: =IF(Q3_2025[[#This Row],[Brutobedrag 2]]<Q3_2025[[#This Row],[Bruto - Rel.korting]],Q3_2025[[#This Row],[Brutobedrag 2]],Q3_2025[[#This Row],[Brutobedrag 2]]*(100-Q3_2025[[#This Row],[Relatiekorting percentage]])/100) -> 897.645
A11: Albeda College - 2025.xls | B11: 5020001 | C11: Wandcontactdoos 1kW | D11: 24 | E11: 29.35 | F11: 704.4 | G11: 493.08 | H11: 30 | I11: =_xlfn.XLOOKUP(Q3_2025[[#This Row],[Artikelnr]],Artikel_prijzen[Artnr],Artikel_prijzen[Groep],"") | J11: =_xlfn.XLOOKUP(Q3_2025[[#This Row],[Artikelnr]],Artikel_prijzen[Artnr],Artikel_prijzen[Prijs 2025],"") | K11: =IF(Q3_2025[[#This Row],[Artikelprijs]]<>"",IF(Q3_2025[[#This Row],[Stuksprijs]]=Q3_2025[[#This Row],[Artikelprijs]],"Prijs gelijk","Prijs wijkt af"),"") | L11: =IF(Q3_2025[[#This Row],[Relatiekorting percentage]]=0, "Nvt", IF(Q3_2025[[#This Row],[Brutobedrag 2]] < Q3_2025[[#This Row],[Bruto - Rel.korting]], "Nee", "Ja")) -> Ja | M11: =IF(Q3_2025[[#This Row],[Artikelprijs]]<>"",Q3_2025[[#This Row],[Artikelprijs]],Q3_2025[[#This Row],[Stuksprijs]]) -> 29.35 | N11: =Q3_2025[[#This Row],[Besteld]]*Q3_2025[[#This Row],[Prijs 2]] -> 704.4 | O11: =IF(Q3_2025[[#This Row],[Brutobedrag 2]]<Q3_2025[[#This Row],[Bruto - Rel.korting]],Q3_2025[[#This Row],[Brutobedrag 2]],Q3_2025[[#This Row],[Brutobedrag 2]]*(100-Q3_2025[[#This Row],[Relatiekorting percentage]])/100) -> 493.08
A12: Albeda College - 2025.xls | B12: 3001044 | C12: Wieland wandcontactdoos tot 3 Kw | D12: 24 | E12: 0 | F12: 0 | G12: 0 | H12: 0 | I12: =_xlfn.XLOOKUP(Q3_2025[[#This Row],[Artikelnr]],Artikel_prijzen[Artnr],Artikel_prijzen[Groep],"") | J12: =_xlfn.XLOOKUP(Q3_2025[[#This Row],[Artikelnr]],Artikel_prijzen[Artnr],Artikel_prijzen[Prijs 2025],"") | K12: =IF(Q3_2025[[#This Row],[Artikelprijs]]<>"",IF(Q3_2025[[#This Row],[Stuksprijs]]=Q3_2025[[#This Row],[Artikelprijs]],"Prijs gelijk","Prijs wijkt af"),"") | L12: =IF(Q3_2025[[#This Row],[Relatiekorting percentage]]=0, "Nvt", IF(Q3_2025[[#This Row],[Brutobedrag 2]] < Q3_2025[[#This Row],[Bruto - Rel.korting]], "Nee", "Ja")) -> Nvt | M12: =IF(Q3_2025[[#This Row],[Artikelprijs]]<>"",Q3_2025[[#This Row],[Artikelprijs]],Q3_2025[[#This Row],[Stuksprijs]]) -> 0 | N12: =Q3_2025[[#This Row],[Besteld]]*Q3_2025[[#This Row],[Prijs 2]] -> 0 | O12: =IF(Q3_2025[[#This Row],[Brutobedrag 2]]<Q3_2025[[#This Row],[Bruto - Rel.korting]],Q3_2025[[#This Row],[Brutobedrag 2]],Q3_2025[[#This Row],[Brutobedrag 2]]*(100-Q3_2025[[#This Row],[Relatiekorting percentage]])/100) -> 0
A13: Albeda College - 2025.xls | B13: 3001102 | C13: Stroomaansl. 1kW + WCD + Verbruik 1d | D13: 20 | E13: 125.65 | F13: 2513 | G13: 1759.1 | H13: 30 | I13: =_xlfn.XLOOKUP(Q3_2025[[#This Row],[Artikelnr]],Artikel_prijzen[Artnr],Artikel_prijzen[Groep],"") -> Elektra | J13: =_xlfn.XLOOKUP(Q3_2025[[#This Row],[Artikelnr]],Artikel_prijzen[Artnr],Artikel_prijzen[Prijs 2025],"") -> 106.8625 | K13: =IF(Q3_2025[[#This Row],[Artikelprijs]]<>"",IF(Q3_2025[[#This Row],[Stuksprijs]]=Q3_2025[[#This Row],[Artikelprijs]],"Prijs gelijk","Prijs wijkt af"),"") -> Prijs wijkt af | L13: =IF(Q3_2025[[#This Row],[Relatiekorting percentage]]=0, "Nvt", IF(Q3_2025[[#This Row],[Brutobedrag 2]] < Q3_2025[[#This Row],[Bruto - Rel.korting]], "Nee", "Ja")) -> Ja | M13: =IF(Q3_2025[[#This Row],[Artikelprijs]]<>"",Q3_2025[[#This Row],[Artikelprijs]],Q3_2025[[#This Row],[Stuksprijs]]) -> 106.8625 | N13: =Q3_2025[[#This Row],[Besteld]]*Q3_2025[[#This Row],[Prijs 2]] -> 2137.25 | O13: =IF(Q3_2025[[#This Row],[Brutobedrag 2]]<Q3_2025[[#This Row],[Bruto - Rel.korting]],Q3_2025[[#This Row],[Brutobedrag 2]],Q3_2025[[#This Row],[Brutobedrag 2]]*(100-Q3_2025[[#This Row],[Relatiekorting percentage]])/100) -> 1496.075
... A1819: Rotterdam Rave - 2025.xls | B1819: 5021001 | C1819: Stroomaansl. 3kW + WCD + Verbruik 1d | D1819: 6 | E1819: 154.5 | F1819: 927 | G1819: 741.6 | H1819: 20 | I1819: =_xlfn.XLOOKUP(Q3_2025[[#This Row],[Artikelnr]],Artikel_prijzen[Artnr],Artikel_prijzen[Groep],"") -> Elektra | J1819: =_xlfn.XLOOKUP(Q3_2025[[#This Row],[Artikelnr]],Artikel_prijzen[Artnr],Artikel_prijzen[Prijs 2025],"") -> 106.8625 | K1819: =IF(Q3_2025[[#This Row],[Artikelprijs]]<>"",IF(Q3_2025[[#This Row],[Stuksprijs]]=Q3_2025[[#This Row],[Artikelprijs]],"Prijs gelijk","Prijs wijkt af"),"") -> Prijs wijkt af | L1819: =IF(Q3_2025[[#This Row],[Relatiekorting percentage]]=0, "Nvt", IF(Q3_2025[[#This Row],[Brutobedrag 2]] < Q3_2025[[#This Row],[Bruto - Rel.korting]], "Nee", "Ja")) -> Nee | M1819: =IF(Q3_2025[[#This Row],[Artikelprijs]]<>"",Q3_2025[[#This Row],[Artikelprijs]],Q3_2025[[#This Row],[Stuksprijs]]) -> 106.8625 | N1819: =Q3_2025[[#This Row],[Besteld]]*Q3_2025[[#This Row],[Prijs 2]] -> 641.175 | O1819: =IF(Q3_2025[[#This Row],[Brutobedrag 2]]<Q3_2025[[#This Row],[Bruto - Rel.korting]],Q3_2025[[#This Row],[Brutobedrag 2]],Q3_2025[[#This Row],[Brutobedrag 2]]*(100-Q3_2025[[#This Row],[Relatiekorting percentage]])/100) -> 641.175
A1820: Totaal | F1820: =SUBTOTAL(109,Q3_2025[Brutobedrag]) -> 760767.03 | G1820: =SUBTOTAL(109,Q3_2025[Bruto - Rel.korting]) -> 630448.76 | N1820: =SUBTOTAL(109,Q3_2025[Brutobedrag 2]) -> 697741.23 | O1820: =SUBTOTAL(109,Q3_2025[Bruto-Rel. korting 2]) -> 581673.18

Sheet Q3 Provisie
B1: Provisie berekening Q3 2025
B4: Provisie | C4: Percentage | D4: Omzet | E4: Provisie
B5: Elektra | C5: 0.23 | D5: =C24 -> 276964.94 | E5: =C5*D5 -> 63701.936
B6: Rigging | C6: 0.16 | D6: =D24 -> 98784.25 | E6: =C6*D6 -> 15805.48
B7: AV | C7: 0.15 | D7: =E24 -> 7788.5 | E7: =C7*D7 -> 1168.275
B8: Omzet Q3 | C8: 0.05 | D8: =G24 -> 581673.18 | E8: =D8*C8 -> 29083.659
B9: Omzet voor het jaar | D9: ='Q2 Provisie '!D9+D8 -> 2857203.2
B10: Omzetstaffels 6,5% en 8% worden in Q4 verrekend
B11: TOTALE PROVISIE | E11: =SUM(E5:E10) -> 109759.35
B14: Evenementen Q3 2025 | C14: Elektra omzet | D14: Rigging omzet | E14: AV omzet | F14: Geen groep omzet | G14: Totaal Omzet | H14: Elektra provisie | I14: Rigging provisie | J14: AV Provisie
B15: {=_xlfn.UNIQUE(Q3_2025[Evenement])} -> Albeda College - 2025.xls | C15: =SUMIFS(Q3_2025[Bruto-Rel. korting 2],Q3_2025[Evenement],'Q3 Provisie'!B15,Q3_2025[Groep],'Q3 Provisie'!$B$5) -> 10309.294 | D15: =SUMIFS(Q3_2025[Bruto-Rel. korting 2],Q3_2025[Evenement],'Q3 Provisie'!B15,Q3_2025[Groep],'Q3 Provisie'!$B$6) -> 17547.5 | E15: =SUMIFS(Q3_2025[Bruto-Rel. korting 2],Q3_2025[Evenement],'Q3 Provisie'!B15,Q3_2025[Groep],'Q3 Provisie'!$B$7) -> 0 | F15: =SUMIFS(Q3_2025[Bruto-Rel. korting 2],Q3_2025[Evenement],'Q3 Provisie'!B15,Q3_2025[Groep],"") -> 39080.668 | G15: =SUM(C15:F15) -> 66937.462 | H15: =C15*$C$5 -> 2371.1376 | I15: =D15*$C$6 -> 2807.6 | J15: =E15*$C$7 -> 0
B16: Eurekaweek - 2025.xls | C16: =SUMIFS(Q3_2025[Bruto-Rel. korting 2],Q3_2025[Evenement],'Q3 Provisie'!B16,Q3_2025[Groep],'Q3 Provisie'!$B$5) -> 7633.05 | D16: =SUMIFS(Q3_2025[Bruto-Rel. korting 2],Q3_2025[Evenement],'Q3 Provisie'!B16,Q3_2025[Groep],'Q3 Provisie'!$B$6) -> 7556.25 | E16: =SUMIFS(Q3_2025[Bruto-Rel. korting 2],Q3_2025[Evenement],'Q3 Provisie'!B16,Q3_2025[Groep],'Q3 Provisie'!$B$7) -> 0 | F16: =SUMIFS(Q3_2025[Bruto-Rel. korting 2],Q3_2025[Evenement],'Q3 Provisie'!B16,Q3_2025[Groep],"") -> 441 | G16: =SUM(C16:F16) -> 15630.3 | H16: =C16*$C$5 -> 1755.6015 | I16: =D16*$C$6 -> 1209 | J16: =E16*$C$7 -> 0
B17: Gastvrij Elektra - 2025.xls | C17: =SUMIFS(Q3_2025[Bruto-Rel. korting 2],Q3_2025[Evenement],'Q3 Provisie'!B17,Q3_2025[Groep],'Q3 Provisie'!$B$5) -> 85167.55 | D17: =SUMIFS(Q3_2025[Bruto-Rel. korting 2],Q3_2025[Evenement],'Q3 Provisie'!B17,Q3_2025[Groep],'Q3 Provisie'!$B$6) -> 0 | E17: =SUMIFS(Q3_2025[Bruto-Rel. korting 2],Q3_2025[Evenement],'Q3 Provisie'!B17,Q3_2025[Groep],'Q3 Provisie'!$B$7) -> 2695 | F17: =SUMIFS(Q3_2025[Bruto-Rel. korting 2],Q3_2025[Evenement],'Q3 Provisie'!B17,Q3_2025[Groep],"") -> 4901.051 | G17: =SUM(C17:F17) -> 92763.601 | H17: =C17*$C$5 -> 19588.537 | I17: =D17*$C$6 -> 0 | J17: =E17*$C$7 -> 404.25
B18: Gastvrij Rigging - 2025.xls | C18: =SUMIFS(Q3_2025[Bruto-Rel. korting 2],Q3_2025[Evenement],'Q3 Provisie'!B18,Q3_2025[Groep],'Q3 Provisie'!$B$5) -> 0 | D18: =SUMIFS(Q3_2025[Bruto-Rel. korting 2],Q3_2025[Evenement],'Q3 Provisie'!B18,Q3_2025[Groep],'Q3 Provisie'!$B$6) -> 37629 | E18: =SUMIFS(Q3_2025[Bruto-Rel. korting 2],Q3_2025[Evenement],'Q3 Provisie'!B18,Q3_2025[Groep],'Q3 Provisie'!$B$7) -> 0 | F18: =SUMIFS(Q3_2025[Bruto-Rel. korting 2],Q3_2025[Evenement],'Q3 Provisie'!B18,Q3_2025[Groep],"") -> 2179.26 | G18: =SUM(C18:F18) -> 39808.26 | H18: =C18*$C$5 -> 0 | I18: =D18*$C$6 -> 6020.64 | J18: =E18*$C$7 -> 0
B19: Gastvrij Stands - 2025.xls | C19: =SUMIFS(Q3_2025[Bruto-Rel. korting 2],Q3_2025[Evenement],'Q3 Provisie'!B19,Q3_2025[Groep],'Q3 Provisie'!$B$5) -> 26803.365 | D19: =SUMIFS(Q3_2025[Bruto-Rel. korting 2],Q3_2025[Evenement],'Q3 Provisie'!B19,Q3_2025[Groep],'Q3 Provisie'!$B$6) -> 23441.5 | E19: =SUMIFS(Q3_2025[Bruto-Rel. korting 2],Q3_2025[Evenement],'Q3 Provisie'!B19,Q3_2025[Groep],'Q3 Provisie'!$B$7) -> 5093.5 | F19: =SUMIFS(Q3_2025[Bruto-Rel. korting 2],Q3_2025[Evenement],'Q3 Provisie'!B19,Q3_2025[Groep],"") -> 113109.09 | G19: =SUM(C19:F19) -> 168447.46 | H19: =C19*$C$5 -> 6164.7739 | I19: =D19*$C$6 -> 3750.64 | J19: =E19*$C$7 -> 764.025
B20: Jeugdvakantieland - 2025.xls | C20: =SUMIFS(Q3_2025[Bruto-Rel. korting 2],Q3_2025[Evenement],'Q3 Provisie'!B20,Q3_2025[Groep],'Q3 Provisie'!$B$5) -> 7121.935 | D20: =SUMIFS(Q3_2025[Bruto-Rel. korting 2],Q3_2025[Evenement],'Q3 Provisie'!B20,Q3_2025[Groep],'Q3 Provisie'!$B$6) -> 0 | E20: =SUMIFS(Q3_2025[Bruto-Rel. korting 2],Q3_2025[Evenement],'Q3 Provisie'!B20,Q3_2025[Groep],'Q3 Provisie'!$B$7) -> 0 | F20: =SUMIFS(Q3_2025[Bruto-Rel. korting 2],Q3_2025[Evenement],'Q3 Provisie'!B20,Q3_2025[Groep],"") -> 3474.388 | G20: =SUM(C20:F20) -> 10596.323 | H20: =C20*$C$5 -> 1638.045 | I20: =D20*$C$6 -> 0 | J20: =E20*$C$7 -> 0
B21: North Sea Jazz - 2025.xls | C21: =SUMIFS(Q3_2025[Bruto-Rel. korting 2],Q3_2025[Evenement],'Q3 Provisie'!B21,Q3_2025[Groep],'Q3 Provisie'!$B$5) -> 112673.9 | D21: =SUMIFS(Q3_2025[Bruto-Rel. korting 2],Q3_2025[Evenement],'Q3 Provisie'!B21,Q3_2025[Groep],'Q3 Provisie'!$B$6) -> 1840 | E21: =SUMIFS(Q3_2025[Bruto-Rel. korting 2],Q3_2025[Evenement],'Q3 Provisie'!B21,Q3_2025[Groep],'Q3 Provisie'!$B$7) -> 0 | F21: =SUMIFS(Q3_2025[Bruto-Rel. korting 2],Q3_2025[Evenement],'Q3 Provisie'!B21,Q3_2025[Groep],"") -> 31812.011 | G21: =SUM(C21:F21) -> 146325.91 | H21: =C21*$C$5 -> 25914.996 | I21: =D21*$C$6 -> 294.4 | J21: =E21*$C$7 -> 0
B22: Premier Padel - 2025.xls | C22: =SUMIFS(Q3_2025[Bruto-Rel. korting 2],Q3_2025[Evenement],'Q3 Provisie'!B22,Q3_2025[Groep],'Q3 Provisie'!$B$5) -> 11455.662 | D22: =SUMIFS(Q3_2025[Bruto-Rel. korting 2],Q3_2025[Evenement],'Q3 Provisie'!B22,Q3_2025[Groep],'Q3 Provisie'!$B$6) -> 10770 | E22: =SUMIFS(Q3_2025[Bruto-Rel. korting 2],Q3_2025[Evenement],'Q3 Provisie'!B22,Q3_2025[Groep],'Q3 Provisie'!$B$7) -> 0 | F22: =SUMIFS(Q3_2025[Bruto-Rel. korting 2],Q3_2025[Evenement],'Q3 Provisie'!B22,Q3_2025[Groep],"") -> 2702.417 | G22: =SUM(C22:F22) -> 24928.079 | H22: =C22*$C$5 -> 2634.8024 | I22: =D22*$C$6 -> 1723.2 | J22: =E22*$C$7 -> 0
B23: Rotterdam Rave - 2025.xls | C23: =SUMIFS(Q3_2025[Bruto-Rel. korting 2],Q3_2025[Evenement],'Q3 Provisie'!B23,Q3_2025[Groep],'Q3 Provisie'!$B$5) -> 15800.19 | D23: =SUMIFS(Q3_2025[Bruto-Rel. korting 2],Q3_2025[Evenement],'Q3 Provisie'!B23,Q3_2025[Groep],'Q3 Provisie'!$B$6) -> 0 | E23: =SUMIFS(Q3_2025[Bruto-Rel. korting 2],Q3_2025[Evenement],'Q3 Provisie'!B23,Q3_2025[Groep],'Q3 Provisie'!$B$7) -> 0 | F23: =SUMIFS(Q3_2025[Bruto-Rel. korting 2],Q3_2025[Evenement],'Q3 Provisie'!B23,Q3_2025[Groep],"") -> 435.6 | G23: =SUM(C23:F23) -> 16235.79 | H23: =C23*$C$5 -> 3634.0437 | I23: =D23*$C$6 -> 0 | J23: =E23*$C$7 -> 0
B24: TOTAAL | C24: =SUM(C15:C23) -> 276964.94 | D24: =SUM(D15:D23) -> 98784.25 | E24: =SUM(E15:E23) -> 7788.5 | F24: =SUM(F15:F23) -> 198135.49 | G24: =SUM(G15:G23) -> 581673.18 | H24: =SUM(H15:H23) -> 63701.936 | I24: =SUM(I15:I23) -> 15805.48 | J24: =SUM(J15:J23) -> 1168.275

Sheet Q3 PT
A3: Evenement | B3: Artikelnr | C3: Omschrijving | D3: Groep | E3: Som van Besteld
A4: Albeda College - 2025.xls | B4: 1007023 | C4: Prikkabel 10m LED wit | E4: 1
B5: 1007051 | C5: Multipar LED 150w DMX 3000-6500K | E5: 34
B6: 1010006 | C6: Nooduitgang verlichting | E6: 2
B7: 1010007 | C7: Nooduitgang verlichting pijl naar rechts | E7: 2
B8: 1010008 | C8: Nooduitgang verlichting pijl naar beneden | E8: 2
B9: 1010010 | C9: Wand montage plaat | E9: 2
B10: 1010011 | C10: Systeem montage plaat | E10: 2
B11: 2004003 | C11: Handtakel 500 kg 10m excl. Ophangpunt | E11: 10
B12: 2004006 | C12: Controller motortakel V08 - 32A | E12: 8
B13: 2004053 | C13: Motortakel 500 kg 20m D8+ excl. ophangpunt | E13: 69
B14: 2004075 | C14: Harp 0.33 ton zwart | E14: 3
B15: 3001044 | C15: Wieland wandcontactdoos tot 3 Kw | E15: 125
B16: 3001102 | C16: Stroomaansl. 1kW + WCD + Verbruik 1d | D16: Elektra | E16: 79
B17: 3001111 | C17: Verlengkabel CEE 16A/230V 3x2,5mm² 25m | E17: 7
B18: 3001129 | C18: Verlengkabel CEE 16A/230V 3x2,5mm² 35m | E18: 7
B19: 4801003 | C19: Nooduitgang verlichting | E19: 2
B20: 5010001 | C20: Avolites - Pearl Tiger Touch II console | E20: 1
C21: Bekabeling, materiaal en materieel | E21: 1
C22: CLF - Hera | E22: 139
C23: CLF Ares - floodlight zaal | E23: 104
C24: Prikkabel 25m LED wit | E24: 30
B25: 5020001 | C25: Wandcontactdoos 1kW | E25: 125
B26: 5021026 | C26: Stroomaansl. 3kW + WCD + Verbruik 2d | D26: Elektra | E26: 1
B27: 5022013 | C27: Power supply 6 kW (incl. CEE 32A & Power Consumption) 2d | D27: Elektra | E27: 9
B28: 5022015 | C28: Power supply 12 kW (incl. CEE 32A & Power Consumption) 2d | D28: Elektra | E28: 4
B29: 5022020 | C29: Power supply 50 kW (incl. CEE 125A & Power Consumption) 2d | D29: Elektra | E29: 2
B30: 5030003 | C30: Zip clip | E30: 6
B31: 5030005 | C31: Voedingskabel via dak (van ophangpunt naar zijkant hal) | D31: Rigging | E31: 15
B32: 5030228 | C32: Handtakel incl. ophangpunt + montage max 250kg | D32: Rigging | E32: 10
B33: 5030229 | C33: Motortakel incl. ophangpunt + montage max 250kg | D33: Rigging | E33: 69
B34: 5030232 | C34: Voedingskabel via dak (van berging naar ophangpunt) | D34: Rigging | E34: 13
B35: 5030234 | C35: Ophangen vlag/banner (max 3m / 20kg) | D35: Rigging | E35: 3
B36: 5031009 | C36: Prolyte truss X30D 3 meter zwart | E36: 219
B37: 5031074 | C37: P&D - 3,00(h) m - 3,00(b) per m¹ (zwart) | E37: 40
B38: 5031075 | C38: P&D - 3,00(h) m - 3,00(b) per m¹ (wit) | E38: 40
B39: 5031076 | C39: P&D - 3,00(h) m - 3,00(b) per m¹ (rood) | E39: 40
A40: Eurekaweek - 2025.xls | B40: 3098016 | C40: Vloerkabelbrug Rubber 2K 98x24x5 zwart geel | E40: 28
B41: 5022014 | C41: Power supply 9 kW (incl. CEE 32A & Power Consumption) 2d | D41: Elektra | E41: 2
B42: 5022016 | C42: Power supply 15 kW (incl. CEE 32A & Power Consumption) 2d | D42: Elektra | E42: 8
B43: 5022018 | C43: Power supply 30 kW (incl. CEE 63A & Power Consumption) 2d | D43: Elektra | E43: 7
B44: 5030226 | C44: Ophangpunt t.b.v. takel tot 500kg | D44: Rigging | E44: 65
A45: Gastvrij Elektra - 2025.xls | B45: 1003012 | C45: Inbouwspot Lika LED 9W 3000K Ø 83mm wit | E45: 3
B46: 1007051 | C46: Multipar LED 150w DMX 3000-6500K | E46: 1
B47: 3001079 | C47: Verloop CEE male/ wieland female | E47: 6
B48: 3002024 | C48: Groepenkast (wieland) 63A/40 kw 12x230V/1x400V/16A1x400V/32A | E48: 2
B49: 3002030 | C49: Groepenkast (Cubes) 32A tot 20 kw 6xCEE 230V | E49: 3
B50: 3002032 | C50: Groepenkast (Cubes) 63A tot 40 kw 1x16A, 2x32A, 12x230V/CEE | E50: 1
B51: 3002038 | C51: VDK(HK) 32A/20kW 6x230V-CEE | E51: 5
B52: 3002039 | C52: VDK(Cube) 32A/20kW 6x230V-CEE | E52: 1
B53: 5010014 | C53: Pendelspot Sis LED 10W par 30 zilver | E53: 2
B54: 5010016 | C54: Pendel LED Luxa 30W / 3000K zilver | E54: 1
C55: Pendel LED Luxa 30W / 3000K zilver (niet in truss!) | E55: 4
B56: 5010017 | C56: Pendel LED Luxa 30W / 4000K zilver | E56: 6
B57: 5020001 | C57: Wandcontactdoos 1kW | E57: 4
B58: 5020002 | C58: Wall socket adapter 3kW | E58: 1
C59: Wandcontactdoos 3kW | E59: 16
B60: 5020003 | C60: Contactdoos CEE 16A/400V | E60: 9
B61: 5020004 | C61: Contactdoos CEE 32A/400V | E61: 3
B62: 5020005 | C62: Power rail + 1 raillight LED 20W tri color - 3000/4000K | E62: 1
B63: 5020008 | C63: Rail + 2 spots LED 20W tri color - 3000K/4000K | E63: 4
B64: 5020009 | C64: Power rail + 3 raillight LED 20W tri color - 3000/4000K | E64: 1
C65: Rail + 3 spots LED 20W tri color - 3000K/4000K | E65: 6
B66: 5020010 | C66: Extra spot 20W tri color - 3000K/4000K | E66: 1
B67: 5020011 | C67: Verdeelkast 32A CEE > 230V schuko | E67: 1
B68: 5021030 | C68: Power connection 3kW + wall socket + consumption | D68: Elektra | E68: 1
C69: power supply. 3kW + WCD + Verbruik 3d | D69: Elektra | E69: 1
C70: Stroomaansl. 3kW + WCD + Verbruik 3d | D70: Elektra | E70: 178
B71: 5022012 | C71: Verdeelblok 3v wcd | E71: 1
B72: 5022023 | C72: Power supply 6 kW (incl. CEE 32A & Power Consumption) 3d | D72: Elektra | E72: 19
B73: 5022024 | C73: A0 Verdeelkast 125A Blok+D > 2x63A / 4x32A / 3xCEE / 3x sch. | E73: 6
B74: 5022026 | C74: Power supply 9 kW (incl. CEE 32A & Power Consumption) 3d | D74: Elektra | E74: 19
B75: 5022028 | C75: Power supply 12 kW (incl. CEE 32A & Power Consumption) 3d | D75: Elektra | E75: 1
B76: 5022030 | C76: Power supply 15 kW (incl. CEE 32A & Power Consumption) 3d | D76: Elektra | E76: 22
B77: 5022032 | C77: Power supply 20 kW (incl. CEE 32A & Power Consumption) 3d | D77: Elektra | E77: 28
B78: 5022038 | C78: Power supply 40 kW (incl. CEE 63A & Power Consumption) 3d | D78: Elektra | E78: 13
B79: 5022042 | C79: Power supply 60 kW (incl. CEE 125A & Power Consumption) 3d | D79: Elektra | E79: 4
B80: 5022044 | C80: Power supply 80 kW (incl. CEE 125A & Power Consumption) 3d | D80: Elektra | E80: 4
B81: 5022046 | C81: Power supply 6 kW (incl. 2x WCD 230V & Power Consumption) 3d | D81: Elektra | E81: 18
B82: 5022048 | C82: Power supply 9 kW (incl. 3x WCD 230V & Power Consumption) 3d | D82: Elektra | E82: 9
B83: 5022052 | C83: Power supply 15 kW (incl. 5x WCD 230V & Power Consumption)3d | D83: Elektra | E83: 3
B84: 5022054 | C84: Power supply 20 kW (incl. 6x WCD 230V & Power Consumption)3d | D84: Elektra | E84: 8
B85: 5040007 | C85: LCD LED Display 32" | D85: AV | E85: 1
... B87: 5040010 | C87: LCD LED Display 55" | D87: AV | E87: 4
B88: 5040016 | C88: Geluidset 2 speakers (incl. headset/handheld) | E88: 1
B89: 5040018 | C89: Design stand (Smartmetals light) !MAX 55 INCH! | E89: 3
A90: Gastvrij Rigging - 2025.xls | B90: 2004057 | C90: Hanging set Reutlinger black | E90: 4
B91: 2004082 | C91: Kabelset motortakels (set voor 4 takels) | E91: 2
B92: 5030001 | C92: Pre-Rigging P36R (per meter) | D92: Rigging | E92: 18
B93: 5030005 | C93: Voedingskabel via dak (van ophangpunt naar zijkant hal) | D93: Rigging | E93: 2
B94: 5030028 | C94: Pre-Rigging H30V (per meter) | E94: 62
B95: 5030225 | C95: Ophangpunt Staalkabel 5mm tot 150kg | D95: Rigging | E95: 7
B96: 5030228 | C96: Handtakel incl. ophangpunt + montage max 250kg | D96: Rigging | E96: 99
C97: Manual chainhoist incl. riggingpoint + assembly max 250kg | D97: Rigging | E97: 9
B98: 5030229 | C98: Motortakel incl. ophangpunt + montage max 250kg | D98: Rigging | E98: 30
B99: 5030232 | C99: Power supply line roof (from storage to riggingpoint) | D99: Rigging | E99: 1
C100: Voedingskabel via dak (van berging naar ophangpunt) | D100: Rigging | E100: 13
B101: 5030234 | C101: Rigging flag/banner (max 3m / 20kg) | D101: Rigging | E101: 1
A102: Gastvrij Stands - 2025.xls | B102: 1001009 | C102: Railspot Lumina LED 30w tri color zwart | E102: 13
B103: 1001027 | C103: Railspot Sintra LED 15w 4000K zwart | E103: 8
...

Sheet Q4 2025
A1: Evenement | B1: Artikelnr | C1: Omschrijving | D1: Besteld | E1: Stuksprijs | F1: Brutobedrag | G1: Bruto - Rel.korting | H1: Relatiekorting percentage | I1: Groep | J1: Artikelprijs | K1: Vergelijk | L1: Relatie korting | M1: Prijs 2 | N1: Brutobedrag 2 | O1: Bruto-Rel. korting 2
A2: 100% Auto Live - 2025.xls | B2: 5021026 | C2: Stroomaansl. 3kW + WCD + Verbruik 2d | D2: 40 | E2: 164.8 | F2: 6592 | G2: 6592 | H2: 0 | I2: =_xlfn.XLOOKUP(Q4_2025[[#This Row],[Artikelnr]],Artikel_prijzen[Artnr],Artikel_prijzen[Groep],"") -> Elektra | J2: =_xlfn.XLOOKUP(Q4_2025[[#This Row],[Artikelnr]],Artikel_prijzen[Artnr],Artikel_prijzen[Prijs 2025],"") -> 106.8625 | K2: =IF(Q4_2025[[#This Row],[Artikelprijs]]<>"",IF(Q4_2025[[#This Row],[Stuksprijs]]=Q4_2025[[#This Row],[Artikelprijs]],"Prijs gelijk","Prijs wijkt af"),"") -> Prijs wijkt af | L2: =IF(Q4_2025[[#This Row],[Relatiekorting percentage]]=0, "Nvt", IF(Q4_2025[[#This Row],[Brutobedrag 2]] < Q4_2025[[#This Row],[Bruto - Rel.korting]], "Nee", "Ja")) -> Nvt | M2: =IF(Q4_2025[[#This Row],[Artikelprijs]]<>"",Q4_2025[[#This Row],[Artikelprijs]],Q4_2025[[#This Row],[Stuksprijs]]) -> 106.8625 | N2: =Q4_2025[[#This Row],[Besteld]]*Q4_2025[[#This Row],[Prijs 2]] -> 4274.5 | O2: =IF(Q4_2025[[#This Row],[Brutobedrag 2]]<Q4_2025[[#This Row],[Bruto - Rel.korting]],Q4_2025[[#This Row],[Brutobedrag 2]],Q4_2025[[#This Row],[Brutobedrag 2]]*(100-Q4_2025[[#This Row],[Relatiekorting percentage]])/100) -> 4274.5
A3: 100% Auto Live - 2025.xls | B3: 5022013 | C3: Power supply 6 kW (incl. CEE 32A & Power Consumption) 2d | D3: 2 | E3: 317.69 | F3: 635.38 | G3: 635.38 | H3: 0 | I3: =_xlfn.XLOOKUP(Q4_2025[[#This Row],[Artikelnr]],Artikel_prijzen[Artnr],Artikel_prijzen[Groep],"") -> Elektra | J3: =_xlfn.XLOOKUP(Q4_2025[[#This Row],[Artikelnr]],Artikel_prijzen[Artnr],Artikel_prijzen[Prijs 2025],"") -> 252.35 | K3: =IF(Q4_2025[[#This Row],[Artikelprijs]]<>"",IF(Q4_2025[[#This Row],[Stuksprijs]]=Q4_2025[[#This Row],[Artikelprijs]],"Prijs gelijk","Prijs wijkt af"),"") -> Prijs wijkt af | L3: =IF(Q4_2025[[#This Row],[Relatiekorting percentage]]=0, "Nvt", IF(Q4_2025[[#This Row],[Brutobedrag 2]] < Q4_2025[[#This Row],[Bruto - Rel.korting]], "Nee", "Ja")) -> Nvt | M3: =IF(Q4_2025[[#This Row],[Artikelprijs]]<>"",Q4_2025[[#This Row],[Artikelprijs]],Q4_2025[[#This Row],[Stuksprijs]]) -> 252.35 | N3: =Q4_2025[[#This Row],[Besteld]]*Q4_2025[[#This Row],[Prijs 2]] -> 504.7 | O3: =IF(Q4_2025[[#This Row],[Brutobedrag 2]]<Q4_2025[[#This Row],[Bruto - Rel.korting]],Q4_2025[[#This Row],[Brutobedrag 2]],Q4_2025[[#This Row],[Brutobedrag 2]]*(100-Q4_2025[[#This Row],[Relatiekorting percentage]])/100) -> 504.7
A4: 100% Auto Live - 2025.xls | B4: 5021004 | C4: Power supply 6 kW (incl. 2x WCD 230V & Power Consumption) 2d | D4: 1 | E4: 394.94 | F4: 394.94 | G4: 394.94 | H4: 0 | I4: =_xlfn.XLOOKUP(Q4_2025[[#This Row],[Artikelnr]],Artikel_prijzen[Artnr],Artikel_prijzen[Groep],"") -> Elektra | J4: =_xlfn.XLOOKUP(Q4_2025[[#This Row],[Artikelnr]],Artikel_prijzen[Artnr],Artikel_prijzen[Prijs 2025],"") -> 329.6 | K4: =IF(Q4_2025[[#This Row],[Artikelprijs]]<>"",IF(Q4_2025[[#This Row],[Stuksprijs]]=Q4_2025[[#This Row],[Artikelprijs]],"Prijs gelijk","Prijs wijkt af"),"") -> Prijs wijkt af | L4: =IF(Q4_2025[[#This Row],[Relatiekorting percentage]]=0, "Nvt", IF(Q4_2025[[#This Row],[Brutobedrag 2]] < Q4_2025[[#This Row],[Bruto - Rel.korting]], "Nee", "Ja")) -> Nvt | M4: =IF(Q4_2025[[#This Row],[Artikelprijs]]<>"",Q4_2025[[#This Row],[Artikelprijs]],Q4_2025[[#This Row],[Stuksprijs]]) -> 329.6 | N4: =Q4_2025[[#This Row],[Besteld]]*Q4_2025[[#This Row],[Prijs 2]] -> 329.6 | O4: =IF(Q4_2025[[#This Row],[Brutobedrag 2]]<Q4_2025[[#This Row],[Bruto - Rel.korting]],Q4_2025[[#This Row],[Brutobedrag 2]],Q4_2025[[#This Row],[Brutobedrag 2]]*(100-Q4_2025[[#This Row],[Relatiekorting percentage]])/100) -> 329.6
A5: 100% Auto Live - 2025.xls | B5: 5022019 | C5: Power supply 40 kW (incl. CEE 63A & Power Consumption) 2d | D5: 1 | E5: 1025.92 | F5: 1025.92 | G5: 1025.92 | H5: 0 | I5: =_xlfn.XLOOKUP(Q4_2025[[#This Row],[Artikelnr]],Artikel_prijzen[Artnr],Artikel_prijzen[Groep],"") -> Elektra | J5: =_xlfn.XLOOKUP(Q4_2025[[#This Row],[Artikelnr]],Artikel_prijzen[Artnr],Artikel_prijzen[Prijs 2025],"") -> 700 | K5: =IF(Q4_2025[[#This Row],[Artikelprijs]]<>"",IF(Q4_2025[[#This Row],[Stuksprijs]]=Q4_2025[[#This Row],[Artikelprijs]],"Prijs gelijk","Prijs wijkt af"),"") -> Prijs wijkt af | L5: =IF(Q4_2025[[#This Row],[Relatiekorting percentage]]=0, "Nvt", IF(Q4_2025[[#This Row],[Brutobedrag 2]] < Q4_2025[[#This Row],[Bruto - Rel.korting]], "Nee", "Ja")) -> Nvt | M5: =IF(Q4_2025[[#This Row],[Artikelprijs]]<>"",Q4_2025[[#This Row],[Artikelprijs]],Q4_2025[[#This Row],[Stuksprijs]]) -> 700 | N5: =Q4_2025[[#This Row],[Besteld]]*Q4_2025[[#This Row],[Prijs 2]] -> 700 | O5: =IF(Q4_2025[[#This Row],[Brutobedrag 2]]<Q4_2025[[#This Row],[Bruto - Rel.korting]],Q4_2025[[#This Row],[Brutobedrag 2]],Q4_2025[[#This Row],[Brutobedrag 2]]*(100-Q4_2025[[#This Row],[Relatiekorting percentage]])/100) -> 700
A6: 100% Auto Live - 2025.xls | B6: 5022017 | C6: Power supply 20 kW (incl. CEE 32A & Power Consumption) 2d | D6: 3 | E6: 632.59 | F6: 1897.77 | G6: 1897.77 | H6: 0 | I6: =_xlfn.XLOOKUP(Q4_2025[[#This Row],[Artikelnr]],Artikel_prijzen[Artnr],Artikel_prijzen[Groep],"") -> Elektra | J6: =_xlfn.XLOOKUP(Q4_2025[[#This Row],[Artikelnr]],Artikel_prijzen[Artnr],Artikel_prijzen[Prijs 2025],"") -> 458.35 | K6: =IF(Q4_2025[[#This Row],[Artikelprijs]]<>"",IF(Q4_2025[[#This Row],[Stuksprijs]]=Q4_2025[[#This Row],[Artikelprijs]],"Prijs gelijk","Prijs wijkt af"),"") -> Prijs wijkt af | L6: =IF(Q4_2025[[#This Row],[Relatiekorting percentage]]=0, "Nvt", IF(Q4_2025[[#This Row],[Brutobedrag 2]] < Q4_2025[[#This Row],[Bruto - Rel.korting]], "Nee", "Ja")) -> Nvt | M6: =IF(Q4_2025[[#This Row],[Artikelprijs]]<>"",Q4_2025[[#This Row],[Artikelprijs]],Q4_2025[[#This Row],[Stuksprijs]]) -> 458.35 | N6: =Q4_2025[[#This Row],[Besteld]]*Q4_2025[[#This Row],[Prijs 2]] -> 1375.05 | O6: =IF(Q4_2025[[#This Row],[Brutobedrag 2]]<Q4_2025[[#This Row],[Bruto - Rel.korting]],Q4_2025[[#This Row],[Brutobedrag 2]],Q4_2025[[#This Row],[Brutobedrag 2]]*(100-Q4_2025[[#This Row],[Relatiekorting percentage]])/100) -> 1375.05
A7: 100% Auto Live - 2025.xls | B7: 5021026 | C7: Stroomaansl. 3kW + WCD + Verbruik 2d | D7: 1 | E7: 164.8 | F7: 164.8 | G7: 164.8 | H7: 0 | I7: =_xlfn.XLOOKUP(Q4_2025[[#This Row],[Artikelnr]],Artikel_prijzen[Artnr],Artikel_prijzen[Groep],"") -> Elektra | J7: =_xlfn.XLOOKUP(Q4_2025[[#This Row],[Artikelnr]],Artikel_prijzen[Artnr],Artikel_prijzen[Prijs 2025],"") -> 106.8625 | K7: =IF(Q4_2025[[#This Row],[Artikelprijs]]<>"",IF(Q4_2025[[#This Row],[Stuksprijs]]=Q4_2025[[#This Row],[Artikelprijs]],"Prijs gelijk","Prijs wijkt af"),"") -> Prijs wijkt af | L7: =IF(Q4_2025[[#This Row],[Relatiekorting percentage]]=0, "Nvt", IF(Q4_2025[[#This Row],[Brutobedrag 2]] < Q4_2025[[#This Row],[Bruto - Rel.korting]], "Nee", "Ja")) -> Nvt | M7: =IF(Q4_2025[[#This Row],[Artikelprijs]]<>"",Q4_2025[[#This Row],[Artikelprijs]],Q4_2025[[#This Row],[Stuksprijs]]) -> 106.8625 | N7: =Q4_2025[[#This Row],[Besteld]]*Q4_2025[[#This Row],[Prijs 2]] -> 106.8625 | O7: =IF(Q4_2025[[#This Row],[Brutobedrag 2]]<Q4_2025[[#This Row],[Bruto - Rel.korting]],Q4_2025[[#This Row],[Brutobedrag 2]],Q4_2025[[#This Row],[Brutobedrag 2]]*(100-Q4_2025[[#This Row],[Relatiekorting percentage]])/100) -> 106.8625
A8: 100% Auto Live - 2025.xls | B8: 5030230 | C8: Inhangen motortakel incl. ophangpunt, excl huur | D8: 8 | E8: 247.2 | F8: 1977.6 | G8: 1977.6 | H8: 0 | I8: =_xlfn.XLOOKUP(Q4_2025[[#This Row],[Artikelnr]],Artikel_prijzen[Artnr],Artikel_prijzen[Groep],"") -> Rigging | J8: =_xlfn.XLOOKUP(Q4_2025[[#This Row],[Artikelnr]],Artikel_prijzen[Artnr],Artikel_prijzen[Prijs 2025],"") -> 240 | K8: =IF(Q4_2025[[#This Row],[Artikelprijs]]<>"",IF(Q4_2025[[#This Row],[Stuksprijs]]=Q4_2025[[#This Row],[Artikelprijs]],"Prijs gelijk","Prijs wijkt af"),"") -> Prijs wijkt af | L8: =IF(Q4_2025[[#This Row],[Relatiekorting percentage]]=0, "Nvt", IF(Q4_2025[[#This Row],[Brutobedrag 2]] < Q4_2025[[#This Row],[Bruto - Rel.korting]], "Nee", "Ja")) -> Nvt | M8: =IF(Q4_2025[[#This Row],[Artikelprijs]]<>"",Q4_2025[[#This Row],[Artikelprijs]],Q4_2025[[#This Row],[Stuksprijs]]) -> 240 | N8: =Q4_2025[[#This Row],[Besteld]]*Q4_2025[[#This Row],[Prijs 2]] -> 1920 | O8: =IF(Q4_2025[[#This Row],[Brutobedrag 2]]<Q4_2025[[#This Row],[Bruto - Rel.korting]],Q4_2025[[#This Row],[Brutobedrag 2]],Q4_2025[[#This Row],[Brutobedrag 2]]*(100-Q4_2025[[#This Row],[Relatiekorting percentage]])/100) -> 1920
A9: 100% Auto Live - 2025.xls | B9: 5021026 | C9: Stroomaansl. 3kW + WCD + Verbruik 2d | D9: 2 | E9: 164.8 | F9: 329.6 | G9: 329.6 | H9: 0 | I9: =_xlfn.XLOOKUP(Q4_2025[[#This Row],[Artikelnr]],Artikel_prijzen[Artnr],Artikel_prijzen[Groep],"") -> Elektra | J9: =_xlfn.XLOOKUP(Q4_2025[[#This Row],[Artikelnr]],Artikel_prijzen[Artnr],Artikel_prijzen[Prijs 2025],"") -> 106.8625 | K9: =IF(Q4_2025[[#This Row],[Artikelprijs]]<>"",IF(Q4_2025[[#This Row],[Stuksprijs]]=Q4_2025[[#This Row],[Artikelprijs]],"Prijs gelijk","Prijs wijkt af"),"") -> Prijs wijkt af | L9: =IF(Q4_2025[[#This Row],[Relatiekorting percentage]]=0, "Nvt", IF(Q4_2025[[#This Row],[Brutobedrag 2]] < Q4_2025[[#This Row],[Bruto - Rel.korting]], "Nee", "Ja")) -> Nvt | M9: =IF(Q4_2025[[#This Row],[Artikelprijs]]<>"",Q4_2025[[#This Row],[Artikelprijs]],Q4_2025[[#This Row],[Stuksprijs]]) -> 106.8625 | N9: =Q4_2025[[#This Row],[Besteld]]*Q4_2025[[#This Row],[Prijs 2]] -> 213.725 | O9: =IF(Q4_2025[[#This Row],[Brutobedrag 2]]<Q4_2025[[#This Row],[Bruto - Rel.korting]],Q4_2025[[#This Row],[Brutobedrag 2]],Q4_2025[[#This Row],[Brutobedrag 2]]*(100-Q4_2025[[#This Row],[Relatiekorting percentage]])/100) -> 213.725
A10: 100% Auto Live - 2025.xls | B10: 5030005 | C10: Voedingskabel via dak (van ophangpunt naar zijkant hal) | D10: 1 | E10: 200.85 | F10: 200.85 | G10: 200.85 | H10: 0 | I10: =_xlfn.XLOOKUP(Q4_2025[[#This Row],[Artikelnr]],Artikel_prijzen[Artnr],Artikel_prijzen[Groep],"") -> Rigging | J10: =_xlfn.XLOOKUP(Q4_2025[[#This Row],[Artikelnr]],Artikel_prijzen[Artnr],Artikel_prijzen[Prijs 2025],"") -> 195 | K10: =IF(Q4_2025[[#This Row],[Artikelprijs]]<>"",IF(Q4_2025[[#This Row],[Stuksprijs]]=Q4_2025[[#This Row],[Artikelprijs]],"Prijs gelijk","Prijs wijkt af"),"") -> Prijs wijkt af | L10: =IF(Q4_2025[[#This Row],[Relatiekorting percentage]]=0, "Nvt", IF(Q4_2025[[#This Row],[Brutobedrag 2]] < Q4_2025[[#This Row],[Bruto - Rel.korting]], "Nee", "Ja")) -> Nvt | M10: =IF(Q4_2025[[#This Row],[Artikelprijs]]<>"",Q4_2025[[#This Row],[Artikelprijs]],Q4_2025[[#This Row],[Stuksprijs]]) -> 195 | N10: =Q4_2025[[#This Row],[Besteld]]*Q4_2025[[#This Row],[Prijs 2]] -> 195 | O10: =IF(Q4_2025[[#This Row],[Brutobedrag 2]]<Q4_2025[[#This Row],[Bruto - Rel.korting]],Q4_2025[[#This Row],[Brutobedrag 2]],Q4_2025[[#This Row],[Brutobedrag 2]]*(100-Q4_2025[[#This Row],[Relatiekorting percentage]])/100) -> 195
A11: 100% Auto Live - 2025.xls | B11: 5022013 | C11: Power supply 6 kW (incl. CEE 32A & Power Consumption) 2d | D11: 1 | E11: 317.69 | F11: 317.69 | G11: 317.69 | H11: 0 | I11: =_xlfn.XLOOKUP(Q4_2025[[#This Row],[Artikelnr]],Artikel_prijzen[Artnr],Artikel_prijzen[Groep],"") -> Elektra | J11: =_xlfn.XLOOKUP(Q4_2025[[#This Row],[Artikelnr]],Artikel_prijzen[Artnr],Artikel_prijzen[Prijs 2025],"") -> 252.35 | K11: =IF(Q4_2025[[#This Row],[Artikelprijs]]<>"",IF(Q4_2025[[#This Row],[Stuksprijs]]=Q4_2025[[#This Row],[Artikelprijs]],"Prijs gelijk","Prijs wijkt af"),"") -> Prijs wijkt af | L11: =IF(Q4_2025[[#This Row],[Relatiekorting percentage]]=0, "Nvt", IF(Q4_2025[[#This Row],[Brutobedrag 2]] < Q4_2025[[#This Row],[Bruto - Rel.korting]], "Nee", "Ja")) -> Nvt | M11: =IF(Q4_2025[[#This Row],[Artikelprijs]]<>"",Q4_2025[[#This Row],[Artikelprijs]],Q4_2025[[#This Row],[Stuksprijs]]) -> 252.35 | N11: =Q4_2025[[#This Row],[Besteld]]*Q4_2025[[#This Row],[Prijs 2]] -> 252.35 | O11: =IF(Q4_2025[[#This Row],[Brutobedrag 2]]<Q4_2025[[#This Row],[Bruto - Rel.korting]],Q4_2025[[#This Row],[Brutobedrag 2]],Q4_2025[[#This Row],[Brutobedrag 2]]*(100-Q4_2025[[#This Row],[Relatiekorting percentage]])/100) -> 252.35
A12: 100% Auto Live - 2025.xls | B12: 5021026 | C12: Stroomaansl. 3kW + WCD + Verbruik 2d | D12: -1 | E12: 164.8 | F12: -164.8 | G12: -164.8 | H12: 0 | I12: =_xlfn.XLOOKUP(Q4_2025[[#This Row],[Artikelnr]],Artikel_prijzen[Artnr],Artikel_prijzen[Groep],"") -> Elektra | J12: =_xlfn.XLOOKUP(Q4_2025[[#This Row],[Artikelnr]],Artikel_prijzen[Artnr],Artikel_prijzen[Prijs 2025],"") -> 106.8625 | K12: =IF(Q4_2025[[#This Row],[Artikelprijs]]<>"",IF(Q4_2025[[#This Row],[Stuksprijs]]=Q4_2025[[#This Row],[Artikelprijs]],"Prijs gelijk","Prijs wijkt af"),"") -> Prijs wijkt af | L12: =IF(Q4_2025[[#This Row],[Relatiekorting percentage]]=0, "Nvt", IF(Q4_2025[[#This Row],[Brutobedrag 2]] < Q4_2025[[#This Row],[Bruto - Rel.korting]], "Nee", "Ja")) -> Nvt | M12: =IF(Q4_2025[[#This Row],[Artikelprijs]]<>"",Q4_2025[[#This Row],[Artikelprijs]],Q4_2025[[#This Row],[Stuksprijs]]) -> 106.8625 | N12: =Q4_2025[[#This Row],[Besteld]]*Q4_2025[[#This Row],[Prijs 2]] -> -106.8625 | O12: =IF(Q4_2025[[#This Row],[Brutobedrag 2]]<Q4_2025[[#This Row],[Bruto - Rel.korting]],Q4_2025[[#This Row],[Brutobedrag 2]],Q4_2025[[#This Row],[Brutobedrag 2]]*(100-Q4_2025[[#This Row],[Relatiekorting percentage]])/100) -> -106.8625
A13: 100% Auto Live - 2025.xls | B13: 5022013 | C13: Power supply 6 kW (incl. CEE 32A & Power Consumption) 2d | D13: 1 | E13: 317.69 | F13: 317.69 | G13: 317.69 | H13: 0 | I13: =_xlfn.XLOOKUP(Q4_2025[[#This Row],[Artikelnr]],Artikel_prijzen[Artnr],Artikel_prijzen[Groep],"") -> Elektra | J13: =_xlfn.XLOOKUP(Q4_2025[[#This Row],[Artikelnr]],Artikel_prijzen[Artnr],Artikel_prijzen[Prijs 2025],"") -> 252.35 | K13: =IF(Q4_2025[[#This Row],[Artikelprijs]]<>"",IF(Q4_2025[[#This Row],[Stuksprijs]]=Q4_2025[[#This Row],[Artikelprijs]],"Prijs gelijk","Prijs wijkt af"),"") -> Prijs wijkt af | L13: =IF(Q4_2025[[#This Row],[Relatiekorting percentage]]=0, "Nvt", IF(Q4_2025[[#This Row],[Brutobedrag 2]] < Q4_2025[[#This Row],[Bruto - Rel.korting]], "Nee", "Ja")) -> Nvt | M13: =IF(Q4_2025[[#This Row],[Artikelprijs]]<>"",Q4_2025[[#This Row],[Artikelprijs]],Q4_2025[[#This Row],[Stuksprijs]]) -> 252.35 | N13: =Q4_2025[[#This Row],[Besteld]]*Q4_2025[[#This Row],[Prijs 2]] -> 252.35 | O13: =IF(Q4_2025[[#This Row],[Brutobedrag 2]]<Q4_2025[[#This Row],[Bruto - Rel.korting]],Q4_2025[[#This Row],[Brutobedrag 2]],Q4_2025[[#This Row],[Brutobedrag 2]]*(100-Q4_2025[[#This Row],[Relatiekorting percentage]])/100) -> 252.35
... A2088: WK Handbal - 2025.xls | B2088: 5030226 | C2088: Ophangpunt t.b.v. takel tot 500kg | D2088: 2 | E2088: 159.65 | F2088: 319.3 | G2088: 319.3 | H2088: 0 | I2088: =_xlfn.XLOOKUP(Q4_2025[[#This Row],[Artikelnr]],Artikel_prijzen[Artnr],Artikel_prijzen[Groep],"") -> Rigging | J2088: =_xlfn.XLOOKUP(Q4_2025[[#This Row],[Artikelnr]],Artikel_prijzen[Artnr],Artikel_prijzen[Prijs 2025],"") -> 155 | K2088: =IF(Q4_2025[[#This Row],[Artikelprijs]]<>"",IF(Q4_2025[[#This Row],[Stuksprijs]]=Q4_2025[[#This Row],[Artikelprijs]],"Prijs gelijk","Prijs wijkt af"),"") -> Prijs wijkt af | L2088: =IF(Q4_2025[[#This Row],[Relatiekorting percentage]]=0, "Nvt", IF(Q4_2025[[#This Row],[Brutobedrag 2]] < Q4_2025[[#This Row],[Bruto - Rel.korting]], "Nee", "Ja")) -> Nvt | M2088: =IF(Q4_2025[[#This Row],[Artikelprijs]]<>"",Q4_2025[[#This Row],[Artikelprijs]],Q4_2025[[#This Row],[Stuksprijs]]) -> 155 | N2088: =Q4_2025[[#This Row],[Besteld]]*Q4_2025[[#This Row],[Prijs 2]] -> 310 | O2088: =IF(Q4_2025[[#This Row],[Brutobedrag 2]]<Q4_2025[[#This Row],[Bruto - Rel.korting]],Q4_2025[[#This Row],[Brutobedrag 2]],Q4_2025[[#This Row],[Brutobedrag 2]]*(100-Q4_2025[[#This Row],[Relatiekorting percentage]])/100) -> 310
A2089: Totaal | F2089: =SUBTOTAL(109,Q4_2025[Brutobedrag]) -> 1082981 | G2089: =SUBTOTAL(109,Q4_2025[Bruto - Rel.korting]) -> 1006684.4 | N2089: =SUBTOTAL(109,Q4_2025[Brutobedrag 2]) -> 931222.62 | O2089: =SUBTOTAL(109,Q4_2025[Bruto-Rel. korting 2]) -> 869160.47

Sheet Q4 Provisie
B1: Provisie berekening Q4 2025
B4: Provisie | C4: Percentage | D4: Omzet | E4: Provisie | G4: VERREKENING: | H4: Omzet voor het jaar | I4: =D9 -> 3726363.7 | L4: Uitbetaalde omzet provisie
B5: Elektra | C5: 0.23 | D5: =C39 -> 331798.32 | E5: =C5*D5 -> 76313.615 | L5: Kwartaal | M5: Provisie
B6: Rigging | C6: 0.16 | D6: =D39 -> 267991.9 | E6: =C6*D6 -> 42878.704 | G6: t/m €1.000.000 | H6: 0.05 | I6: 1000000 | J6: =H6*I6 -> 50000 | L6: Omzet Q1 | M6: ='Q1 Provisie'!E8 -> 56958.835
B7: AV | C7: 0.15 | D7: =E39 -> 33955.25 | E7: =C7*D7 -> 5093.2875 | G7: €1.000.001 t/m 2 mln | H7: 0.065 | I7: 1000000 | J7: =H7*I7 -> 65000 | L7: Omzet Q2 | M7: ='Q2 Provisie '!E8 -> 56817.667
B8: Omzet Q3 | C8: 0.05 | D8: =G39 -> 869160.47 | E8: =D8*C8 -> 43458.024 | G8: €2.000.001 > | H8: 0.08 | I8: =I4-2000000 -> 1726363.7 | J8: =H8*I8 -> 138109.1 | L8: Omzet Q3 | M8: ='Q3 Provisie'!E8 -> 29083.659
B9: Omzet voor het jaar | D9: ='Q3 Provisie'!D9+'Q4 Provisie'!D8 -> 3726363.7 | G9: Totale omzet provisie | I9: =SUM(I6:I8) -> 3726363.7 | J9: =SUM(J6:J8) -> 253109.1 | L9: Omzet Q4 | M9: =E8 -> 43458.024
B10: Omzetstaffels 6,5% en 8% worden in Q4 verrekend | G10: Uitbetaalde omzet provisie | J10: =M10*-1 -> -186318.18 | L10: Totaal | M10: =SUM(M6:M9) -> 186318.18
B11: TOTALE PROVISIE | E11: =SUM(E5:E10) -> 167743.63 | G11: Omzetstaffel provisie te betalen | J11: =SUM(J9:J10) -> 66790.911
B14: Evenementen Q4 2025 | C14: Elektra omzet | D14: Rigging omzet | E14: AV omzet | F14: Geen groep omzet | G14: Totaal Omzet | H14: Elektra provisie | I14: Rigging provisie | J14: AV Provisie
